Workbook

Sheet Dashboard
B2: GABINETE DO VEREADOR FLÁVIO VALLE
B4: PAINEL | T4: ACERVO
C5: Data | E5: Agendas Realizadas | G5: Indicações Parl. Enviadas | I5: Medalhas 2025 | M5: Projetos Protocolados | O5: Total Imprensa | Q5: Base Contatos | U5: MATERIAL GRÁFICO | W5: APRESENTAÇÕES | Y5: PROJETOS | AA5: LEIS SANCIONADAS | AC5: ESTUDOS
C6: =TODAY() -> 46083 | E6: =counta(Agendas!A:A) -> 1883 | G6: =COUNTA('Indicações'!C:C) -> 659 | J6: Pedro Ernesto | K6: 45780 | M6: =COUNTA('Proposições legislativas'!B3:B1017) -> 63 | O6: =counta('Assessoria de Imprensa'!A:A) -> 292 | Q6: 18308 | U6: PLACA CARDOSÃO | W6: ='Apresentações'!G2 -> RIO EM ORDEM | Y6: PROJETO VAGA VIVA | AA6: LEI CORRIDA VERA CRUZ | AC6: Custo do antissemitismo
J7: Chiquinha Gonzaga | K7: 45718 | U7: ESTATUTO DA ORLA | W7: ='Apresentações'!G3 -> PLANEJAMENTO COMUNICAÇÃO | Y7: PROJETO CARDOSÃO NATUREZA IMATERIAL | AA7: LEI COMPLEMENTAR INTERVENÇÃO RISCO ESTRUTURAL | AC7: Relevância da educação para economia
J8: São Francisco | K8: 45780 | U8: FEST RIO | W8: ='Apresentações'!G4 -> DECK RIO | Y8: PROJETO CARDOSÃO INTERESSE CULTURAL | AA8: LEI PADARIA IPANEMA | AC8: Nota sobre regulamentação do Airbnb
C9: Dias de mandato | E9: Gab. Itinerante | G9: Moções Entregues | J9: Título de Cidadão | K9: 45718 | M9: Leis Sancionadas | O9: Posts Instagram | Q9: Atendimentos | U9: ORLA ORDENADA | W9: ='Apresentações'!G5 -> ISS CONSERVAÇÃO | Y9: PROJETO CIRCUITO CARIOCA INTERESSE CULTURAL | AA9: LEI DIA DO COMBATE AO ANTISSEMITISMO | AC9: Impacto da implementação do BRT
C10: =DAYS(C6,"01/01/2025") -> 425 | E10: =COUNTIF('Gabinete Itinerante'!E:E,'Gabinete Itinerante'!E2) -> 16 | G10: =counta('Moções'!A:A) -> 403 | J10: Título Esportivo | K10: 45658 | M10: =COUNTIF('Proposições legislativas'!B:B,'Tabelas e Gráficos'!A21) -> 17 | O10: =COUNTA('Comunicação Digital'!E:E) -> 368 | Q10: 1503 | U10: ADESIVO GABINETE | W10: ='Apresentações'!G6 -> TURISMO - VISIT RIO | Y10: PROJETO CIRCUITO CARIOCA NATUREZA IMATERIAL | AA10: LEI CARDOSÃO NATUREZA IMATERIAL | AC10: Impacto econômico do turismo no Rio de Janeiro
U11: ADESIVOS ORLA | W11: ='Apresentações'!G7 -> 100 DIAS DE MANDATO | Y11: PROJETO DEFINIÇÃO ANTISSEMITISMO | AA11: LEI CARDOSÃO INTERESSE CULTURAL | AC11: Panorama dos acidentes de trânsito
U12: ADESIVOS AIRBNB | W12: ='Apresentações'!G8 -> AUDIÊNCIA PÚBLICA: REGULAMENTAÇÃO DO SERVIÇO DE LOCAÇÃO POR TEMPORADA | Y12: PROJETO SAMBANTERO CALENDÁRIO DA CIDADE | AA12: LEI SISTEMA DE ÁREA AZUL DIGITAL | AC12: Segurança Presente
U13: BALCÃO STAND | W13: ='Apresentações'!G9 -> REVIVA ORLA | Y13: PROJETO SAMBANTERO NATUREZA IMATERIAL | AA13: LEI CIRCUITO CARIOCA NATUREZA IMATERIAL | AC13: Cassinos e jogos de azar
B14: INDICADORES | U14: CADERNETA LIDERA | W14: ='Apresentações'!G10 -> TURISMO - CONSELHO DA ORLA | Y14: PROJETO DIA DO COMBATE AO ANTISSEMITISMO | AA14: LEI SAMBANTERO CALENDÁRIO DA CIDADE | AC14: Corridas de rua
C15: AGENDAS | U15: ROTEIRO HISTÓRICO CULTURAL JUDAICO | W15: ='Apresentações'!G11 -> RIO: CAPITAL DO TURISMO NO BRASIL | Y15: PROJETO CAMPANHA MUNICIPAL PARA PROMOÇÃO DE ESTACIONAMENTO REGULAR | AA15: LEI DIA DA AMIZADE BRASIL-ISRAEL NO CALENDÁRIO | AC15: Custo econômico da violência
U16: COLETE | W16: ='Apresentações'!G12 -> LIDERA RIO | O PAPEL DO LEGISLATIVO NA CONSTRUÇÃO DO ORÇAMENTO PÚBLICO | Y16: PROJETO DECK RIO | AA16: LEI NOME DO ANDRÉ DO VALLE A UNIDADE DE ENSINO | AC16: Megaeventos esportivos
U17: CORDÃO VERSO | W17: ='Apresentações'!G13 -> A IMPORTÂNCIA DOS JUDEUS NA POLÍTICA CARIOCA | Y17: PROJETO ISS CONSERVAÇÃO | AA17: LEI COMLURB PATRIMÔNIO CULTURAL | AC17: Turismo e capitalidade
U18: CORDÃO FRENTE | W18: ='Apresentações'!G14 -> AUDIÊNCIA PÚBLICA: O RIO E SUAS ORLAS UM PATRIMÔNIO EM DISCUSSÃO | Y18: PROJETO TÍTULO DE CIDADÃO HONORÁRIO PAULO HENRIQUE GANSO | AA18: LEI NOME DE MARIANGELES IBARRA MAIA A LOGRADOURO OU EQUIPAMENTO PÚBLICO | AC18: Conselhos fiscais
U19: DOBRA CARTEIRA | W19: ='Apresentações'!G15 -> LIDERA RIO | Y19: PROJETO TÍTULO DE CIDADÃO HONORÁRIO EDUARDO MANEIRA | AA19: LEI CIDADE SAN SEBASTIAN COMO CIDADE-IRMÃ | AC19: Motivos para aprovar o empréstimo
U20: FLYER MANDATO PARTICIPATIVO | W20: ='Apresentações'!G16 -> AQUI TEM CEP | Y20: PROJETO SERVIÇOS DE ENTREGA | AA20: LEI DIA DE IEMANJÁ DO ARPOADOR | AC20: Orçamento 2024 (LDO 2026)
U21: ILUSTRADOR CANETA PLÁSTICA | W21: ='Apresentações'!G17 -> LIDERA RIO | Y21: PROJETO POLUIÇÃO SONORA | AA21: LEI DIA DE IEMANJÁ DO ARPOADOR NO CALENDÁRIO | AC21: VLT/BRT
U22: MATEIROS ADESIVOS | W22: ='Apresentações'!G18 -> ORLA QUE QUEREMOS | Y22: PROJETO COMERCIALIZAÇÃO DE ANIMAIS | AA22: LEI VEREADOR JUVENIL
U23: ROTEIRO HISTÓRICO CULTURAL JUDAICO | W23: ='Apresentações'!G19 -> WORKSHOP DE MOBILIZAÇÃO & COMUNICAÇÃO POLÍTICA | Y23: PROJETO CONSELHO FISCAL INDEPENDENTE
U24: PIRULITO FRENTE | W24: ='Apresentações'!G20 -> JUNTOS RENOVANDO O RIO: UM MANDATO COLETIVO | Y24: PROJETO TOMBAMENTO IMÓVEL FLAMENGO
U25: PIRULITO VERSO | W25: ='Apresentações'!G21 -> DINÂMICA DE ELABORAÇÃO DE PROJETO DE LEI MUNICIPAL | Y25: PROJETO MIRANTE DO PEDRÃO
U26: REVISTA A5 | W26: ='Apresentações'!G22 -> PROJETO ESTATUTO DA ORLA | Y26: PROJETO SELO DE RELEVÂNCIA TURÍSTICA
U27: REVISTA A5 SEIS MESES | W27: ='Apresentações'!G23 | Y27: PROJETO ESTATUTO DA ORLA
U28: SEU VEREADOR CARTÃO | W28: ='Apresentações'!G24 | Y28: PROJETO MUNICIPALIZAÇÃO FLORESTA DA TIJUCA
U29: WINDBANNER | W29: ='Apresentações'!G25 | Y29: PROJETO NATURALIZAÇÃO DA LAGOA (PARQUE DOS PATINS)
C30: PRODUÇÃO LEGISLATIVA | W30: ='Apresentações'!G26 | Y30: PROJETO NATURALIZAÇÃO LAGOA (PARQUE CANTAGALO)
W31: ='Apresentações'!G27 | Y31: PROJETO ARNALDO QUINTELA INTERESSE TURÍSTICO
W32: ='Apresentações'!G28 | Y32: PROJETO BAIXO LAGOA
W33: ='Apresentações'!G29 | Y33: PROJETO VENDAS E LOCAÇÕES BIKE ELÉTRICA
W34: ='Apresentações'!G30 | Y34: PROJETO PROGRAMA ADOÇÃO CARIOCA
W35: ='Apresentações'!G31 | Y35: PROJETO RIO CELEBRA
W36: ='Apresentações'!G32 | Y36: PROJETO CRISTO REDENTOR
W37: ='Apresentações'!G33 | Y37: PROJETO ENTREGA DE PRODUTOS NA ORLA
W38: ='Apresentações'!G34 | Y38: PROJETO TÍTULO DE CIDADÃO HONORÁRIO ILAN GOLDFAJN
W39: ='Apresentações'!G35 | Y39: PROJETO ARNALDO QUINTELA (HORÁRIO DE FUNCIONAMENTO)
W40: ='Apresentações'!G36 | Y40: PROJETO ROTEIRO TURÍSTICO JUDAICO
W41: ='Apresentações'!G37 | Y41: PROJETO FINANÇAS IDOSOS
W42: ='Apresentações'!G38 | Y42: PROJETO ENSINO SOBRE O HOLOCAUSTO
... W45: ='Apresentações'!G41 | Y45: PROJETO AEIU E AEIT ARPOADOR
Y46: PROJETO IPTU HOTÉIS
Y47: PROJETO CORRIDA VERA CRUZ
Y48: PROJETO RESTAURANTE AMARELINHO
Y49: PROJETO RESTAURANTE TRAPIÁ
Y50: PROJETO PROTEÇÃO ENTIDADES
Y51: PROJETO PADARIA IPANEMA
Y52: PROJETO SAMBOTICA
C72: ESTUDOS
C92: INDICAÇÕES PARLAMENTARES | W92: ='Apresentações'!G42
C113: IMPRENSA
Y131: ='Proposições legislativas'!F66
Y132: ='Proposições legislativas'!F67
Y133: ='Proposições legislativas'!F68
Y134: ='Proposições legislativas'!F69
Y135: ='Proposições legislativas'!F70
Y136: ='Proposições legislativas'!F71
C150: REDES SOCIAIS

Sheet Agendas
A1: Título | B1: Descrição | C1: Local | D1: Começo | E1: Convidados | F1: Mês | H1: Classificação
A2: Pré matrícula mestrado FGV | D2: 45644 | F2: =TEXT(D2, "mm/yyyy") -> 12/2024 | H2: Mestrado
A3: Posse do Prefeito, Vice-prefeito e Vereadores | B3: *Amigo e amiga*, *O convite da POSSE do Prefeito, Vice-prefeito e Vereadores, marcada para o dia 01 de janeiro/2025, às 09h30min, no Plenário Teotônio Villela, com as devidas orientações e as 4 pulseiras para os convidados terem acesso à galeria e ainda as 3 pulseiras para os convidados terem acesso ao Salão Nobre, já estão à disposição na Presidência.* Verinha à disposição | C3: Câmara Municipal do Rio de Janeiro, Praça Floriano - Centro, Rio de Janeiro - RJ, 20031-050, Brasil | D3: 45658.396 | E3: flaviogvalle@gmail.com | F3: =TEXT(D3, "mm/yyyy") -> 01/2025 | H3: Eventos
A4: Reunião - Organização GVFV | C4: Câmara Municipal do Rio de Janeiro, Praça Floriano - Centro, Rio de Janeiro - RJ, 20031-050, Brasil | D4: 45659.438 | E4: lucasrosa.arq@gmail.com;lfdsbr@gmail.com | F4: =TEXT(D4, "mm/yyyy") -> 01/2025 | H4: Reunião Interna/Planejamento
A5: Reunião Política | C5: Câmara Municipal do Rio de Janeiro, Praça Floriano - Centro, Rio de Janeiro - RJ, 20031-050, Brasil | D5: 45659.542 | E5: lucasrosa.arq@gmail.com;flaviogvalle@gmail.com;leomartins.rzs@gmail.com;monteirojpf@gmail.com;gisellygazevedo@gmail.com;lfdsbr@gmail.com | F5: =TEXT(D5, "mm/yyyy") -> 01/2025 | H5: Reunião Interna/Planejamento
A6: Treinamento Wrike | B6: Informações Evento Data: 02/01 Horário: 14:30h Local: Gabinete 506 Observações: Treinamento Plataforma Wrike Responsável: Solicitado p/ FV em 29/12 | C6: Câmara Municipal do Rio de Janeiro, Praça Floriano - Centro, Rio de Janeiro - RJ, 20031-050, Brasil | D6: 45659.604 | E6: lucasrosa.arq@gmail.com;otaviobopp@gmail.com;leonardosolabloise@gmail.com;lauranalbq@gmail.com;viniciusmmg@gmail.com;juliagardel2@gmail.com;pedroangelito22@gmail.com;contato.lucasfajardo@gmail.com;flaviogvalle@gmail.com;andrew.mata.2022@gmail.com;leomartins.rzs@gmail.com;monteirojpf@gmail.com;crislobo@gmail.com;lfdsbr@gmail.com;lima.saramoreira@gmail.com;biarsbz@gmail.com;rafaazamor@gmail.com;matheus.ocn@gmail.com;gisellygazevedo@gmail.com;martinsmt1000@gmail.com | F6: =TEXT(D6, "mm/yyyy") -> 01/2025 | H6: Reunião Interna/Planejamento
A7: Reunião - Marcel Balassiano | B7: Informado p/ Léo Fernandes em 01/01. | C7: Câmara Municipal do Rio de Janeiro, Praça Floriano - Centro, Rio de Janeiro - RJ, 20031-050, Brasil | D7: 45659.688 | E7: flaviogvalle@gmail.com;lfdsbr@gmail.com;marcel.balassiano@fgv.br | F7: =TEXT(D7, "mm/yyyy") -> 01/2025 | H7: Reunião Executivo
A8: Reunião - Luiz Murillo Tobias | B8: Informado p/ Leo Fernandes em 02/01 | C8: Câmara Municipal do Rio de Janeiro, Praça Floriano - Centro, Rio de Janeiro - RJ, 20031-050, Brasil | D8: 45660.458 | E8: flaviogvalle@gmail.com;lfdsbr@gmail.com | F8: =TEXT(D8, "mm/yyyy") -> 01/2025 | H8: Reunião Executivo
A9: Reunião - Bruno Ramos | B9: Informações Evento Data: 03/01 Horário: 10h Local: Gabinete 506 Observações: Solicitado p/ FV em 02/01 | C9: Câmara Municipal do Rio de Janeiro, Praça Floriano - Centro, Rio de Janeiro - RJ, 20031-050, Brasil | D9: 45660.542 | E9: flaviogvalle@gmail.com;brfbruno2@gmail.com | F9: =TEXT(D9, "mm/yyyy") -> 01/2025 | H9: Reunião Executivo
A10: Entrevista Estagiário - Jiskya | D10: 45663.604 | E10: torresjiskya@gmail.com;flaviogvalle@gmail.com | F10: =TEXT(D10, "mm/yyyy") -> 01/2025 | H10: Reunião Interna/Planejamento
A11: Entrevista Estagiário - Kelvin | D11: 45663.625 | E11: kelvinmafra1@gmail.com;flaviogvalle@gmail.com | F11: =TEXT(D11, "mm/yyyy") -> 01/2025 | H11: Reunião Interna/Planejamento
A12: Entrevista Estagiário - Renato | D12: 45663.646 | E12: leonardo.moog@hotmail.com;flaviogvalle@gmail.com;renato-908070@hotmail.com | F12: =TEXT(D12, "mm/yyyy") -> 01/2025 | H12: Reunião Interna/Planejamento
A13: Reunião - Sec. Lucas Padilha | B13: *MARCADO* Reunião com vereador Flavio Valle, segunda-feira, 6 de jan. · 17:30 Câmara Municipal do Rio de Janeiro, Praça Floriano | C13: Câmara Municipal do Rio de Janeiro, Praça Floriano - Centro, Rio de Janeiro - RJ, 20031-050, Brasil | D13: 45663.729 | E13: ce.lopess57@gmail.com;flaviogvalle@gmail.com | F13: =TEXT(D13, "mm/yyyy") -> 01/2025 | H13: Reunião Executivo
A14: Entrevista Estagiário - Lucas Vidal | D14: 45664.583 | E14: lucasfvida@gmail.com;leonardo.moog@hotmail.com;flaviogvalle@gmail.com | F14: =TEXT(D14, "mm/yyyy") -> 01/2025 | H14: Reunião Interna/Planejamento
A15: Reunião Diego Vaz + Vereador Flávio Valle | B15: Agendado: Reunião Diego Vaz + Vereador Flávio Valle Quarta-feira, 07 de Janeiro de 2025. 18h Local: Secretaria de Conservação (Rua Maia Lacerda, 167- Estácio - 5° andar) | C15: R. Maia de Lacerda, 167 - Estácio, Rio de Janeiro - RJ, 20250-001, Brasil | D15: 45664.75 | E15: flaviogvalle@gmail.com | F15: =TEXT(D15, "mm/yyyy") -> 01/2025 | H15: Reunião Executivo
A16: Reunião Jockey e IRPH | B16: Informações Evento Data: 08/01 Horário: 11:30H Local: Rua Gago Coutinho, n° 52 3º andar - Laranjeiras Observações: Boa Tarde Lucas! A reunião será no dia 08/01(4ªfeira) às 11h no IRPH (Rua Gago Coutinho, n° 52 3º andar - Laranjeiras.) Att, Ariele Contato: Enviado p/ FV em 23/12 | C16: R. Gago Coutinho, 52 - Laranjeiras, Rio de Janeiro - RJ, 22221-070, Brasil | D16: 45665.479 | E16: flaviogvalle@gmail.com | F16: =TEXT(D16, "mm/yyyy") -> 01/2025 | H16: Reunião Executivo
A17: Reunião - Edmilson (Educação) | B17: Informações Evento Data: 08/01 Horário: 13:30h Local: Câmara Municipal do Rio de Janeiro - Gabinete 506 Observações: Pauta relacionada a continuidade do trabalho na Educação Contato: +55 21 98155-6601 | C17: Câmara Municipal do Rio de Janeiro, Praça Floriano - Centro, Rio de Janeiro - RJ, 20031-050, Brasil | D17: 45665.562 | E17: flaviogvalle@gmail.com | F17: =TEXT(D17, "mm/yyyy") -> 01/2025 | H17: Reunião Executivo
A18: Jantar - Edu Goldenberg + Joyce Trindade + Lucas Padilha | B18: Informações Evento Data: 08/01 Horário: 20h Local: Casa do Edu Goldenberg Rua Domingos Ferreira 178, apto. 702. Observações: Levar vinho Responsável: Léo Fernandes | C18: R. Domingos Ferreira, 178 - apto 702 - Copacabana, Rio de Janeiro - RJ, 22050-012, Brasil | D18: 45665.833 | E18: flaviogvalle@gmail.com;lfdsbr@gmail.com | F18: =TEXT(D18, "mm/yyyy") -> 01/2025 | H18: Compromissos Pessoais FV
A19: Reunião - Otávio Leite | B19: Informações Evento Data: 09/01 Horário: 09:30h Local: Marquês de Abrantes, 99/10º Andar. Observações: Agenda/bate-papo sobre turismo. Responsável: Léo Fernandes | C19: R. Marquês de Abrantes, 99 - Flamengo, Rio de Janeiro - RJ, 22230-061, Brasil | D19: 45666.396 | E19: flaviogvalle@gmail.com;lfdsbr@gmail.com | F19: =TEXT(D19, "mm/yyyy") -> 01/2025 | H19: Reunião Atendimento
A20: Reunião com Dr Carlos Ivan e Dr Sérgio Werlang | B20: Reunião com Dr Carlos Ivan e Dr Sérgio Werlang Data : 09/01/2025 Horário : 11h30 Local : FGV sede Praia de Botafogo, 190 - Botafogo - 12° andar | C20: Fundação Getulio Vargas, Praia de Botafogo, 190 - Botafogo, Rio de Janeiro - RJ, 22250-145, Brasil | D20: 45666.479 | E20: flaviogvalle@gmail.com | F20: =TEXT(D20, "mm/yyyy") -> 01/2025 | H20: Reunião Atendimento
A21: Reunião - Fabinho | B21: Informações Evento Data: 09/01 Horário: 16:30h Local: Gabinete 506 Observações: Solicitado p/ Fabinho para tratar de assuntos pessoais. | C21: Câmara Municipal do Rio de Janeiro, Praça Floriano - Centro, Rio de Janeiro - RJ, 20031-050, Brasil | D21: 45666.625 | E21: fabiocampellobjj@gmail.com;flaviogvalle@gmail.com | F21: =TEXT(D21, "mm/yyyy") -> 01/2025 | H21: Reunião Interna/Planejamento
A22: Reunião - Ana Ribeiro | B22: Informações Evento Data: 09/01 Horário: 15:30h Local: Câmara Municipal do Rio de Janeiro, Praça Floriano - Centro Contato: Solicitado p/ João | C22: Câmara Municipal do Rio de Janeiro, Praça Floriano - Centro, Rio de Janeiro - RJ, 20031-050, Brasil | D22: 45666.646 | E22: viniciusmmg@gmail.com;flaviogvalle@gmail.com;leomartins.rzs@gmail.com;monteirojpf@gmail.com | F22: =TEXT(D22, "mm/yyyy") -> 01/2025 | H22: Reunião Interna/Planejamento
A23: Reunião - Rafael Azamor | C23: Câmara Municipal do Rio de Janeiro, Praça Floriano - Centro, Rio de Janeiro - RJ, 20031-050, Brasil | D23: 45666.708 | E23: rafaazamor@gmail.com;flaviogvalle@gmail.com | F23: =TEXT(D23, "mm/yyyy") -> 01/2025 | H23: Reunião Interna/Planejamento
A24: Evento: Happy Hour Maravalley | B24: Informações Evento Data: 09/01 Horário: 17h Local: Porto Maravalley, Av. Prof. Pereira Reis, 76 Observações: Gente, o Marcel Balassiano, subsecretário de desenvolvimento econômico e inovação da Prefeitura, pediu para eu repassar esse convite a vocês, para quem tiver interesse em comparecer amanhã. Contato: Responsável: Leonardo Moog | C24: Porto Maravalley, Av. Prof. Pereira Reis, 76 - Santo Cristo, Rio de Janeiro - RJ, 20220-800, Brasil | D24: 45666.75 | E24: leonardo.moog@hotmail.com;flaviogvalle@gmail.com;lfdsbr@gmail.com | F24: =TEXT(D24, "mm/yyyy") -> 01/2025 | H24: Eventos
A25: Jantar | D25: 45666.854 | E25: flaviogvalle@gmail.com | F25: =TEXT(D25, "mm/yyyy") -> 01/2025 | H25: Compromissos Pessoais FV
A26: Gravação Vídeo Chuvas | C26: R. Mena Barreto, 129 - Botafogo, Rio de Janeiro - RJ, 22271-100, Brasil | D26: 45667.396 | E26: contato.lucasfajardo@gmail.com;flaviogvalle@gmail.com;gisellygazevedo@gmail.com | F26: =TEXT(D26, "mm/yyyy") -> 01/2025 | H26: Comunicação/Imprensa
A27: Café - Flavio + Andrew | D27: 45667.458 | E27: flaviogvalle@gmail.com | F27: =TEXT(D27, "mm/yyyy") -> 01/2025 | H27: Reunião Interna/Planejamento
A28: Gravação Vídeo Chuvas | C28: diversos locais | D28: 45667.5 | E28: contato.lucasfajardo@gmail.com;flaviogvalle@gmail.com;gisellygazevedo@gmail.com | F28: =TEXT(D28, "mm/yyyy") -> 01/2025 | H28: Comunicação/Imprensa
A29: Cláudio | C29: Confeitaria Kurt - Doces e Tortas, R. Gen. Urquiza, 117 B - Leblon, Rio de Janeiro - RJ, 22431-040, Brasil | D29: 45667.583 | F29: =TEXT(D29, "mm/yyyy") -> 01/2025 | H29: Reunião Atendimento
A30: Visita ao Hospital Oftalmológico com Almyr Sabrosa | B30: Informações Evento Data: 10/01 Horário: 14:30h Local: Rio Vision - Hospital oftalmológico, R. Prudente de Morais, 1276 Observações: Ida ao hospital oftalmológico com Almyr Sabrosa, para agradecimento e conhecer. Responsável: Bruno Ramos | C30: Rio Vision - Hospital oftalmológico, R. Prudente de Morais, 1276 - Ipanema, Rio de Janeiro - RJ, 22420-042, Brasil | D30: 45667.604 | E30: flaviogvalle@gmail.com;mrpaulobarros@gmail.com;brfbruno2@gmail.com | F30: =TEXT(D30, "mm/yyyy") -> 01/2025 | H30: Externa/Rua
A31: Celebração da Posse da Nova Diretoria da ARI | B31: Informações Evento Data: 10/01 Horário: A partir das 18h Melhor horário: 18:30h Local: R. Gen. Severiano, 170 - Botafogo Observações: A associação Religiosa Israelita - ARI tem a honra de convidas V.Sa. para a Celebração da Posse da Nova Diretoria e do Conselho Diretor para o Biênio 2025/26, no dia 10 de janeiro próximo, a partir das 18h, quando serão comemorados também os 83 anos de fundação da instituição com um Kabalat Shabat especial, seguido de um Lechaim comunitário no Salão Nobre. Contamos com sua presença para juntos celebrarmos mais este marco em nossa trajetória. Para confirmar sua presença, por favor, entre em contato por e-mail: meireles@aririo.org.br, ou telefones (21) 97650-9039; (21) 97641-6234; (21) 2156-0444, até as 12h de sexta-feira, 10 de janeiro. Contato: Recebido do Gabinete do Prefeito em 07/01 Responsável: Rafael Azamor | C31: R. Gen. Severiano, 170 - Botafogo, Rio de Janeiro - RJ, 22290-040, Brasil | D31: 45667.771 | E31: rafaazamor@gmail.com;flaviogvalle@gmail.com;lfdsbr@gmail.com | F31: =TEXT(D31, "mm/yyyy") -> 01/2025 | H31: Comunidade Judaica
A32: Conversa com a Associação de Moradores da Chácara do Céu | C32: Estr. do Vidigal, 555 - Vidigal, Rio de Janeiro - RJ, 22450-230, Brasil | D32: 45668.417 | E32: lucasjb27@hotmail.com;bernardorubiao@gmail.com;marcosbarato177@gmail.com;gabrielleal1995@gmail.com;joycenani.rio@gmail.com;leonardolopes@llfilm.com.br;flaviogvalle@gmail.com;leomartins.rzs@gmail.com;monteirojpf@gmail.com;mrpaulobarros@gmail.com;subzonasul.imprensa@gmail.com | F32: =TEXT(D32, "mm/yyyy") -> 01/2025 | H32: Externa/Rua
A33: Visita Terreirão do samba c/ associação dos barraqueiros | B33: Visita Terreirão do samba c/ associação dos barraqueiros - Chegada do Vereador Flavio Vale (Resp. agenda Marcelinho Doper) Sábado, 11 de janeiro⋅12:30 até 13:30 Terreirão do Samba Nelson Sargento R. Benedito Hipólito, 66 - Centro, Rio de Janeiro | C33: Terreirão do Samba Nelson Sargento, R. Benedito Hipólito, 66 - Centro, Rio de Janeiro - RJ, 20211-130, Brasil | D33: 45668.521 | E33: flaviogvalle@gmail.com | F33: =TEXT(D33, "mm/yyyy") -> 01/2025 | H33: Externa/Rua
A34: Descoberta da Matzeiva - Bernardo Griner | B34: Informações Evento Data: 12/01 Horário: 11h Local: Cemitério Israelita de Belford Roxo (Chevra Kadisha), Av. Automóvel Clube, 1921 - Jardim Gláucia, Belford Roxo Contato: Recebido p/ FV em 10/01 | C34: Cemitério Israelita de Belford Roxo (Chevra Kadisha), Av. Automóvel Clube, 1921 - Jardim Gláucia, Belford Roxo - RJ, 26196-030, Brasil | D34: 45669.458 | E34: rafaazamor@gmail.com;flaviogvalle@gmail.com | F34: =TEXT(D34, "mm/yyyy") -> 01/2025 | H34: Comunidade Judaica
A35: Reunião Márcio Ribeiro | D35: 45670.375 | F35: =TEXT(D35, "mm/yyyy") -> 01/2025 | H35: Reunião Legislativo
A36: Reunião Semanal - Comunicação e Imprensa | C36: Câmara Municipal do Rio de Janeiro, Praça Floriano - Centro, Rio de Janeiro - RJ, 20031-050, Brasil | D36: 45670.417 | E36: contato.lucasfajardo@gmail.com;flaviogvalle@gmail.com;monteirojpf@gmail.com;crislobo@gmail.com;gisellygazevedo@gmail.com;lfdsbr@gmail.com | F36: =TEXT(D36, "mm/yyyy") -> 01/2025 | H36: Reunião Interna/Planejamento
A37: Reunião Semanal - Pesquisa e Redação | C37: Câmara Municipal do Rio de Janeiro, Praça Floriano - Centro, Rio de Janeiro - RJ, 20031-050, Brasil | D37: 45670.438 | E37: lima.saramoreira@gmail.com;leonardo.moog@hotmail.com;pedroangelito22@gmail.com;flaviogvalle@gmail.com;monteirojpf@gmail.com;lfdsbr@gmail.com | F37: =TEXT(D37, "mm/yyyy") -> 01/2025 | H37: Reunião Interna/Planejamento
A38: Reunião Semanal - Atendimento | C38: Câmara Municipal do Rio de Janeiro, Praça Floriano - Centro, Rio de Janeiro - RJ, 20031-050, Brasil | D38: 45670.458 | E38: lauranalbq@gmail.com;flaviogvalle@gmail.com;andrew.mata.2022@gmail.com;monteirojpf@gmail.com;lfdsbr@gmail.com | F38: =TEXT(D38, "mm/yyyy") -> 01/2025 | H38: Reunião Interna/Planejamento
A39: Reunião Semanal - Gabinete | C39: Câmara Municipal do Rio de Janeiro, Praça Floriano - Centro, Rio de Janeiro - RJ, 20031-050, Brasil | D39: 45670.479 | E39: lucasrosa.arq@gmail.com;flaviogvalle@gmail.com;monteirojpf@gmail.com;lfdsbr@gmail.com | F39: =TEXT(D39, "mm/yyyy") -> 01/2025 | H39: Reunião Interna/Planejamento
A40: Fotos Equipe GVFV | B40: Comunicação irá fazer fotos individuais da equipe no gabinete. | C40: Câmara Municipal do Rio de Janeiro, Praça Floriano - Centro, Rio de Janeiro - RJ, 20031-050, Brasil | D40: 45670.562 | E40: otaviobopp@gmail.com;lucasrosa.arq@gmail.com;leonardosolabloise@gmail.com;leonardo.moog@hotmail.com;lauranalbq@gmail.com;viniciusmmg@gmail.com;juliagardel2@gmail.com;pedroangelito22@gmail.com;leonardolopes@llfilm.com.br;contato.lucasfajardo@gmail.com;leomartins.rzs@gmail.com;andrew.mata.2022@gmail.com;monteirojpf@gmail.com;crislobo@gmail.com;lfdsbr@gmail.com;lima.saramoreira@gmail.com;biarsbz@gmail.com;rafaazamor@gmail.com;matheus.ocn@gmail.com;mrpaulobarros@gmail.com;gisellygazevedo@gmail.com;martinsmt1000@gmail.com | F40: =TEXT(D40, "mm/yyyy") -> 01/2025 | H40: Comunicação/Imprensa
A41: Reabertura do Museu Nacional de Belas Artes | B41: Informações Evento Data: 13/01 Horário: 14h Local: Museu Nacional de Belas Artes, Av. Rio Branco, 199 - Centro Contato: Aline Ribeiro +55 21 99346-8433 em 07/01 Boa tarde, Lucas. Tudo bem? Meu nome é Aline Ribeiro e faço parte da equipe de comunicação do Museu Nacional de Belas Artes enquanto relações institucionais e eventos. Quem passou seu contato foi João Pedro a fim de convidarmos Flavio Valle para o evento que vamos realizar no próximo dia 13 de janeiro pelo aniversário de 88 anos do Museu. Como estamos em obras vai ser um soft opening para poucos convidados mas fazemos questão de ter por perto aqueles que sabemos que são de grande valia e importância para esse período de obras e transformações que o Museu vem passando rumo à sua reabertura. | C41: Museu Nacional de Belas Artes, Av. Rio Branco, 199 - Centro, Rio de Janeiro - RJ, 20040-008, Brasil | D41: 45670.583 | E41: flaviogvalle@gmail.com | F41: =TEXT(D41, "mm/yyyy") -> 01/2025 | H41: Eventos
A42: Reunião - Adriana Camargo | B42: Informações Evento Data: 13/01 Horário: 15:30h Local: CASS - 15° andar (Sala de Reunião do Schleder, procurar Laura) Contato: 21 98640-1547 | C42: Centro Administrativo São Sebastião - Cidade Nova, Rio de Janeiro - RJ, Brasil | D42: 45670.646 | E42: flaviogvalle@gmail.com | F42: =TEXT(D42, "mm/yyyy") -> 01/2025 | H42: Reunião Atendimento
A43: Reunião com Edinho | B43: Reunião com Ver. Flávio Valle Segunda-feira dia 13 de janeiro de 2025 • 17:00 até 18:00 Dom Marcos Barbosa, 2 andar | C43: Centro Administrativo São Sebastião - Cidade Nova, Rio de Janeiro - RJ, Brasil | D43: 45670.708 | E43: flaviogvalle@gmail.com;brfbruno2@gmail.com | F43: =TEXT(D43, "mm/yyyy") -> 01/2025 | H43: Reunião Executivo
A44: Conversa com a Associação de Moradores Morro Azul | C44: R. Paulo VI, 62 - Flamengo, Rio de Janeiro - RJ, 22230-080, Brasil | D44: 45671.375 | E44: lucasjb27@hotmail.com;bernardorubiao@gmail.com;marcosbarato177@gmail.com;joycenani.rio@gmail.com;yagodicarahy@gmail.com;flaviogvalle@gmail.com;leomartins.rzs@gmail.com;monteirojpf@gmail.com;subzonasul.imprensa@gmail.com | F44: =TEXT(D44, "mm/yyyy") -> 01/2025 | H44: Externa/Rua
A45: Visita a Obra do Guararapes | B45: Informações Evento Data: 09/01 Horário: 10:30h Local: Ladeira dos Guararapes - Cosme Velho Observações: Visita a Obra do Guararapes Contato: Agendado diretamente pelo Flávio c/ Fernanda Riourbe | C45: Ladeira dos Guararapes - Cosme Velho, Rio de Janeiro - RJ, 22241, Brasil | D45: 45671.438 | E45: flaviogvalle@gmail.com;leomartins.rzs@gmail.com;yagodicarahy@gmail.com | F45: =TEXT(D45, "mm/yyyy") -> 01/2025 | H45: Externa/Rua
A46: Buscar roupa | D46: 45671.479 | F46: =TEXT(D46, "mm/yyyy") -> 01/2025 | H46: Compromissos Pessoais FV
A47: Almoço c/ Adib + BR | B47: Informações Evento Data: 14/01 Horário: 12h Local: Restaurante VAMO - Av. Borges de Medeiros, 1111 - Lagoa Contato: Laura BR +55 21 98210-0622 Responsável: BR | C47: Av. Borges de Medeiros, 1111 - Leblon, Rio de Janeiro - RJ, 22430-041, Brasil | D47: 45671.5 | E47: flaviogvalle@gmail.com;brfbruno2@gmail.com | F47: =TEXT(D47, "mm/yyyy") -> 01/2025 | H47: Reunião Atendimento
A48: Reunião - João Marcello Barreto | B48: Informações Evento Data: 14/01 Horário: 14h Local: Estr. do Joá, 3336 - Joá (Sede da Orla Rio) Observações: Apresentar o Subprefeito ao João Marcello do Orla Rio. Contato: +55 21 99931-6177 | C48: Estr. do Joá, 3336 - Joá, Rio de Janeiro - RJ, 22611-022, Brasil | D48: 45671.583 | E48: bernardorubiao@gmail.com;flaviogvalle@gmail.com | F48: =TEXT(D48, "mm/yyyy") -> 01/2025 | H48: Reunião Atendimento
A49: Café c/ Dr. Rodrigo Lourega (Procurador Geral da Câmara) | B49: Informações Evento Data: 14/01 Horário: 15h30 Local: CMRJ Observações: Apresentar o Procurador Geral da Câmara (antigo Procurador Geral do Município). Responsável: Fabinho | C49: Câmara Municipal do Rio de Janeiro, Praça Floriano - Centro, Rio de Janeiro - RJ, 20031-050, Brasil | D49: 45671.646 | E49: fabiocampellobjj@gmail.com;flaviogvalle@gmail.com | F49: =TEXT(D49, "mm/yyyy") -> 01/2025 | H49: Reunião Legislativo
A50: Ligar Andrew Hancock | D50: 45671.667 | F50: =TEXT(D50, "mm/yyyy") -> 01/2025 | H50: Compromissos Pessoais FV
A51: Reuniao - Coronel Ludogero e Claudio Banda de Ipanema | B51: Informações Evento Data: 14/01 Horário: 17h Local: 23º Batalhão de Polícia Militar, R. Cap. César de Andrade, 119 - Leblon Observações: Reunião com Coronel Ludogero e Claudio Banda de Ipanema Contato: Ludogero +55 21 96477-8687 | C51: 23º Batalhão de Polícia Militar, R. Cap. César de Andrade, 119 - Leblon, Rio de Janeiro - RJ, 22431-010, Brasil | D51: 45671.729 | E51: flaviogvalle@gmail.com | F51: =TEXT(D51, "mm/yyyy") -> 01/2025 | H51: Reunião Atendimento
A52: Game Night com Lord of the Quiz | B52: Informações Evento Data: 14/01 Horário: 19h Local: Hillel Rio de Janeiro, R. Barão de Jaguaripe, 182 - Ipanema Observações: Além de board gamos à disposição, preparem-se para encarar o desafio do Lord of the Quiz, um game-show incrível com perguntar sobre cultura pop, além de concorrer a diversos prêmios. Contato: Enviado p/ FV em 09/01 | C52: Hillel Rio de Janeiro, R. Barão de Jaguaripe, 182 - Ipanema, Rio de Janeiro - RJ, 22421-000, Brasil | D52: 45671.792 | E52: flaviogvalle@gmail.com | F52: =TEXT(D52, "mm/yyyy") -> 01/2025 | H52: Comunidade Judaica
A53: Conversa com a Associação de Moradores do Vidigal | C53: Av. Presidente João Goulart, 735 - Vidigal, Rio de Janeiro - RJ, 22450-244, Brasil | D53: 45672.375 | E53: lucasjb27@hotmail.com;bernardorubiao@gmail.com;marcosbarato177@gmail.com;gabrielleal1995@gmail.com;joycenani.rio@gmail.com;flaviogvalle@gmail.com;leomartins.rzs@gmail.com;monteirojpf@gmail.com;subzonasul.imprensa@gmail.com | F53: =TEXT(D53, "mm/yyyy") -> 01/2025 | H53: Externa/Rua
A54: Estará acontecendo: Curso E-Câmara – Processo Administrativo | B54: Senhoras Vereadoras e Senhores Vereadores Comunico que a Câmara Municipal realizará o curso E-Câmara – Processo Administrativo – Noções Básicas, dia 15/01 de 10h às 13h, no Auditório, para os novos servidores dos gabinetes. A confirmação das inscrições será através dos ramais 1393 e 1033 ou pelo e-mail eslec@camara.rj.gov.br | C54: Câmara Municipal do Rio de Janeiro, Praça Floriano - Centro, Rio de Janeiro - RJ, 20031-050, Brasil | D54: 45672.417 | E54: lucasrosa.arq@gmail.com;flaviogvalle@gmail.com;lfdsbr@gmail.com | F54: =TEXT(D54, "mm/yyyy") -> 01/2025
A55: Visita ao Super Centro Carioca de Saúde | B55: Queridos, liguei hoje para o Deputado Dr. Daniel Soranz e fechei com ele na semana que vem uma visita de toda nossa equipe ao Super Centro Carioca de Saúde em Benfica seguido de uma palestra do Daniel sobre nosso sistema de saúde, para que todos conheçam os princípios básicos do SUS e da regulação do sistema. - Data: 15/01 às 11h - ⁠Local: Super Centro Carioca de Saúde - Benfica Conto com a presença de todos vocês. | C55: Super Centro Carioca de Saúde, R. Gen. Gustavo Cordeiro de Farias, 545 - Benfica, Rio de Janeiro - RJ, 20910-220, Brasil | D55: 45672.458 | E55: otaviobopp@gmail.com;lucasrosa.arq@gmail.com;leonardosolabloise@gmail.com;lauranalbq@gmail.com;viniciusmmg@gmail.com;juliagardel2@gmail.com;pedroangelito22@gmail.com;leonardolopes@llfilm.com.br;fabiocampellobjj@gmail.com;contato.lucasfajardo@gmail.com;leomartins.rzs@gmail.com;andrew.mata.2022@gmail.com;flaviogvalle@gmail.com;monteirojpf@gmail.com;crislobo@gmail.com;lfdsbr@gmail.com;lima.saramoreira@gmail.com;biarsbz@gmail.com;matheus.ocn@gmail.com;mrpaulobarros@gmail.com;gisellygazevedo@gmail.com | F55: =TEXT(D55, "mm/yyyy") -> 01/2025 | H55: Reunião Interna/Planejamento
A56: Cerimonia de Colocação da Mezuzá | C56: Câmara Municipal do Rio de Janeiro, Praça Floriano - Centro, Rio de Janeiro - RJ, 20031-050, Brasil | D56: 45672.625 | E56: rafaazamor@gmail.com;flaviogvalle@gmail.com | F56: =TEXT(D56, "mm/yyyy") -> 01/2025 | H56: Comunidade Judaica
A57: Encontro c/ Leandro Resende (CBN) | B57: Informações Evento Data: 15/01 Horário: 16h Local: Câmara Municipal do Rio de Janeiro, Praça Floriano - Centro Observações: Encontro c/ Leandro Resende (CBN) Contato: Marcado p/ FV em 07/01 | C57: Câmara Municipal do Rio de Janeiro, Praça Floriano - Centro, Rio de Janeiro - RJ, 20031-050, Brasil | D57: 45672.667 | E57: flaviogvalle@gmail.com;crislobo@gmail.com | F57: =TEXT(D57, "mm/yyyy") -> 01/2025 | H57: Comunicação/Imprensa
A58: Sessão de fotos KV | B58: Solicitado p/ Comunicação. Fotos para peças publicitárias. | C58: Câmara Municipal do Rio de Janeiro, Praça Floriano - Centro, Rio de Janeiro - RJ, 20031-050, Brasil | D58: 45672.708 | E58: flaviogvalle@gmail.com;mrpaulobarros@gmail.com;gisellygazevedo@gmail.com | F58: =TEXT(D58, "mm/yyyy") -> 01/2025 | H58: Comunicação/Imprensa
A59: Reunião no Jobi | B59: Informações Evento Data: 15/01 Horário: 18h Local: Jobi, Av. Ataulfo de Paiva, 1166 - Leblon Observações: Agenda Jobi + Guilherme Responsável: Bruno Ramos | C59: Jobi, Av. Ataulfo de Paiva, 1166 - Leblon, Rio de Janeiro - RJ, 22440-035, Brasil | D59: 45672.75 | E59: flaviogvalle@gmail.com;brfbruno2@gmail.com | F59: =TEXT(D59, "mm/yyyy") -> 01/2025 | H59: Reunião Atendimento
A60: Reunião - Bernardo Rubião | C60: Liz Cocktail & Co, Rua Dias Ferreira, 679A - Leblon, Rio de Janeiro - RJ, 22431-050, Brasil | D60: 45672.833 | E60: flaviogvalle@gmail.com;lfdsbr@gmail.com | F60: =TEXT(D60, "mm/yyyy") -> 01/2025 | H60: Reunião Executivo
A61: Reunião - Beth Yunes | B61: Informações Evento Data: 16/01 Horário: 10h Local: Gabinete 506 Contato: +55 21 97568-2097 | C61: Câmara Municipal do Rio de Janeiro, Praça Floriano - Centro, Rio de Janeiro - RJ, 20031-050, Brasil | D61: 45673.417 | E61: flaviogvalle@gmail.com | F61: =TEXT(D61, "mm/yyyy") -> 01/2025 | H61: Reunião Atendimento
A62: Visita ao Maravalley | C62: Porto Maravalley, Av. Prof. Pereira Reis, 76 - Santo Cristo, Rio de Janeiro - RJ, 20220-800, Brasil | D62: 45673.458 | E62: lucasrosa.arq@gmail.com;otaviobopp@gmail.com;leonardosolabloise@gmail.com;lauranalbq@gmail.com;leonardo.moog@hotmail.com;viniciusmmg@gmail.com;juliagardel2@gmail.com;pedroangelito22@gmail.com;leonardolopes@llfilm.com.br;contato.lucasfajardo@gmail.com;flaviogvalle@gmail.com;andrew.mata.2022@gmail.com;leomartins.rzs@gmail.com;crislobo@gmail.com;monteirojpf@gmail.com;lfdsbr@gmail.com;lima.saramoreira@gmail.com;biarsbz@gmail.com;matheus.ocn@gmail.com;lorekutwak@gmail.com;mrpaulobarros@gmail.com;gisellygazevedo@gmail.com | F62: =TEXT(D62, "mm/yyyy") -> 01/2025 | H62: Reunião Interna/Planejamento
A63: Almoço no Rancho Portugues com Seu Gabriel e Cesar do Momo | B63: Informações Evento Data: 16/01 Horário: 13h Local: Rancho Português, R. Maria Quitéria, 136 - Ipanema Observações: Almoço no Rancho Portugues com Seu Gabriel e Cesar do Momo. Responsável: Pedro Angelito | C63: Rancho Português, R. Maria Quitéria, 136 - Ipanema, Rio de Janeiro - RJ, 22410-040, Brasil | D63: 45673.542 | E63: bernardorubiao@gmail.com;pedroangelito22@gmail.com;flaviogvalle@gmail.com;lfdsbr@gmail.com | F63: =TEXT(D63, "mm/yyyy") -> 01/2025 | H63: Reunião Atendimento
A64: Visita ao COR | C64: Centro de Operações Rio (COR), Rua Ulysses Guimarães, 300 - Cidade Nova, Rio de Janeiro - RJ, 20211-225, Brasil | D64: 45673.625 | E64: otaviobopp@gmail.com;lucasrosa.arq@gmail.com;leonardosolabloise@gmail.com;lauranalbq@gmail.com;leonardo.moog@hotmail.com;viniciusmmg@gmail.com;juliagardel2@gmail.com;pedroangelito22@gmail.com;leonardolopes@llfilm.com.br;contato.lucasfajardo@gmail.com;leomartins.rzs@gmail.com;andrew.mata.2022@gmail.com;flaviogvalle@gmail.com;monteirojpf@gmail.com;crislobo@gmail.com;lfdsbr@gmail.com;lima.saramoreira@gmail.com;biarsbz@gmail.com;matheus.ocn@gmail.com;lorekutwak@gmail.com;mrpaulobarros@gmail.com;gisellygazevedo@gmail.com | F64: =TEXT(D64, "mm/yyyy") -> 01/2025 | H64: Reunião Interna/Planejamento
A65: Reunião - Dan Messer | B65: Informações Evento Data: 16/01 Horário: 17:30h Local: Avenida epitacio pessoa, 318, sala 103, em frente ao jardim de alah Contato: +55 21 99055-0443 | C65: Av. Epitácio Pessoa, 318 - Ipanema, Rio de Janeiro - RJ, 22410-090, Brasil | D65: 45673.729 | E65: flaviogvalle@gmail.com | F65: =TEXT(D65, "mm/yyyy") -> 01/2025 | H65: Reunião Atendimento
A66: Fernando Kaplan | C66: SO_Lo, Av. Ataulfo de Paiva, 1120 - Leblon, Rio de Janeiro - RJ, 22440-035, Brasil | D66: 45673.771 | F66: =TEXT(D66, "mm/yyyy") -> 01/2025 | H66: Reunião Atendimento
A67: Churrasco Farm House (Jerson Farofa) | B67: Informações Evento<br><br>Data: 16/01<br>Horário: A partir das 18h <br>Local: R. Voluntários da Pátria, 301/302<br>Observações: Passando para convida-lo para o já tradicional churrasco da House. A partir das 18h. Será uma honra recebê-lo. <br>Contato: <a target="_blank">+5521983539780</a><br><br><br><span>Responsável: Recebido p/ FV em 13/01.</span> | C67: R. Voluntários da Pátria, 301 - Botafogo, Rio de Janeiro - RJ, 22270-003, Brasil | D67: 45673.771 | E67: flaviogvalle@gmail.com | F67: =TEXT(D67, "mm/yyyy") -> 01/2025 | H67: Eventos
A68: Despedida Elissa | C68: Avenida Rodrigo Otavio próximo ao 1003, Gávea, Rio de Janeiro - RJ, 22450-060, Brasil | D68: 45673.875 | F68: =TEXT(D68, "mm/yyyy") -> 01/2025 | H68: Compromissos Pessoais FV
A69: Reunião - Fluxo Sistema "Meu Gabinete" | B69: Informações Evento Data: 17/01 Horário: 10:30h Local: Instituto 12, Av. Ataulfo de Paiva, 1120 - Leblon Contato: Marcado p/ FV | C69: Instituto 12, Av. Ataulfo de Paiva, 1120 - Leblon, Rio de Janeiro - RJ, 22440-035, Brasil | D69: 45674.438 | E69: lucasrosa.arq@gmail.com;lauranalbq@gmail.com;viniciusmmg@gmail.com;biarsbz@gmail.com;flaviogvalle@gmail.com;andrew.mata.2022@gmail.com;leomartins.rzs@gmail.com;matheus.ocn@gmail.com;monteirojpf@gmail.com;gisellygazevedo@gmail.com;lfdsbr@gmail.com | F69: =TEXT(D69, "mm/yyyy") -> 01/2025 | H69: Reunião Interna/Planejamento
A70: Almoço Marcelo V3A | B70: Informações Evento Data: 17/01 Horário: 12:30h Local: Rancho Português, R. Maria Quitéria, 136 - Ipanema Responsável: Bruno Ramos | C70: Rancho Português, R. Maria Quitéria, 136 - Ipanema, Rio de Janeiro - RJ, 22410-040, Brasil | D70: 45674.521 | E70: flaviogvalle@gmail.com;brfbruno2@gmail.com | F70: =TEXT(D70, "mm/yyyy") -> 01/2025 | H70: Reunião Atendimento
A71: Reunião com Alexandre + Rubião | C71: Copacabana Palace, Av. Atlântica, 1702 - Copacabana, Rio de Janeiro - RJ, 22021-001, Brasil | D71: 45674.625 | E71: bernardorubiao@gmail.com | F71: =TEXT(D71, "mm/yyyy") -> 01/2025 | H71: Reunião Executivo
A72: Escrever artigo | D72: 45674.667 | F72: =TEXT(D72, "mm/yyyy") -> 01/2025 | H72: Compromissos Pessoais FV
A73: Reunião - Osmar Lima + Marcel Balassiano | B73: Informações Evento Data: 17/01 Horário: 17h Local: CCPAR - Rua Sacadura Cabral, 133, 3o andar Observações: Companhia Carioca de Parcerias e Investimentos - CCPar, R. Sacadura Cabral, 133 - Saúde Responsável: Marcel Balassiano Osmar Lima, secretário de Desenvolvimento Econômico e presidente da CCPAR | C73: Companhia Carioca de Parcerias e Investimentos - CCPar, R. Sacadura Cabral, 133 - Saúde, Rio de Janeiro - RJ, 20081-261, Brasil | D73: 45674.708 | E73: flaviogvalle@gmail.com;marcel.balassiano@fgv.br;lfdsbr@gmail.com | F73: =TEXT(D73, "mm/yyyy") -> 01/2025 | H73: Reunião Executivo
A74: (Aguardando + Info) Inauguração Arena LEV | D74: 45675 | E74: flaviogvalle@gmail.com | F74: =TEXT(D74, "mm/yyyy") -> 01/2025
A75: Aniversário - Rony (Comunidade Judaica) | B75: Informações Evento Data: 18/01 Horário: 20h Local: Maraca Pub, Rua da Passagem, 39 - Botafogo Observações: E aí Flávio, tudo bem? Olá só, faço aniversário dia 19/01 mas vou comemorar dia 18 num Pub em Botafogo, Maraca Pub, queria te convidar. Seria lá pelas 20h. Vai ter bastante gente que votou em ti, pessoal da comunidade. Contato: Rony Comunidade Judaica Responsável: Recebido p/ FV em 08/01. | C75: Maraca Pub, Rua da Passagem, 39 - Botafogo, Rio de Janeiro - RJ, 22290-030, Brasil | D75: 45675.833 | E75: flaviogvalle@gmail.com | F75: =TEXT(D75, "mm/yyyy") -> 01/2025 | H75: Comunidade Judaica
A76: Corrida de São Sebastião 5km/10km | B76: <b>Convite Secretário Guilherme Schleder</b><br><br>Data do evento: 20 de janeiro de 2025<br>Tipo de evento: Corrida de São Sebastião 5km/10km<br>Local: Aterro do Flamengo<br>Largada e chegada: Pórtico no Aterro do Flamengo, entre as Ruas Tucumã e Cruz Lima<br>Horário do evento: 06:00 às 11:00<br>Melhor horário de chegada: 08:45<br>Estimativa de público: 10 mil pessoas<br>Assessor Resp: Nicole Calheiros<br>Programação:<br>Abertura das áreas do Evento: 06:00<br>Largada da prova: 07:00<br>Premiação: 09:00<br>Término da prova: 09:00<br>Encerramento da Arena: 11:00<br>Observação:<br>- A Corrida de São Sebastião convida o Secretário de Esportes e Lazer da Cidade do Rio de Janeiro a comparecer ao evento e prestigiar os nossos atletas.<br>- Esse evento é em homenagem ao Padroeiro de nossa Cidade, que traz ao Rio atletas de todo o mundo para correr e celebrar.<br>- O evento faz parte do calendário oficial da Cidade, conforme Lei Municipal 4.314. Por seu nível técnico, estruturas, reconhecimento internacional e chancelas, nossa prova é certificada e membro da AIMS, órgão máximo em maratonas provas de rua no mundo, e prova nível A da Confederação Brasileira de Atletismo. | C76: Boteco Belmonte, Praia do Flamengo, 300 - Loja B - Flamengo, Rio de Janeiro - RJ, 22210-030, Brasil | D76: 45677.365 | E76: flaviogvalle@gmail.com | F76: =TEXT(D76, "mm/yyyy") -> 01/2025 | H76: Eventos
A77: Celebração do Dia de São Sebastião c/ Cavaliere | B77: Informado p/ Leo Fernandes Obs: Vestir vermelho. | C77: Basílica Santuário de São Sebastião (Igreja dos Capuchinhos), R. Haddock Lobo, 266 - Tijuca, Rio de Janeiro - RJ, 20260-142, Brasil | D77: 45677.625 | E77: flaviogvalle@gmail.com;lfdsbr@gmail.com | F77: =TEXT(D77, "mm/yyyy") -> 01/2025 | H77: Eventos
A78: Visita Colônia de Férias c/ Guilherme Schleder | B78: Data do evento: 21 de janeiro de 2025 Tipo de evento: Visita na Vila Olímpica do Vidigal na Abertura da Colônia de Férias Local: Vila Olímpica do Vidigal Endereço: Av. Presidente João Goulart - Vidigal Melhor horário de chegada: 09:30 Estimativa de público: 30 pessoas Responsável: Bruno Ramos (Chefe de Gabinete) Observação: - Guilherme será recebido na Vila pelos coordenadores, terá um café da manhã para recepcioná-lo; - Cerca de 30 alunos que participam da colônia de férias estarão presentes. | C78: Anfiteatro Vila Olímpica, Av. Presidente João Goulart - Vidigal, Rio de Janeiro - RJ, 22452-694, Brasil | D78: 45678.396 | E78: flaviogvalle@gmail.com | F78: =TEXT(D78, "mm/yyyy") -> 01/2025 | H78: Externa/Rua
A79: EA: Ciclo de Treinamento da Câmara - Lei Orgânica do Município (LOM) | B79: 21/01 - Lei Orgânica do Município (LOM); 22/01 - Noções Gerais de Direito Constitucional; 23/01 - Noções de Regimento Interno da CMRJ e Lei nº 48/2000; 24/01 - Sistema de Assessoramento Legislativo (SAL) e Verse; 27/01 - E-Câmara - Processo Administrativo - Considerações Gerais; 28/01 - Técnicas de Redação - Projetos, Moções, Indicações, Req. Informações; 29/01 - Técnicas de Redação - Ofícios e Requerimentos; 30/01 - Comissões - Permanentes, Especiais e de Inquéritos - Frente Parlamentar; 31/01 - Intranet; 03/02 - Competências do Encarregado de Núcleo; 04/02 - Processo Legislativo na Câmara Municipal do RJ. | C79: Câmara Municipal do Rio de Janeiro, Praça Floriano - Centro, Rio de Janeiro - RJ, 20031-050, Brasil | D79: 45678.417 | E79: flaviogvalle@gmail.com | F79: =TEXT(D79, "mm/yyyy") -> 01/2025 | H79: Reunião Interna/Planejamento
A80: Reunião - Cris Lobo e Giselly | C80: Câmara Municipal do Rio de Janeiro, Praça Floriano - Centro, Rio de Janeiro - RJ, 20031-050, Brasil | D80: 45678.521 | E80: flaviogvalle@gmail.com;crislobo@gmail.com;gisellygazevedo@gmail.com | F80: =TEXT(D80, "mm/yyyy") -> 01/2025 | H80: Reunião Interna/Planejamento
A81: Reunião Semanal - Comunicação e Imprensa | C81: Câmara Municipal do Rio de Janeiro, Praça Floriano - Centro, Rio de Janeiro - RJ, 20031-050, Brasil | D81: 45678.542 | E81: contato.lucasfajardo@gmail.com;flaviogvalle@gmail.com;monteirojpf@gmail.com;crislobo@gmail.com;gisellygazevedo@gmail.com;lfdsbr@gmail.com | F81: =TEXT(D81, "mm/yyyy") -> 01/2025 | H81: Reunião Interna/Planejamento
A82: Reunião Semanal - Gabinete | C82: Câmara Municipal do Rio de Janeiro, Praça Floriano - Centro, Rio de Janeiro - RJ, 20031-050, Brasil | D82: 45678.625 | E82: lucasrosa.arq@gmail.com;flaviogvalle@gmail.com;monteirojpf@gmail.com;lfdsbr@gmail.com | F82: =TEXT(D82, "mm/yyyy") -> 01/2025 | H82: Reunião Interna/Planejamento
A83: Reunião Semanal - Pesquisa e Redação | C83: Câmara Municipal do Rio de Janeiro, Praça Floriano - Centro, Rio de Janeiro - RJ, 20031-050, Brasil | D83: 45678.667 | E83: lima.saramoreira@gmail.com;leonardo.moog@hotmail.com;juliagardel2@gmail.com;pedroangelito22@gmail.com;fabiocampellobjj@gmail.com;flaviogvalle@gmail.com;monteirojpf@gmail.com;lfdsbr@gmail.com | F83: =TEXT(D83, "mm/yyyy") -> 01/2025 | H83: Reunião Interna/Planejamento
A84: Reunião Semanal - Atendimento | C84: Câmara Municipal do Rio de Janeiro, Praça Floriano - Centro, Rio de Janeiro - RJ, 20031-050, Brasil | D84: 45678.688 | E84: lauranalbq@gmail.com;flaviogvalle@gmail.com;andrew.mata.2022@gmail.com;monteirojpf@gmail.com;lfdsbr@gmail.com | F84: =TEXT(D84, "mm/yyyy") -> 01/2025 | H84: Reunião Interna/Planejamento
A85: EA: Encontros Veja Rio de 2025 | B85: Oi, tudo bem? Boa tarde. Você é nosso convidado para a primeira edição do Encontros Veja Rio de 2025. Podemos contar com a sua presença? Dia 21 de janeiro, às 17h, no SEL d’Ipanema. | C85: Sel d'Ipanema Beach Club, Avenida Vieira Souto - R. Maria Quitéria, 00 - Qc 11 e 12 E/f A - Ipanema, Rio de Janeiro - RJ, 22420-002, Brasil | D85: 45678.708 | E85: flaviogvalle@gmail.com | F85: =TEXT(D85, "mm/yyyy") -> 01/2025 | H85: Eventos
A86: Fiscalização c/ João Pires | C86: Academia Smart Fit - Bambina, R. Bambina, 146 - Botafogo, Rio de Janeiro - RJ, 22251-050, Brasil | D86: 45678.75 | E86: flaviogvalle@gmail.com | F86: =TEXT(D86, "mm/yyyy") -> 01/2025 | H86: Vistorias
A87: EA: Ciclo de Treinamento da Câmara - Noções de Regimento Interno da CMRJ e Lei nº 48/2000 | B87: 21/01 - Lei Orgânica do Município (LOM); 22/01 - Noções Gerais de Direito Constitucional; 23/01 - Noções de Regimento Interno da CMRJ e Lei nº 48/2000; 24/01 - Sistema de Assessoramento Legislativo (SAL) e Verse; 27/01 - E-Câmara - Processo Administrativo - Considerações Gerais; 28/01 - Técnicas de Redação - Projetos, Moções, Indicações, Req. Informações; 29/01 - Técnicas de Redação - Ofícios e Requerimentos; 30/01 - Comissões - Permanentes, Especiais e de Inquéritos - Frente Parlamentar; 31/01 - Intranet; 03/02 - Competências do Encarregado de Núcleo; 04/02 - Processo Legislativo na Câmara Municipal do RJ. | C87: Câmara Municipal do Rio de Janeiro, Praça Floriano - Centro, Rio de Janeiro - RJ, 20031-050, Brasil | D87: 45679.417 | E87: flaviogvalle@gmail.com | F87: =TEXT(D87, "mm/yyyy") -> 01/2025 | H87: Reunião Interna/Planejamento
A88: Reunião - Procuradora Olívia + João Moraes | B88: Informações Evento Data: 22/01 Horário: 10h Local: Tv. do Ouvidor, 4 - Centro - 4º Andar Observações: Reunião com Procuradora Olívia + João Moraes Contato: Marcado p/ FV em 16/01 | C88: Tv. do Ouvidor, 4 - Centro, Rio de Janeiro - RJ, 20040-040, Brasil | D88: 45679.417 | E88: flaviogvalle@gmail.com | F88: =TEXT(D88, "mm/yyyy") -> 01/2025 | H88: Reunião Atendimento
A89: Despacho Semanal - Rafael Azamor | C89: R. Vinícius de Moraes, 149 - Ipanema, Rio de Janeiro - RJ, 22411-010, Brasil | D89: 45679.562 | E89: rafaazamor@gmail.com;flaviogvalle@gmail.com | F89: =TEXT(D89, "mm/yyyy") -> 01/2025 | H89: Reunião Interna/Planejamento
A90: Almoço - Ronaldo Gomlevsky | B90: Informações Evento Data: 22/01 Horário: 14h Local: Restaurante casa mohamed R. Vinícius de Moraes, 149 - Ipanema Observações: É um ex vereador da comunidade judaica que quer tambem entrevistar ele Responsável: Rafael Azamor | C90: R. Vinícius de Moraes, 149 - Ipanema, Rio de Janeiro - RJ, 22411-010, Brasil | D90: 45679.583 | E90: rafaazamor@gmail.com;flaviogvalle@gmail.com | F90: =TEXT(D90, "mm/yyyy") -> 01/2025 | H90: Comunidade Judaica
A91: Reunião - Alberto Dawidovitch | B91: Informações Evento Data: 22/01 Horário: 15h Local: McDonald's, R. Visc. de Pirajá, 338 - Ipanema Observações: Bate-papo Contato: +55 21 98604-3495 | C91: McDonald's, R. Visc. de Pirajá, 338 - Ipanema, Rio de Janeiro - RJ, 22410-000, Brasil | D91: 45679.625 | E91: flaviogvalle@gmail.com | F91: =TEXT(D91, "mm/yyyy") -> 01/2025 | H91: Reunião Atendimento
A92: Reunião - João Pires | B92: Informações Evento Data: 22/01 Horário: 16:30h Local: Aristides Lobo, 71/2º andar - Rio Comprido Observações: Marcado p/ FV em 21/01 Contato: Claudia Argento +55 21 97034-7709 | C92: R. Aristídes Lôbo, 71 - Rio Comprido, Rio de Janeiro - RJ, 20250-450, Brasil | D92: 45679.688 | E92: flaviogvalle@gmail.com | F92: =TEXT(D92, "mm/yyyy") -> 01/2025 | H92: Reunião Executivo
A93: EA: Ciclo de Treinamento da Câmara - Noções de Regimento Interno da CMRJ e Lei nº 48/2000 | B93: 21/01 - Lei Orgânica do Município (LOM); 22/01 - Noções Gerais de Direito Constitucional; 23/01 - Noções de Regimento Interno da CMRJ e Lei nº 48/2000; 24/01 - Sistema de Assessoramento Legislativo (SAL) e Verse; 27/01 - E-Câmara - Processo Administrativo - Considerações Gerais; 28/01 - Técnicas de Redação - Projetos, Moções, Indicações, Req. Informações; 29/01 - Técnicas de Redação - Ofícios e Requerimentos; 30/01 - Comissões - Permanentes, Especiais e de Inquéritos - Frente Parlamentar; 31/01 - Intranet; 03/02 - Competências do Encarregado de Núcleo; 04/02 - Processo Legislativo na Câmara Municipal do RJ. | C93: Câmara Municipal do Rio de Janeiro, Praça Floriano - Centro, Rio de Janeiro - RJ, 20031-050, Brasil | D93: 45680.417 | E93: flaviogvalle@gmail.com | F93: =TEXT(D93, "mm/yyyy") -> 01/2025 | H93: Reunião Interna/Planejamento
A94: Reunião - Secretário Lucas Padilha | B94: MARCADO Reunião com o Vereador Flavio Valle. Pauta: Equipamentos da SMC na ZS Quinta-feira, 23 de janeiro⋅13:00 até 14:00 Gabinete SMC, 3 andar - Centro Administrativo São Sebastião - Cidade Nova, Rio de Janeiro - RJ, Brasil | C94: Centro Administrativo São Sebastião - Cidade Nova, Rio de Janeiro - RJ, Brasil | D94: 45680.542 | E94: flaviogvalle@gmail.com | F94: =TEXT(D94, "mm/yyyy") -> 01/2025 | H94: Reunião Executivo
A95: Gravar vídeo Plano Estratégico | D95: 45680.604 | F95: =TEXT(D95, "mm/yyyy") -> 01/2025 | H95: Comunicação/Imprensa
A96: EA: Conversa c/ Moradores do Horto sobre Lixeiras | C96: Horto - Jardim Botânico, Rio de Janeiro - State of Rio de Janeiro, 22460-320, Brasil | D96: 45680.625 | E96: flaviogvalle@gmail.com;leomartins.rzs@gmail.com | F96: =TEXT(D96, "mm/yyyy") -> 01/2025
A97: Reunião - Secretária Martha Rocha | B97: Informações Evento Data: 23/01 Horário: 16h Local: Sala 501 - Centro Administrativo São Sebastião - Cidade Nova Observações: Solicitado p/ FV. Contato: Vinícius +55 21 99989-7221 | C97: Centro Administrativo São Sebastião - Cidade Nova, Rio de Janeiro - RJ, Brasil | D97: 45680.667 | E97: flaviogvalle@gmail.com | F97: =TEXT(D97, "mm/yyyy") -> 01/2025 | H97: Reunião Executivo
A98: Reunião - Pres. Luiz Eduardo (CET-Rio) | B98: Informações Evento Data: 23/01 Horário: 17h Local: Rua Ulysses Guimarães, 16 - Cidade Nova (Prédio atrás do CASS) Observações: Solicitado p/ FV. Contato: +55 21 98093-5557 Marseille | C98: Rua Ulysses Guimarães, 16 - Cidade Nova, Rio de Janeiro - RJ, 20211-225, Brasil | D98: 45680.708 | E98: flaviogvalle@gmail.com | F98: =TEXT(D98, "mm/yyyy") -> 01/2025 | H98: Reunião Executivo
A99: Futebol | B99: Futebol (quinta-feira) Dia:23/01 Horário:19 hrs Local: Campo do Aterro Responsável: Leonardo Martins | C99: Campos de Futebol Society, Praia do Flamengo, 20 - Flamengo, Rio de Janeiro - RJ, 22210-030, Brasil | D99: 45680.792 | E99: flaviogvalle@gmail.com;leomartins.rzs@gmail.com | F99: =TEXT(D99, "mm/yyyy") -> 01/2025 | H99: Eventos
A100: Visita as Obras da GeoRio no Vidigal | B100: Sexta-feira, 24 de janeiro Visita as Obras da GeoRio no Vidigal - Resp. Edinho Sexta-feira, 24 de janeiro⋅07:00 até 08:00 | C100: Vidigal, Av. Presidente João Goulart, 464 - Vidigal, Rio de Janeiro - RJ, 22450-242, Brasil | D100: 45681.292 | E100: flaviogvalle@gmail.com;leomartins.rzs@gmail.com | F100: =TEXT(D100, "mm/yyyy") -> 01/2025 | H100: Externa/Rua
...

Sheet Gabinete Itinerante
A1: Edição | B1: Data | C1: Local | D1: Bairro | E1: Coluna 1
A2: 1 | B2: 45786 | C2: Praça Nelson Mandela | D2: Botafogo | E2: Concluído
A3: 2 | B3: 45787 | C3: Praça Tião Belo | D3: Botafogo | E3: Concluído
A4: 3 | B4: 45793 | C4: Metrô São Conrado | D4: Rocinha | E4: Concluído
A5: 4 | B5: 45800 | C5: Praça Sezerdelo | D5: Copacabana | E5: Concluído
A6: 5 | B6: 45807 | C6: Praça do Vidigal | D6: Vidigal | E6: Concluído
A7: 6 | B7: 45814 | C7: Largo dos Leões | D7: Humaitá | E7: Concluído
A8: 7 | B8: 45821 | C8: Ladeira dos Tabajaras | D8: Tabajaras | E8: Concluído
A9: 8 | B9: 45828 | C9: Feriado | D9: - | E9: Cancelado
A10: 9 | B10: 45835 | C10: Nossa Senhora da Paz | D10: Ipanema | E10: Concluído
A11: 10 | B11: 45842 | C11: Feriado | D11: - | E11: Cancelado
A12: 11 | B12: 45849 | C12: Praça Edmundo Bittencourt | D12: Copacabana | E12: Concluído
A13: 12 | B13: 45856 | C13: PPG | D13: Copacabana | E13: Concluído
... A24: 23 | B24: 45935 | C24: Praça Nossa Senhora da Paz | D24: Ipanema | E24: Concluído

Sheet Indicações
A1: - | B1: ÓRGÃO COMPETENTE | C1: RESUMO SOLICITAÇÃO | D1: DATA | E1: BAIRRO
A2: 1 | B2: COMLURB | C2: SOLICITA PROVIDÊNCIAS JUNTO À COMPANHIA MUNICIPAL DE LIMPEZA URBANA - COMLURB, VISANDO MANUTENÇÃO DE BRINQUEDOS DA PRAÇA ALMIRANTE JÚLIO DE NORONHA, BAIRRO DO LEME. | E2: LEME
A3: 2 | B3: COMLURB | C3: SOLICITA PROVIDÊNCIAS JUNTO À COMPANHIA MUNICIPAL DE LIMPEZA URBANA - COMLURB, VISANDO A LIMPEZA DO AMBULATÓRIO DA PRAIA DO PINTO, NO BAIRRO DO JARDIM BOTÂNICO | E3: JARDIM BOTÂNICO
A4: 3 | B4: CET-RIO | C4: SOLICITA PROVIDÊNCIAS JUNTO À COMPANHIA DE ENGENHARIA DE TRÁFEGO DO RIO DE JANEIRO - CET-RIO, VISANDO MANUTENÇÃO DA FAIXA DE PEDESTRES DA RUA PAULO BARRETO, 65, NO BAIRRO DE BOTAFOGO. | E4: BOTAFOGO
A5: 4 | B5: SMS | C5: SOLICITA PROVIDÊNCIAS JUNTO À SECRETARIA MUNICIPAL DE SAÚDE, VISANDO COMBATE AOS FOCOS DE DENGUE NO BAIRRO DE IPANEMA. | E5: IPANEMA
A6: 5 | B6: COMLURB | C6: SOLICITA PROVIDÊNCIAS JUNTO À COMPANHIA MUNICIPAL DE LIMPEZA URBANA - COMLURB, VISANDO LIMPEZA DA PRAÇA NOSSA SENHORA DA PAZ, NO BAIRRO DE IPANEMA. | E6: IPANEMA
A7: 6 | B7: COMLURB | C7: SOLICITA PROVIDÊNCIAS JUNTO À COMPANHIA MUNICIPAL DE LIMPEZA URBANA - COMLURB, VISANDO RETIRADA DE LIXO NA COMUNIDADE SANTA MARTA, NAS PROXIMIDADES DA RUA OSWALDO SEABRA, 961. | E7: SANTA MARTA
A8: 7 | B8: SMTR | C8: SOLICITA PROVIDÊNCIAS JUNTO À SECRETARIA MUNICPAL DE TRANSPORTES E AO PROCON CARIOCA VISANDO AUMENTO DA FROTA 538/539 LEME-ROCINHA | E8: LEME
A9: 8 | B9: COMLURB | C9: SOLICITA PROVIDÊNCIAS JUNTO À COMPANHIA MUNICIPAL DE LIMPEZA URBANA - COMLURB, VISANDO VARRIÇÃO DE LOGRADOURO - RUA MAJOR RUBENS VAZ, NO BAIRRO DA GÁVEA | E9: GÁVEA
A10: 9 | B10: SECONSERVA | C10: SOLICITA PROVIDÊNCIAS JUNTO À SECRETARIA MUNICIPAL DE CONSERVAÇÃO - SECONSERVA, VISANDO TAPA BURACO NA RUA JOÃO AFONSO N°108, NO BAIRRO DO HUMAÍTA | E10: HUMAITÁ
A11: 10 | B11: COMLURB | C11: SOLICITA PROVIDÊNCIAS JUNTO À COMPANHIA MUNICIPAL DE LIMPEZA URBANA - COMLURB, VISANDO PODA NA RUA GENERAL URQUIZA COM JOÃO DE BARROS, NO BAIRRO DO LEBLON | E11: LEBLON
A12: 11 | B12: COMLURB | C12: SOLICITA PROVIDÊNCIAS JUNTO À COMPANHIA MUNICIPAL DE LIMPEZA URBANA - COMLURB, VISANDO PODA NA RUA GENERAL SEVERIANO, Nº 170, NO BAIRRO DE BOTAFOGO | E12: BOTAFOGO
A13: 12 | B13: COMLURB | C13: SOLICITA PROVIDÊNCIAS JUNTO À COMPANHIA MUNICIPAL DE LIMPEZA URBANA - COMLURB, VISANDO SERVIÇO DE ROÇADA NA RUA JOÃO AFONSO, Nº 86 -, NO BAIRRO DO HUMAITÁ | E13: HUMAITÁ
... A70: 69 | B70: COMLURB | C70: SOLICITA PROVIDÊNCIAS JUNTO À COMPANHIA MUNICIPAL DE LIMPEZA URBANA – COMLURB E À SECRETARIA MUNICIPAL DE MEIO AMBIENTE E CLIMA – SMAC, PARA VIABILIZAR A MANUTENÇÃO DE ÁREA VERDE NA RUA TONELERO, Nº 311, NO BAIRRO DE COPACABANA | E70: COPACABANA
A71: 70 | C71: SOLICITA PROVIDÊNCIAS JUNTO À SECRETARIA MUNICIPAL DO ENVELHECIMENTO SAUDÁVEL E QUALIDADE DE VIDA – SEMESQV, VISANDO A INSTALAÇÃO DE ACADEMIA AO AR LIVRE NA ESTRADA DA GÁVEA, Nº 232, NA PRACINHA DA ROCINHA | E71: ROCINHA
A72: 71 | B72: CET-RIO | C72: SOLICITA PROVIDÊNCIAS JUNTO À COMPANHIA DE ENGENHARIA DE TRÁFEGO DO RIO DE JANEIRO – CET-RIO, VISANDO ESTUDO DE VIABILIDADE PARA INSTALAÇÃO DE QUEBRA-MOLAS NA ESTRADA DA GÁVEA | E72: ROCINHA
A73: 72 | B73: RIOLUZ | C73: SOLICITA PROVIDÊNCIAS JUNTO À COMPANHIA MUNICIPAL DE ENERGIA E ILUMINAÇÃO – RIOLUZ, VISANDO MELHORIA NA ILUMINAÇÃO DA CICLOVIA ENTRE BOTAFOGO E COPACABANA | E73: BOTAFOGO
A74: 73 | B74: RIOLUZ | C74: SOLICITA PROVIDÊNCIAS JUNTO À COMPANHIA MUNICIPAL DE ENERGIA E ILUMINAÇÃO – RIOLUZ, VISANDO A RETIRADA DE POSTES OCIOSOS NA RUA MONTE ALEGRE, Nº 348, NO BAIRRO DE SANTA TERESA | E74: SANTA TERESA
A75: 74 | B75: COMLURB | C75: SOLICITA PROVIDÊNCIAS JUNTO À COMPANHIA MUNICIPAL DE LIMPEZA URBANA – COMLURB, PARA O ENVIO DO LAUDO REFERENTE À PODA REALIZADA NA CASA DE SAÚDE SÃO SEBASTIÃO, LOCALIZADA NA RUA BENTO LISBOA, Nº 160, NO BAIRRO DO CATETE | E75: CATETE
A76: 75 | B76: COMLURB | C76: SOLICITA PROVIDÊNCIAS JUNTO À COMPANHIA MUNICIPAL DE LIMPEZA URBANA – COMLURB, PARA VIABILIZAR PODA NA PRAÇA MILTON CAMPOS, Nº 1, NO BAIRRO DO LEBLON | E76: LEBLON
A77: 76 | B77: SECONSERVA | C77: SOLICITA PROVIDÊNCIAS JUNTO À SECRETARIA MUNICIPAL DE CONSERVAÇÃO E SERVIÇOS PÚBLICOS – SECONSERVA, REFERENTE ÀS AÇÕES NA RUA VOLUNTÁRIOS DA PÁTRIA, Nº 283, NO BAIRRO DE BOTAFOGO | E77: BOTAFOGO
A78: 77 | B78: SECONSERVA | C78: SOLICITA PROVIDÊNCIAS JUNTO À SECRETARIA MUNICIPAL DE CONSERVAÇÃO E SERVIÇOS PÚBLICOS – SECONSERVA, REFERENTE ÀS AÇÕES NA RUA SÃO CLEMENTE, Nº 226, NO BAIRRO DE BOTAFOGO | E78: BOTAFOGO
A79: 78 | B79: RIOLUZ | C79: SOLICITA PROVIDÊNCIAS JUNTO À COMPANHIA MUNICIPAL DE ENERGIA E ILUMINAÇÃO – RIOLUZ, VISANDO RESTABELECIMENTO DA ILUMINAÇÃO NA PRAÇA MILTON CAMPOS, NO BAIRRO DO LEBLON | E79: LEBLON
A80: 79 | B80: SECONSERVA | C80: SOLICITA PROVIDÊNCIAS JUNTO À SECRETARIA MUNICIPAL DE CONSERVAÇÃO E SERVIÇOS PÚBLICOS – SECONSERVA, REFERENTE ÀS AÇÕES NA RUA PEDRO AMÉRICO, Nº 90, NO BAIRRO DO CATETE | E80: CATETE
A81: 80 | C81: SOLICITA PROVIDÊNCIAS JUNTO À SUPERINTENDÊNCIA EXECUTIVA DE PATRIMÔNIO IMOBILIÁRIO – F/SUBEX/SUPPA, REFERENTE À TROCA DE PLACAS DE RUA NA PRAÇA CORUMBÁ, NO BAIRRO DE BOTAFOGO | E81: BOTAFOGO
A82: 81 | B82: CET-RIO | C82: SOLICITA PROVIDÊNCIAS JUNTO À COMPANHIA DE ENGENHARIA DE TRÁFEGO DO RIO DE JANEIRO – CET-RIO, VISANDO PINTURA DAS FAIXAS DE SINALIZAÇÃO NA RUA PACHECO LEÃO, Nº 1418, NO BAIRRO DO JARDIM BOTÂNICO | E82: JARDIM BOTÂNICO
A83: 82 | B83: COMLURB | C83: SOLICITA PROVIDÊNCIAS JUNTO À COMPANHIA MUNICIPAL DE LIMPEZA URBANA – COMLURB E À SECRETARIA MUNICIPAL DE CONSERVAÇÃO E SERVIÇOS PÚBLICOS – SECONSERVA, PARA VIABILIZAR A MANUTENÇÃO DOS BRINQUEDOS, MOBILIÁRIOS E GRADIL DA PRAÇA NOSSA SENHORA DA PAZ, NO BAIRRO DE IPANEMA | E83: IPANEMA
A84: 83 | B84: CET-RIO | C84: SOLICITA PROVIDÊNCIAS JUNTO À COMPANHIA DE ENGENHARIA DE TRÁFEGO DO RIO DE JANEIRO – CET-RIO E À SECRETARIA MUNICIPAL DE ORDEM PÚBLICA – SEOP, VISANDO A REPOSIÇÃO DE PLACAS DE SINALIZAÇÃO E FISCALIZAÇÃO DE ESTACIONAMENTO IRREGULAR NA RUA BARÃO DA TORRE, NO BAIRRO DE IPANEMA | E84: IPANEMA
A85: 84 | B85: SMAS | C85: SOLICITA PROVIDÊNCIAS JUNTO À SECRETARIA MUNICIPAL DE ASSISTÊNCIA SOCIAL – SMAS, REFERENTE ÀS AÇÕES NO PARQUE ESTADUAL DA CHACRINHA, LOCALIZADO NA RUA GUIMARÃES NATAL, S/N, NO BAIRRO DE COPACABANA | E85: COPACABANA
A86: 85 | B86: COMLURB | C86: SOLICITA PROVIDÊNCIAS JUNTO À COMPANHIA MUNICIPAL DE LIMPEZA URBANA – COMLURB E À SECRETARIA MUNICIPAL DE ORDEM PÚBLICA – SEOP, PARA VIABILIZAR LIMPEZA E MANUTENÇÃO DO PARQUE ESTADUAL DA CHACRINHA, NO BAIRRO DE COPACABANA | E86: COPACABANA
A87: 86 | B87: SMAS | C87: SOLICITA PROVIDÊNCIAS JUNTO À SECRETARIA MUNICIPAL DE ASSISTÊNCIA SOCIAL – SMAS, REFERENTE ÀS AÇÕES NA PRAÇA DO LARGO DO MACHADO, Nº 1, NO BAIRRO DO CATETE | E87: CATETE
A88: 87 | B88: COMLURB | C88: SOLICITA PROVIDÊNCIAS JUNTO À SECRETARIA MUNICIPAL DE CONSERVAÇÃO E SERVIÇOS PÚBLICOS – SECONSERVA E À COMPANHIA MUNICIPAL DE LIMPEZA URBANA – COMLURB, PARA VIABILIZAR MANUTENÇÃO NO PARQUE GAROTA DE IPANEMA, NO BAIRRO DE IPANEMA | E88: IPANEMA
A89: 88 | B89: SEOP | C89: SOLICITA PROVIDÊNCIAS JUNTO À SECRETARIA MUNICIPAL DE ORDEM PÚBLICA – SEOP E À GUARDA MUNICIPAL, VISANDO INTENSIFICAR AÇÕES DE ORDENAMENTO NA RUA HUMBERTO DE CAMPOS, NO BAIRRO DO LEBLON | E89: LEBLON
A90: 89 | B90: SEOP | C90: SOLICITA PROVIDÊNCIAS JUNTO À SECRETARIA MUNICIPAL DE ORDEM PÚBLICA – SEOP E À GUARDA MUNICIPAL, VISANDO INTENSIFICAR A FISCALIZAÇÃO NA RUA SIQUEIRA CAMPOS, Nº 20, NO BAIRRO DE COPACABANA | E90: COPACABANA
A91: 90 | B91: SEOP | C91: SOLICITA PROVIDÊNCIAS JUNTO À SECRETARIA MUNICIPAL DE ORDEM PÚBLICA – SEOP E À GUARDA MUNICIPAL, VISANDO FISCALIZAÇÃO DE ESTACIONAMENTO IRREGULAR NA CALÇADA DA PRAÇA GENERAL OSÓRIO, NO BAIRRO DE IPANEMA | E91: IPANEMA
A92: 91 | B92: SECONSERVA | C92: SOLICITA PROVIDÊNCIAS JUNTO À SECRETARIA MUNICIPAL DE CONSERVAÇÃO E SERVIÇOS PÚBLICOS – SECONSERVA, REFERENTE ÀS AÇÕES NA AVENIDA PADRE LEONEL FRANCA, Nº 261, NO BAIRRO DA GÁVEA | E92: GÁVEA
A93: 92 | B93: COMLURB | C93: SOLICITA PROVIDÊNCIAS JUNTO À COMPANHIA MUNICIPAL DE LIMPEZA URBANA – COMLURB, PARA VIABILIZAR PODA NA AVENIDA PADRE LEONEL FRANCA, Nº 261, NO BAIRRO DA GÁVEA | E93: GÁVEA
... A148: 147 | B148: SECONSERVA | C148: SOLICITA PROVIDÊNCIAS JUNTO À EMPRESA MUNICIPAL DE ILUMINAÇÃO URBANA – RIOLUZ E À SECRETARIA MUNICIPAL DE CONSERVAÇÃO E SERVIÇOS PÚBLICOS – SECONSERVA, REFERENTE A POSTES DANIFICADOS E EMPECILHOS À ACESSIBILIDADE NA RUA SÃO LUIZ GONZAGA, NO BAIRRO DE BENFICA | E148: BENFICA
A149: 148 | B149: SECONSERVA | C149: SOLICITA PROVIDÊNCIAS JUNTO À SECRETARIA MUNICIPAL DE CONSERVAÇÃO E SERVIÇOS PÚBLICOS – SECONSERVA, REFERENTE A AÇÕES DE CONSERVAÇÃO NA RUA SÃO LUIZ GONZAGA, NO BAIRRO DE SÃO CRISTÓVÃO
A150: 149 | B150: SEOP | C150: SOLICITA PROVIDÊNCIAS JUNTO À SECRETARIA MUNICIPAL DE ORDEM PÚBLICA – SEOP, REFERENTE À FISCALIZAÇÃO DE OBSTRUÇÃO DE ÁREA PÚBLICA NA RUA SENADOR SIMONSEN, NO BAIRRO DO JARDIM BOTÂNICO | E150: JARDIM BOTÂNICO
A151: 150 | B151: CET-RIO | C151: SOLICITA PROVIDÊNCIAS JUNTO À COMPANHIA DE ENGENHARIA DE TRÁFEGO DO RIO DE JANEIRO – CET-RIO, VISANDO REVITALIZAÇÃO DE SINALIZAÇÃO VERTICAL E HORIZONTAL NAS RUAS MIRANDA VALVERDE E GOETHE, NOS BAIRROS DO HUMAÍTA E BOTAFOGO, RESPECTIVAMENTE | E151: BOTAFOGO
A152: 151 | B152: COMLURB | C152: SOLICITA PROVIDÊNCIAS JUNTO À COMPANHIA MUNICIPAL DE LIMPEZA URBANA – COMLURB, PARA VIABILIZAR A PODA DE JAQUEIRAS NO MIRANTE DAS CANOAS, NA ESTRADA DAS CANOAS, Nº 2753, NO BAIRRO DE SÃO CONRADO | E152: SÃO CONRADO
A153: 152 | B153: CET-RIO | C153: SOLICITA PROVIDÊNCIAS JUNTO À COMPANHIA DE ENGENHARIA DE TRÁFEGO DO RIO DE JANEIRO – CET-RIO, VISANDO A REVITALIZAÇÃO DA SINALIZAÇÃO HORIZONTAL NA RUA JÚLIO DE CASTILHOS, ESQUINA COM RAUL POMPÉIA, NO BAIRRO DE COPACABANA | E153: COPACABANA
A154: 153 | B154: SEOP | C154: SOLICITA PROVIDÊNCIAS JUNTO À SECRETARIA MUNICIPAL DE ORDEM PÚBLICA – SEOP E À GUARDA MUNICIPAL, REFERENTE À FISCALIZAÇÃO DE CAMINHÃO SUPOSTAMENTE IRREGULAR DE RECICLÁVEIS NA AVENIDA NOSSA SENHORA DE COPACABANA, Nº 1236, NO BAIRRO DE COPACABANA | E154: COPACABANA
A155: 154 | B155: SEOP | C155: SOLICITA PROVIDÊNCIAS JUNTO À SECRETARIA MUNICIPAL DE ORDEM PÚBLICA – SEOP, REFERENTE A FESTAS SUPOSTAMENTE IRREGULARES NA ESTRADA DA PEDRA BONITA, Nº 140, NO ALTO DA BOA VISTA
A156: 155 | B156: SECONSERVA | C156: SOLICITA PROVIDÊNCIAS JUNTO À SECRETARIA MUNICIPAL DE CONSERVAÇÃO E SERVIÇOS PÚBLICOS – SECONSERVA, REFERENTE À REPOSIÇÃO DE AREIA NA QUADRA DE TÊNIS DA PRAÇA DO QUAFA, NO BAIRRO DE BANGU
A157: 156 | B157: COMLURB | C157: SOLICITA PROVIDÊNCIAS JUNTO À COMPANHIA MUNICIPAL DE LIMPEZA URBANA – COMLURB E À SECRETARIA MUNICIPAL DE ORDEM PÚBLICA – SEOP, REFERENTE À SUJEIRA CONSTANTE DECORRENTE DE AÇÕES PUBLICITÁRIAS NA RUA GENERAL URQUIZA COM RUA JOÃO DE BARROS, NO BAIRRO DO LEBLON | E157: LEBLON
A158: 157 | B158: COMLURB | C158: SOLICITA PROVIDÊNCIAS JUNTO À COMPANHIA MUNICIPAL DE LIMPEZA URBANA – COMLURB, PARA VIABILIZAR PODA NA RUA GILBERTO CARDOSO, Nº 300 E Nº 326, NO BAIRRO DO LEBLON | E158: LEBLON
A159: 158 | B159: SECONSERVA | C159: SOLICITA PROVIDÊNCIAS JUNTO À SECRETARIA MUNICIPAL DE CONSERVAÇÃO E SERVIÇOS PÚBLICOS – SECONSERVA, REFERENTE AO NIVELAMENTO DO PARQUE DAS CRIANÇAS, NA AVENIDA INFANTE DOM HENRIQUE, S/N, NO BAIRRO DO FLAMENGO | E159: FLAMENGO
A160: 159 | B160: RIOLUZ | C160: SOLICITA PROVIDÊNCIAS JUNTO À EMPRESA MUNICIPAL DE ILUMINAÇÃO URBANA – RIOLUZ, VISANDO A MELHORIA DA ILUMINAÇÃO NA RUA GORCEIX, NO BAIRRO DE IPANEMA | E160: IPANEMA
A161: 160 | B161: RIOLUZ | C161: SOLICITA PROVIDÊNCIAS JUNTO À EMPRESA MUNICIPAL DE ILUMINAÇÃO URBANA – RIOLUZ, VISANDO MELHORIA NA ILUMINAÇÃO NA RUA BARTOLOMEU MITRE, NA ALTURA DO Nº 705, NO BAIRRO DO LEBLON | E161: LEBLON
A162: 161 | B162: SECONSERVA | C162: SOLICITA PROVIDÊNCIAS JUNTO À SECRETARIA MUNICIPAL DE CONSERVAÇÃO E SERVIÇOS PÚBLICOS – SECONSERVA, REFERENTE AO REPARO DA CALÇADA DE PEDRA PORTUGUESA EM FRENTE À ESCOLA MUNICIPAL VITAL BRASIL, NA RUA DO CATETE, PRAÇA DO POETA, Nº 135, NO BAIRRO DO FLAMENGO | E162: FLAMENGO
A163: 162 | B163: SECONSERVA | C163: SOLICITA PROVIDÊNCIAS JUNTO À SECRETARIA MUNICIPAL DE CONSERVAÇÃO E SERVIÇOS PÚBLICOS – SECONSERVA, PARA VIABILIZAR A MANUTENÇÃO DO BICICLETÁRIO NO POSTO DE SAÚDE HÉLIO PELLEGRINO, NA RUA DO MATOSO, Nº 96, NO BAIRRO DA PRAÇA DA BANDEIRA | E163: TIJUCA
A164: 163 | B164: SECONSERVA | C164: SOLICITA PROVIDÊNCIAS JUNTO À SECRETARIA MUNICIPAL DE CONSERVAÇÃO E SERVIÇOS PÚBLICOS – SECONSERVA, PARA VIABILIZAR A INSTALAÇÃO DE BICICLETÁRIO NO MIRANTE DA GLÓRIA, NA RUA A, NO MORRO DA GLÓRIA | E164: GLÓRIA
A165: 164 | B165: SMAS | C165: SOLICITA PROVIDÊNCIAS JUNTO À SECRETARIA MUNICIPAL DE ASSISTÊNCIA SOCIAL – SMAS, REFERENTE ÀS AÇÕES DE ACOLHIMENTO EM FRENTE À ESCOLA MUNICIPAL VITAL BRASIL, NO BAIRRO DO FLAMENGO | E165: FLAMENGO
A166: 165 | B166: PMERJ | C166: SOLICITA PROVIDÊNCIAS JUNTO À POLÍCIA MILITAR DO ESTADO DO RIO DE JANEIRO – PMERJ, VISANDO INTENSIFICAÇÃO DAS AÇÕES DE SEGURANÇA NA RUA MARECHAL PIRES FERREIRA, NO BAIRRO DO COSME VELHO | E166: COSME VELHO
A167: 166 | B167: SEOP | C167: SOLICITA PROVIDÊNCIAS JUNTO À SECRETARIA MUNICIPAL DE ORDEM PÚBLICA – SEOP, REFERENTE À FISCALIZAÇÃO NA RUA ARTUR BERNARDES, NO BAIRRO DO CATETE | E167: CATETE
A168: 167 | B168: SMAS | C168: SOLICITA PROVIDÊNCIAS JUNTO À SECRETARIA MUNICIPAL DE ASSISTÊNCIA SOCIAL – SMAS, REFERENTE ÀS AÇÕES DE ACOLHIMENTO NA PRAÇA DO LARGO DO MACHADO, NO BAIRRO DO CATETE | E168: CATETE
... A178: 177 | B178: SMAS | C178: SOLICITA PROVIDÊNCIAS JUNTO À SECRETARIA MUNICIPAL DE ASSISTÊNCIA SOCIAL – SMAS E À SECRETARIA MUNICIPAL DE ORDEM PÚBLICA – SEOP, REFERENTE ÀS AÇÕES DE ACOLHIMENTO E ORDENAMENTO NA RUA VOLUNTÁRIOS DA PÁTRIA, Nº 452, NO BAIRRO DE BOTAFOGO | E178: BOTAFOGO
A179: 178 | B179: SEOP | C179: SOLICITA PROVIDÊNCIAS JUNTO À SECRETARIA MUNICIPAL DE ORDEM PÚBLICA – SEOP, REFERENTE À INSTALAÇÃO DE PORTÃO EM ÁREA PÚBLICA NA RUA CORONEL CAMISÃO, Nº 1001, NO BAIRRO DE CORDOVIL
A180: 179 | B180: SMAS | C180: SOLICITA PROVIDÊNCIAS JUNTO À SECRETARIA MUNICIPAL DE ORDEM PÚBLICA – SEOP E À SECRETARIA MUNICIPAL DE ASSISTÊNCIA SOCIAL – SMAS, REFERENTE ÀS AÇÕES DE ORDENAMENTO E ACOLHIMENTO NA PRAÇA INHANGÁ E ARREDORES, NO BAIRRO DE COPACABANA | E180: COPACABANA
A181: 180 | B181: SEOP | C181: SOLICITA PROVIDÊNCIAS JUNTO À SECRETARIA MUNICIPAL DE ORDEM PÚBLICA – SEOP, REFERENTE AO ORDENAMENTO DE TRÂNSITO NA BEIRA DA PRAIA DE SÃO CONRADO, NA ESTRADA DO JOÁ, Nº 1400 | E181: SÃO CONRADO
A182: 181 | B182: COMLURB | C182: SOLICITA PROVIDÊNCIAS JUNTO À COMPANHIA MUNICIPAL DE LIMPEZA URBANA – COMLURB E À SECRETARIA MUNICIPAL DE CONSERVAÇÃO E SERVIÇOS PÚBLICOS – SECONSERVA, REFERENTE À CONSERVAÇÃO E LIMPEZA DA PRAÇA PARIS, NO BAIRRO DA GLÓRIA | E182: GLÓRIA
A183: 182 | B183: SEOP | C183: SOLICITA PROVIDÊNCIAS JUNTO À SECRETARIA MUNICIPAL DE ORDEM PÚBLICA – SEOP, REFERENTE AO ORDENAMENTO NA RUA PAUL REDFERN, NO BAIRRO DE IPANEMA | E183: IPANEMA
A184: 183 | B184: SEOP | C184: SOLICITA PROVIDÊNCIAS JUNTO À SECRETARIA MUNICIPAL DE ORDEM PÚBLICA – SEOP, REFERENTE À FISCALIZAÇÃO DE BARULHO EXCESSIVO NA AVENIDA OLEGÁRIO MACIEL, ESQUINA COM A RUA JOÃO CARLOS MACHADO, NO BAIRRO DA BARRA DA TIJUCA | E184: BARRA DA TIJUCA
A185: 184 | B185: SEOP | C185: SOLICITA PROVIDÊNCIAS JUNTO À SECRETARIA MUNICIPAL DE ORDEM PÚBLICA – SEOP, REFERENTE À FISCALIZAÇÃO DE BICICLETAS E CARRINHOS DE ENTREGA OBSTRUINDO A PASSAGEM NA AVENIDA HENRIQUE DUMONT, Nº 85, NO BAIRRO DE IPANEMA | E185: IPANEMA
A186: 185 | B186: SECONSERVA | C186: SOLICITA PROVIDÊNCIAS JUNTO À SECRETARIA MUNICIPAL DE CONSERVAÇÃO E SERVIÇOS PÚBLICOS – SECONSERVA, PARA VIABILIZAR A INSTALAÇÃO DE BANHEIRO PÚBLICO NA PRAIA VERMELHA, NA PRAÇA GENERAL TIBÚRCIO, Nº 75, NO BAIRRO DA URCA | E186: URCA
A187: 186 | B187: SECONSERVA | C187: SOLICITA PROVIDÊNCIAS JUNTO À SECRETARIA MUNICIPAL DE CONSERVAÇÃO E SERVIÇOS PÚBLICOS – SECONSERVA, PARA VIABILIZAR O REPARO DE CANTEIROS E DO ASFALTO AO LADO DA PRAÇA DO LARGO DO MACHADO, NO BAIRRO DO CATETE | E187: CATETE
A188: 187 | B188: SEOP | C188: SOLICITA PROVIDÊNCIAS JUNTO À SECRETARIA MUNICIPAL DE ORDEM PÚBLICA – SEOP E À GUARDA MUNICIPAL, REFERENTE À FISCALIZAÇÃO DE TERRENO INVADIDO NA RUA REAL GRANDEZA, Nº 20, NO BAIRRO DE BOTAFOGO | E188: BOTAFOGO
A189: 188 | B189: SEOP | C189: SOLICITA PROVIDÊNCIAS JUNTO À SECRETARIA MUNICIPAL DE ORDEM PÚBLICA – SEOP, REFERENTE À FISCALIZAÇÃO DE BARRAQUEIROS IRREGULARES NO ARMAZÉM UTOPIA, NA AVENIDA RODRIGUES ALVES, S/N, NO BAIRRO DO SANTO CRISTO
A190: 189 | B190: SEOP | C190: SOLICITA PROVIDÊNCIAS JUNTO À SECRETARIA MUNICIPAL DE ORDEM PÚBLICA – SEOP, REFERENTE À FISCALIZAÇÃO DE ACESSO BLOQUEADO À CACHOEIRA DO SANTINHO, NO HORTO, NA ESTRADA DAS PAINEIRAS, S/N, NO BAIRRO DE SANTA TERESA | E190: SANTA TERESA
A191: 190 | B191: SECONSERVA | C191: SOLICITA PROVIDÊNCIAS JUNTO À SECRETARIA MUNICIPAL DE CONSERVAÇÃO E SERVIÇOS PÚBLICOS – SECONSERVA, REFERENTE AO REPARO DA CALÇADA DE CIMENTO NA AVENIDA NOSSA SENHORA DE COPACABANA, Nº 722, NO BAIRRO DE COPACABANA | E191: COPACABANA
A192: 191 | B192: COMLURB | C192: SOLICITA PROVIDÊNCIAS JUNTO À COMPANHIA MUNICIPAL DE LIMPEZA URBANA – COMLURB, PARA VIABILIZAR PODA NA RUA JARDIM BOTÂNICO, PRÓXIMO AO Nº 31, NO BAIRRO DO JARDIM BOTÂNICO | E192: JARDIM BOTÂNICO
A193: 192 | B193: COMLURB | C193: SOLICITA PROVIDÊNCIAS JUNTO À COMPANHIA MUNICIPAL DE LIMPEZA URBANA – COMLURB, PARA VIABILIZAR A MANUTENÇÃO DOS BRINQUEDOS NA PRAÇA DO LIDO, NO BAIRRO DE COPACABANA | E193: COPACABANA
A194: 193 | B194: SEOP | C194: SOLICITA PROVIDÊNCIAS JUNTO À SECRETARIA MUNICIPAL DE ORDEM PÚBLICA – SEOP, REFERENTE À FISCALIZAÇÃO DE "SHOPPING-CHÃO" NA RUA NOSSA SENHORA DE COPACABANA, Nº 454, NO BAIRRO DE COPACABANA | E194: COPACABANA
A195: 194 | B195: RIOLUZ | C195: SOLICITA PROVIDÊNCIAS JUNTO À EMPRESA MUNICIPAL DE ILUMINAÇÃO URBANA – RIOLUZ, VISANDO A INSTALAÇÃO OU REPARO DE ILUMINAÇÃO PÚBLICA NA RUA PROFESSOR MANUEL FERREIRA, NO BAIRRO DA GÁVEA | E195: GÁVEA
A196: 195 | B196: CET-RIO | C196: SOLICITA PROVIDÊNCIAS JUNTO À COMPANHIA DE ENGENHARIA DE TRÁFEGO DO RIO DE JANEIRO – CET-RIO, REFERENTE À INSTALAÇÃO DE PLACA DE SINALIZAÇÃO VERTICAL "PRIORIDADE DO PEDESTRE" NA RUA GUILHERMINA GUINLE, ESQUINA COM A RUA VOLUNTÁRIOS DA PÁTRIA, NO BAIRRO DE BOTAFOGO | E196: BOTAFOGO
A197: 196 | B197: COMLURB | C197: SOLICITA PROVIDÊNCIAS JUNTO À COMPANHIA MUNICIPAL DE LIMPEZA URBANA – COMLURB, À SECRETARIA MUNICIPAL DE ORDEM PÚBLICA – SEOP E À EMPRESA MUNICIPAL DE ILUMINAÇÃO URBANA – RIOLUZ, REFERENTE À MANUTENÇÃO, LIMPEZA E ILUMINAÇÃO DA PRAÇA CHAIM WEIZMANN, NO BAIRRO DE BOTAFOGO | E197: BOTAFOGO
A198: 197 | B198: SEOP | C198: SOLICITA PROVIDÊNCIAS JUNTO À SECRETARIA MUNICIPAL DE ORDEM PÚBLICA – SEOP, REFERENTE À FISCALIZAÇÃO DE CAMINHÕES SENDO USADOS COMO DEPÓSITO NA EXTENSÃO DA RUA TEIXEIRA DE MELO, NO BAIRRO DE IPANEMA | E198: IPANEMA
A199: 198 | B199: COMLURB | C199: SOLICITA PROVIDÊNCIAS JUNTO À COMPANHIA MUNICIPAL DE LIMPEZA URBANA – COMLURB, À SECRETARIA MUNICIPAL DE CONSERVAÇÃO E SERVIÇOS PÚBLICOS – SECONSERVA E À EMPRESA MUNICIPAL DE ILUMINAÇÃO URBANA – RIOLUZ, REFERENTE À MANUTENÇÃO DE BRINQUEDOS E ILUMINAÇÃO NA PRAÇA EM FRENTE AO HOSPITAL ROCHA MAIA, NO BAIRRO DE BOTAFOGO | E199: BOTAFOGO
A200: 199 | B200: COMLURB | C200: SOLICITA PROVIDÊNCIAS JUNTO À COMPANHIA MUNICIPAL DE LIMPEZA URBANA – COMLURB, PARA VIABILIZAR A LIMPEZA DA PRAIA DE BOTAFOGO, NO BAIRRO DE BOTAFOGO | E200: BOTAFOGO
A201: 200 | B201: COMLURB | C201: SOLICITA PROVIDÊNCIAS JUNTO À COMPANHIA MUNICIPAL DE LIMPEZA URBANA – COMLURB, PARA VIABILIZAR A LIMPEZA NO ENTORNO DO THEATRO MUNICIPAL DO RIO DE JANEIRO, NO CENTRO | E201: CENTRO
... A229: 228 | B229: SEOP | C229: SOLICITA PROVIDÊNCIAS JUNTO À SECRETARIA MUNICIPAL DE ORDEM PÚBLICA – SEOP, REFERENTE AO ORDENAMENTO DOS CAMELÔS NO LARGO DO MACHADO, NO BAIRRO DO CATETE | E229: CATETE
A230: 229 | B230: SECONSERVA | C230: SOLICITA PROVIDÊNCIAS JUNTO À SECRETARIA MUNICIPAL DE CONSERVAÇÃO E SERVIÇOS PÚBLICOS – SECONSERVA E À SECRETARIA MUNICIPAL DE ORDEM PÚBLICA – SEOP, REFERENTE AO ESTACIONAMENTO IRREGULAR NA RUA VITOR MEIRELES, NO BAIRRO DO RIACHUELO
A231: 230 | B231: SEOP | C231: SOLICITA PROVIDÊNCIAS JUNTO À SECRETARIA MUNICIPAL DE ORDEM PÚBLICA – SEOP, REFERENTE À FISCALIZAÇÃO E ORDENAMENTO NO ATERRO DO FLAMENGO, NO BAIRRO DO FLAMENGO | E231: FLAMENGO
A232: 231 | B232: SEOP | C232: SOLICITA PROVIDÊNCIAS JUNTO À SECRETARIA MUNICIPAL DE ORDEM PÚBLICA – SEOP E À SECRETARIA MUNICIPAL DE ASSISTÊNCIA SOCIAL – SMAS, REFERENTE À FISCALIZAÇÃO E AÇÕES DE ASSISTÊNCIA NA PRAÇA COMPOSITOR MAURO DUARTE, NA RUA GENERAL POLIDORO, NO BAIRRO DE BOTAFOGO | E232: BOTAFOGO
A233: 232 | B233: SEOP | C233: SOLICITA PROVIDÊNCIAS JUNTO À SECRETARIA MUNICIPAL DE ORDEM PÚBLICA – SEOP, REFERENTE À RETIRADA DE BICICLETAS ABANDONADAS NA LADEIRA DOS TABAJARAS, Nº 20, NO BAIRRO DE COPACABANA | E233: COPACABANA
A234: 233 | B234: CET-RIO | C234: SOLICITA PROVIDÊNCIAS JUNTO À COMPANHIA DE ENGENHARIA DE TRÁFEGO DO RIO DE JANEIRO – CET-RIO, REFERENTE À REVITALIZAÇÃO DA SINALIZAÇÃO HORIZONTAL E VERTICAL NA AVENIDA LINEU DE PAULA MACHADO, Nº 795, NO BAIRRO DO JARDIM BOTÂNICO | E234: JARDIM BOTÂNICO
A235: 234 | B235: SEOP | C235: SOLICITA PROVIDÊNCIAS JUNTO À SECRETARIA MUNICIPAL DE ORDEM PÚBLICA – SEOP, REFERENTE AO ORDENAMENTO NO PARQUE DOS PATINS, NA AVENIDA BORGES DE MEDEIROS, NO BAIRRO DA LAGOA | E235: LAGOA
A236: 235 | B236: SMAS | C236: SOLICITA PROVIDÊNCIAS JUNTO À SECRETARIA MUNICIPAL DE ASSISTÊNCIA SOCIAL – SMAS, REFERENTE ÀS AÇÕES DE ACOLHIMENTO NO LARGO DO MACHADO E NO BAIRRO DO FLAMENGO | E236: FLAMENGO
A237: 236 | B237: SECONSERVA | C237: SOLICITA PROVIDÊNCIAS JUNTO À SECRETARIA MUNICIPAL DE CONSERVAÇÃO E SERVIÇOS PÚBLICOS – SECONSERVA, PARA VIABILIZAR A REFORMA DA CALÇADA NO LARGO SÉRGIO VIEIRA DE MELLO, NO BAIRRO DO LEBLON | E237: LEBLON
A238: 237 | B238: RIOLUZ | C238: SOLICITA PROVIDÊNCIAS JUNTO À EMPRESA MUNICIPAL DE ILUMINAÇÃO URBANA – RIOLUZ E À LIGHT, REFERENTE À PODA DE ÁRVORE SECA NA RUA MARECHAL RAMON CASTILLA (LATERAL DO Nº 25) E EM FRENTE À RUA LAURO MULLER, Nº 16, NO BAIRRO DE BOTAFOGO | E238: BOTAFOGO
A239: 400 | B239: COMLURB | C239: SOLICITA PROVIDÊNCIAS JUNTO À COMPANHIA MUNICIPAL DE LIMPEZA URBANA – COMLURB, PARA VIABILIZAR A PODA DE ÁRVORE NA RUA MARECHAL RAMON CASTILLA, APÓS O PRÉDIO Nº 134, NO BAIRRO DE BOTAFOGO | E239: BOTAFOGO
A240: 400 | B240: SEOP | C240: SOLICITA PROVIDÊNCIAS JUNTO À SECRETARIA MUNICIPAL DE ORDEM PÚBLICA – SEOP, REFERENTE À FISCALIZAÇÃO DE KOMBIS DE FERRO-VELHO CAUSANDO PERTURBAÇÃO DO SOSSEGO NA RUA SACOPÃ, NO BAIRRO DA LAGOA | E240: LAGOA
A241: 400 | B241: SECONSERVA | C241: SOLICITA PROVIDÊNCIAS JUNTO À SECRETARIA MUNICIPAL DE CONSERVAÇÃO E SERVIÇOS PÚBLICOS – SECONSERVA, PARA VIABILIZAR O RECAPEAMENTO DE CIMENTO DO REDONDO DA PRAÇA MARCOS TAMOYO, NA RUA FREI VELOSO, NO BAIRRO DA LAGOA | E241: LAGOA
A242: 400 | B242: CET-RIO | C242: SOLICITA PROVIDÊNCIAS JUNTO À COMPANHIA DE ENGENHARIA DE TRÁFEGO DO RIO DE JANEIRO – CET-RIO, VISANDO A REALIZAÇÃO DE ESTUDO DE VIABILIDADE PARA CONSTRUÇÃO DE QUEBRA-MOLAS PRÓXIMO AO PATRONATO DA GÁVEA, NA AVENIDA LINEU DE PAULA MACHADO, Nº 795, NO BAIRRO DO JARDIM BOTÂNICO | E242: JARDIM BOTÂNICO
... A252: 400 | B252: PMERJ | C252: SOLICITA PROVIDÊNCIAS JUNTO À POLÍCIA MILITAR DO ESTADO DO RIO DE JANEIRO – PMERJ, REFERENTE À OCUPAÇÃO DA CICLOVIA POR VIATURAS NA RUA FIGUEIREDO MAGALHÃES, EM FRENTE AO BATALHÃO DE COPACABANA | E252: COPACABANA
A253: 400 | B253: SEOP | C253: SOLICITA PROVIDÊNCIAS JUNTO À SECRETARIA MUNICIPAL DE ORDEM PÚBLICA – SEOP, À GUARDA MUNICIPAL E À COMPANHIA DE ENGENHARIA DE TRÁFEGO DO RIO DE JANEIRO – CET-RIO, REFERENTE AO ORDENAMENTO DE TRÂNSITO NO ENTORNO DA RODOVIÁRIA, NA AVENIDA FRANCISCO BICALHO, Nº 01, NO BAIRRO DE SANTO CRISTO
A254: 400 | B254: SEOP | C254: SOLICITA PROVIDÊNCIAS JUNTO À SECRETARIA MUNICIPAL DE ORDEM PÚBLICA – SEOP, REFERENTE À FISCALIZAÇÃO DE OBRA IRREGULAR NA RUA 3, NA COMUNIDADE DO VIDIGAL | E254: VIDIGAL
A255: 400 | B255: SEOP | C255: SOLICITA PROVIDÊNCIAS JUNTO À SECRETARIA MUNICIPAL DE ORDEM PÚBLICA – SEOP E À GUARDA MUNICIPAL, REFERENTE AO ORDENAMENTO NO PONTO DE ÔNIBUS DA AVENIDA AFRÂNIO DE MELLO FRANCO, EM FRENTE AO Nº 305, NO BAIRRO DO LEBLON | E255: LEBLON
...

Sheet Assessoria de Imprensa
A1: TIPO | B1: DATA | C1: MÊS | D1: ASSUNTO | E1: TITULO | F1: VEÍCULO | G1: JORNALISTA | H1: LINK | I1: ASPAS | J1: CITAÇÃO
A2: RELEASE | B2: 45681 | C2: =(IF(ISBLANK(B2),"",TEXT(DATE(MID(B2,7,4), MID(B2,4,2), MID(B2,1,2)), "mm/yyyy"))) -> 01/2025 | D2: Combate ao Antissemitismo | E2: O custo do antissemitismo para o turismo brasileiro | F2: VEJA RIO | G2: LU LACERDA | H2: https://vejario.abril.com.br/coluna/lu-lacerda/o-custo-do-antissemitismo-para-o-turismo-brasileiro/ | I2: Segundo dados do gabinete, mais ou menos 11,9 mil israelenses judeus visitaram o Brasil no ano passado (dados da Embratur), com uma movimentação de R$ 54,5 milhões (dados do Banco Central). “Um país plural e diverso não pode ter uma perda significativa no turismo, setor que somos referência, por atitudes antissemitas”, diz o vereador.
A3: RELEASE | B3: 45683 | C3: =(IF(ISBLANK(B3),"",TEXT(DATE(MID(B3,7,4), MID(B3,4,2), MID(B3,1,2)), "mm/yyyy"))) -> 01/2025 | D3: Combate ao Antissemitismo | E3: Sobrevivente do holocausto: é preciso denunciar apologias ao nazismo | F3: AGENCIA BRASIL | G3: Mariana Tokarnia | H3: https://agenciabrasil.ebc.com.br/geral/noticia/2025-01/sobrevivente-do-holocausto-e-preciso-denunciar-apologias-ao-nazismo | J3: O evento no Palácio da Cidade, sob o tema 80 anos depois: Memória, Resistência e Esperança, foi uma ação colaborativa entre o vereador Flávio Valle e a Federação Israelita do Estado do Rio de Janeiro (FIERJ) e com apoios da Prefeitura, e da Confederação Israelita do Brasil (Conib). A cerimônia reuniu autoridades, sobreviventes do Holocausto e seus descendentes, políticos e autoridades eclesiais. | W3: MÊS | X3: Causa Animal | Y3: Combate ao Antissemitismo | Z3: Conservação | AA3: Economia | AB3: Esporte e Lazer | AC3: Gabinete | AD3: Meio Ambiente | AE3: Ordenamento | AF3: Saúde | AG3: Segurança | AH3: Turismo | AK3: MÊS | AL3: NOTA | AM3: COLUNA | AN3: ENTREVISTA | AO3: MATÉRIA | AP3: ARTIGO | AQ3: NOTÍCIA | AR3: REDAÇÃO | AS3: REPORTAGEM | AT3: RELEASE
A4: RELEASE | B4: 45683 | C4: =(IF(ISBLANK(B4),"",TEXT(DATE(MID(B4,7,4), MID(B4,4,2), MID(B4,1,2)), "mm/yyyy"))) -> 01/2025 | D4: Combate ao Antissemitismo | E4: Comunidade judaica homenageia vítimas do Holocausto em evento na Zona Sul | F4: O DIA | G4: REDAÇÃO | H4: https://odia.ig.com.br/rio-de-janeiro/2025/01/6992495-comunidade-judaica-homenageia-vitimas-do-holocausto-em-evento-na-zona-sul.html | I4: O vereador Flávio Valle, que é judeu, destacou a importância do enfrentamento ao preconceito contra judeus: "O combate ao antissemitismo não é apenas uma questão de memória histórica, mas uma necessidade urgente da atualidade". | W4: janeiro/2025 | Y4: 9 | AK4: janeiro/2025 | AL4: Agendas! | AP4: 1 | AT4: 7
A5: RELEASE | B5: 45683 | C5: =(IF(ISBLANK(B5),"",TEXT(DATE(MID(B5,7,4), MID(B5,4,2), MID(B5,1,2)), "mm/yyyy"))) -> 01/2025 | D5: Combate ao Antissemitismo | E5: Comunidade judaica do Rio presta homenagem às vítimas do Holocausto em evento no Palácio da Cidade | F5: DIÁRIO DO RIO | G5: QUINTINO GOMES FREIRE | H5: https://diariodorio.com/comunidade-judaica-do-rio-presta-homenagem-as-vitimas-do-holocausto-em-evento-no-palacio-da-cidade/ | I5: O vereador Flávio Valle reforçou a necessidade de combater o antissemitismo de forma contínua. “O combate ao antissemitismo não é apenas uma questão de memória histórica, mas uma necessidade urgente da atualidade. No parlamento, seguirei promovendo iniciativas legislativas que garantam a segurança da comunidade judaica, a educação sobre o Holocausto e a defesa dos direitos humanos”, afirmou. | J5: O evento, realizado sob o tema “80 anos depois: Memória, Resistência e Esperança”, foi fruto de uma parceria entre o vereador Flávio Valle, a Federação Israelita do Estado do Rio de Janeiro (FIERJ), a Prefeitura do Rio e a Confederação Israelita do Brasil (Conib). Amanhã, 27 de janeiro, o mundo celebra o Dia Internacional em Memória das Vítimas do Holocausto, instituído pela ONU em 2005, através da Resolução 60/7. | W5: fevereiro/2025 | Y5: 5 | AC5: 4 | AD5: 2 | AE5: 2 | AG5: 2 | AH5: 3 | AK5: fevereiro/2025 | AL5: 6 | AP5: 1 | AT5: 11
A6: ARTIGO | B6: 45684 | C6: =(IF(ISBLANK(B6),"",TEXT(DATE(MID(B6,7,4), MID(B6,4,2), MID(B6,1,2)), "mm/yyyy"))) -> 01/2025 | D6: Combate ao Antissemitismo | E6: O Holocausto foi o ápice do antissemitismo, mas não o seu fim | F6: DIÁRIO DO RIO | G6: FLÁVIO VALLE | H6: https://diariodorio.com/o-holocausto-foi-o-apice-do-antissemitismo-mas-nao-seu-fim/ | W6: março/2025 | Y6: 1 | AA6: 1 | AC6: 5 | AH6: 18 | AK6: março/2025 | AL6: 15 | AM6: 1 | AO6: 1 | AP6: 1 | AS6: 1 | AT6: 6
A7: RELEASE | B7: 45684 | C7: =(IF(ISBLANK(B7),"",TEXT(DATE(MID(B7,7,4), MID(B7,4,2), MID(B7,1,2)), "mm/yyyy"))) -> 01/2025 | D7: Combate ao Antissemitismo | E7: Tem que combater’, diz sobrevivente do Holocausto sobre apologia ao nazismo | F7: AMAZONAS ATUAL | G7: REDAÇÃO | H7: https://amazonasatual.com.br/tem-que-combater-diz-sobrevivente-do-holocausto-sobre-apologia-ao-nazismo/ | J7: O evento no Palácio da Cidade, sob o tema 80 anos depois: Memória, Resistência e Esperança, foi uma ação colaborativa entre o vereador Flávio Valle e a Federação Israelita do Estado do Rio de Janeiro (FIERJ) e com apoios da Prefeitura, e da Confederação Israelita do Brasil (Conib). A cerimônia reuniu autoridades, sobreviventes do Holocausto e seus descendentes, políticos e autoridades eclesiais. | W7: abril/2025 | X7: 1 | Y7: 1 | AA7: 1 | AB7: 1 | AC7: 1 | AD7: 3 | AE7: 3 | AH7: 1 | AK7: abril/2025 | AL7: 2 | AT7: 10
A8: NOTA | B8: 45684 | C8: =(IF(ISBLANK(B8),"",TEXT(DATE(MID(B8,7,4), MID(B8,4,2), MID(B8,1,2)), "mm/yyyy"))) -> 01/2025 | D8: Combate ao Antissemitismo | E8: É preciso denunciar apologias ao nazismo, diz sobrevivente do Holocausto em cerimônia no Rio | F8: R7 | H8: https://noticias.r7.com/cidades/e-preciso-denunciar-apologias-ao-nazismo-diz-sobrevivente-do-holocausto-em-cerimonia-no-rio-27012025/ | J8: O evento no Palácio da Cidade, sob o tema ’80 anos depois: Memória, Resistência e Esperança', foi uma ação colaborativa entre o vereador Flávio Valle e a FIERJ (Federação Israelita do Estado do Rio de Janeiro) e com apoios da Prefeitura, e da Conib (Confederação Israelita do Brasil). | W8: maio/2025 | Y8: 9 | Z8: 1 | AC8: 11 | AD8: 1 | AE8: 43 | AH8: 4 | AK8: maio/2025 | AL8: 40 | AM8: 2 | AN8: 1 | AQ8: 1 | AR8: 1 | AT8: 24
A9: RELEASE | B9: 45684 | C9: =(IF(ISBLANK(B9),"",TEXT(DATE(MID(B9,7,4), MID(B9,4,2), MID(B9,1,2)), "mm/yyyy"))) -> 01/2025 | D9: Combate ao Antissemitismo | E9: Comunidade judaica do RJ presta homenagem às vítimas do Holocausto em evento no Palácio da Cidade | F9: Conib | H9: https://conib.org.br/noticias-conib/39403-comunidade-judaica-do-rj-presta-homenagem-as-vitimas-do-holocausto-em-evento-no-palacio-da-cidade.html | I9: "O combate ao antissemitismo não é apenas uma questão de memória histórica, mas uma necessidade urgente da atualidade. Como vereador do Rio de Janeiro levo essa bandeira para dentro do parlamento e continuarei trabalhando para que a nossa cidade se torne um modelo no combate ao antissemitismo, promovendo iniciativas legislativas que garantam a segurança da comunidade judaica, a educação sobre o Holocausto e a defesa dos direitos humanos", disse o vereador Flávio Valle. | J9: Flávio Valle também anunciou o estudo realizado por seu gabinete que aponta o custo do antissemitismo para o turismo brasileiro. Segundo dados levantados pelo gabinete do vereador, cerca de 11,9 mil israelenses judeus visitaram o Brasil no ano passado (dados da Embratur), com um impacto na economia brasileira de aproximadamente R$54,5 milhões (dados do Banco Central). | W9: junho/2025 | Y9: 30 | Z9: 2 | AC9: 1 | AE9: 5 | AF9: 1 | AH9: 3 | AK9: junho/2025 | AL9: 28 | AM9: 4 | AT9: 10
A10: RELEASE | B10: 45687 | C10: =(IF(ISBLANK(B10),"",TEXT(DATE(MID(B10,7,4), MID(B10,4,2), MID(B10,1,2)), "mm/yyyy"))) -> 01/2025 | D10: Combate ao Antissemitismo | E10: Câmara do rio remove pichação com suástica nazista em um de seus banheiros | F10: O GLOBO | G10: JOÃO PAULO SACCONI | H10: https://oglobo.globo.com/blogs/lauro-jardim/post/2025/01/camara-do-rio-remove-pichacao-com-suastica-nazista-em-um-de-seus-banheiros.ghtml
A11: ARTIGO | B11: 45684 | C11: =(IF(ISBLANK(B11),"",TEXT(DATE(MID(B11,7,4), MID(B11,4,2), MID(B11,1,2)), "mm/yyyy"))) -> 01/2025 | D11: Combate ao Antissemitismo | E11: O Holocausto foi o ápice do antissemitismo, mas não o seu fim | F11: DIARIO DO RIO | G11: FLAVIO VALLE | H11: https://diariodorio.com/o-holocausto-foi-o-apice-do-antissemitismo-mas-nao-seu-fim/
A12: ARTIGO | B12: 45691 | C12: =(IF(ISBLANK(B12),"",TEXT(DATE(MID(B12,7,4), MID(B12,4,2), MID(B12,1,2)), "mm/yyyy"))) -> 02/2025 | D12: Turismo | E12: O impulso para alavancar tecnologia, sustentabilidade e finanças no Rio de Janeiro | F12: DIÁRIO DO RIO | G12: FLAVIO VALLE | H12: https://diariodorio.com/o-impulso-para-alavancar-tecnologia-sustentabilidade-e-financas-no-rio-de-janeiro-flaviovalle/
A13: NOTA | B13: 45693 | C13: =(IF(ISBLANK(B13),"",TEXT(DATE(MID(B13,7,4), MID(B13,4,2), MID(B13,1,2)), "mm/yyyy"))) -> 02/2025 | D13: Mandato | E13: Vindo de bons resultados, Câmara terá pelada situação x oposição | F13: TEMPO REAL | G13: VITOR D'AVILA | H13: https://temporealrj.com/vindo-de-bons-resultados-camara-tera-pelada-situacao-x-oposicao/ | J13: Nesta quinta-feira (6), acontecerá a pelada situação x oposição. Do lado dos mais chegados ao prefeito Eduardo Paes (PSD), estará o vereador Flávio Valle capitaneando o time. Já o combinado adversário será encabeçado por Pedro Duarte (Novo). Só não vale ir na canela!
A14: NOTA | B14: 45695 | C14: =(IF(ISBLANK(B14),"",TEXT(DATE(MID(B14,7,4), MID(B14,4,2), MID(B14,1,2)), "mm/yyyy"))) -> 02/2025 | D14: Mandato | E14: Pelada entre situação e oposição da Câmara de Vereadores termina empatada | F14: TEMPO REAL | G14: VITOR D'AVILA | H14: https://temporealrj.com/pelada-entre-situacao-e-oposicao-da-camara-de-vereadores-termina-empatada/ | J14: Ao menos no futebol, situação e oposição da Câmara de Vereadores do Rio estão em pé de igualdade. O jogo de futebol entre os gabinetes dos vereadores Pedro Duarte (Novo) e Flávio Valle (PSD), na noite de quinta-feira (6), foi bastante combativo, como se fala no jargão político, mas terminou com placar empatado.
A15: RELEASE | B15: 45698 | C15: =(IF(ISBLANK(B15),"",TEXT(DATE(MID(B15,7,4), MID(B15,4,2), MID(B15,1,2)), "mm/yyyy"))) -> 02/2025 | D15: Ordenamento | E15: Vereador Flávio Valle participa de ação educativa sobre uso das vias fechadas na orla da Zona Sul | F15: DIÁRIO DO RIO | G15: QUINTINO GOMES FREIRE | H15: https://diariodorio.com/vereador-flavio-valle-participa-de-acao-educativa-sobre-uso-das-vias-fechadas-na-orla-da-zona-sul/ | I15: “Atualmente, uma simples caminhada pela orla nas áreas fechadas para lazer aos domingos e feriados pode representar um risco considerável de sofrer um acidente. Não são poucos os condutores de motos e bicicletas elétricas que circulam em alta velocidade nessas vias, causando transtornos para os pedestres, principalmente para crianças e idosos. Esperamos que essas ações colaborem com a conscientização de todos sobre a importância de se respeitar as regras estabelecidas para o bom convívio entre todos”, destacou Valle. | J15: Na manhã deste domingo (9), o vereador Flávio Valle participou de uma ação educativa promovida pela Prefeitura do Rio, com o objetivo de conscientizar usuários sobre a proibição da circulação de bicicletas e bikes elétricas nas vias fechadas para lazer aos domingos e feriados.
A16: RELEASE | B16: 45705 | C16: =(IF(ISBLANK(B16),"",TEXT(DATE(MID(B16,7,4), MID(B16,4,2), MID(B16,1,2)), "mm/yyyy"))) -> 02/2025 | D16: Meio Ambiente | E16: Tem até gavião carijó aparecendo na naturalizada Lagoa Rodrigo de Freitas | F16: O GLOBO | G16: NELSON LIMA NETO | H16: https://oglobo.globo.com/blogs/ancelmo-gois/post/2025/02/tem-ate-gaviao-carijo-aparecendo-na-naturalizada-lagoa-rodrigo-de-freitas.ghtml
A17: RELEASE | B17: 45706 | C17: =(IF(ISBLANK(B17),"",TEXT(DATE(MID(B17,7,4), MID(B17,4,2), MID(B17,1,2)), "mm/yyyy"))) -> 02/2025 | D17: Combate ao Antissemitismo | E17: Vereador apresenta três propostas para combater o antissemitismo no Rio | F17: DIÁRIO DO RIO | G17: QUINTINO GOMES FREIRE | H17: https://diariodorio.com/vereador-apresenta-tres-propostas-para-combater-o-antissemitismo-no-rio/ | I17: “Infelizmente, o ódio contra os judeus ainda persiste, algumas vezes de forma explícita e em outras, disfarçado sob diferentes pretextos. O Rio é uma cidade turística, reconhecida por sua diversidade e pluralidade, e não podemos normalizar o preconceito, a hostilidade ou a discriminação. Conto com meus colegas vereadores para institucionalizar essa pauta na Câmara Municipal e servir de exemplo para outras cidades”, afirmou o vereador | J17: O vereador Flávio Valle (PSD) segue empenhado no combate ao antissemitismo na cidade do Rio de Janeiro. Após garantir que a Prefeitura do Rio fosse a primeira do Brasil a adotar a definição de antissemitismo estabelecida pela Aliança Internacional para a Memória do Holocausto (IHRA), em novembro de 2023, o parlamentar agora leva a pauta para a Câmara Municipal.
A18: RELEASE | B18: 45707 | C18: =(IF(ISBLANK(B18),"",TEXT(DATE(MID(B18,7,4), MID(B18,4,2), MID(B18,1,2)), "mm/yyyy"))) -> 02/2025 | D18: Segurança | E18: Lei anti-Oruam: 'Menores são vítimas e até algozes do crime', diz vereador do Rio | F18: REVISTA OESTE | G18: EUGENIO GOUSSINSKY | H18: https://revistaoeste.com/brasil/lei-anti-oruammenores-sao-vitimas-e-ate-algozes-do-crime-diz-vereador-do-rio-de-janeiro/ | I18: "O texto tem que estar muito bem escrito para não abrir brechas que o enfraqueçam, a música é um instrumento de cultura para criticar certos comportamentos da sociedade, há uma linha tênue entre o que é crítica e o que é apologia", ', alerta Valle, que se coloca como favorável ao projeto. | J18: Na tramitação do projeto, antes de ser votado, alguns vereadores, como Flávio Valle (PSD), buscarão definir o limiar entre liberdade de expressão e apologia do crime.
A19: RELEASE | B19: 45707 | C19: =(IF(ISBLANK(B19),"",TEXT(DATE(MID(B19,7,4), MID(B19,4,2), MID(B19,1,2)), "mm/yyyy"))) -> 02/2025 | D19: Turismo | E19: Visit Rio celebra nomeação de Flávio Valle (PSD) como presidente da Comissão de Turismo da Câmara Municipal do RJ | F19: MERCADO E EVENTOS | G19: JANAÍNA BRITO | H19: https://www.mercadoeeventos.com.br/noticias/politica/visit-rio-celebra-nomeacao-de-flavio-valle-psd-como-presidente-da-comissao-de-turismo-da-camara-municipal-do-rj/ | I19: "O turismo é um dos principais motores da economia carioca, gerando empregos, impulsionando o desenvolvimento regional e promovendo a preservação cultural. O Visit Rio acredita que a renovação e a presença de jovens lideranças contribuem para a pluralidade de ideias. Reforçamos nosso compromisso com o fortalecimento do setor e nos colocamos à disposição para contribuir com sua atuação em prol do turismo na cidade", afirmou a entidade. | J19: O Visit Rio Convention Bureau celebrou, em nota enviada à imprensa, a nomeação do vereador Flávio Valle (PSD) como presidente da Comissão de Turismo da Câmara Municipal do Rio de Janeiro. Flávio, que foi subprefeito da Zona Sul, é reconhecido como uma promissora liderança do Rio e está apto a impulsionar políticas que beneficiem a cidade e o turismo.
A20: RELEASE | B20: 45708 | C20: =(IF(ISBLANK(B20),"",TEXT(DATE(MID(B20,7,4), MID(B20,4,2), MID(B20,1,2)), "mm/yyyy"))) -> 02/2025 | D20: Combate ao Antissemitismo | E20: Câmara do Rio terá Frente Parlamentar de Combate ao Antissemitismo | F20: CÂMARA MUNICIPAL DOS VEREADORES | H20: https://www.camara.rio/comunicacao/noticias/2505-camara-do-rio-tera-frente-parlamentar-de-combate-ao-antissemitismo | I20: “Infelizmente o ódio contra judeus ainda persiste, algumas vezes de forma explícita, e em outras disfarçado sob diferentes pretextos para propagar sua disseminação. O Rio é uma cidade turística e reconhecida por sua diversidade e pluralidade, não podemos normalizar preconceito, hostilidade ou discriminação”, ressaltou o vereador, que é o único judeu no parlamento carioca. | J20: Valle apresentou outras duas propostas para fortalecimento do combate ao antissemitismo no Rio de Janeiro. Uma torna lei a adoção de definição de antissemitismo da IHRA (Aliança Internacional para a Memória do Holocausto) e outra inclui no calendário oficial da cidade o “Dia de Combate ao Antissemitismo”, a ser celebrado em 7 de outubro, data do ataque terrorista do Hamas a Israel.
A21: RELEASE | B21: 45708 | C21: =(IF(ISBLANK(B21),"",TEXT(DATE(MID(B21,7,4), MID(B21,4,2), MID(B21,1,2)), "mm/yyyy"))) -> 02/2025 | D21: Combate ao Antissemitismo | E21: Com aumento de casos, Câmara do Rio cria Frente Parlamentar contra antissemitismo | F21: AGENDA DO PODER | G21: CÁRTER ANDERSON | H21: https://agendadopoder.com.br/com-aumento-de-casos-camara-do-rio-cria-frente-parlamentar-contra-antissemitismo/#google_vignette | I21: “Infelizmente, o ódio contra judeus ainda persiste, algumas vezes de forma explícita, e em outras disfarçado sob diferentes pretextos para propagar sua disseminação. O Rio é uma cidade turística e reconhecida por sua diversidade e pluralidade, não podemos normalizar preconceito, hostilidade ou discriminação”, destacou Valle, que é o único vereador judeu da Câmara carioca. | J21: A iniciativa, publicada no Diário Oficial da Casa nesta quinta-feira (20), foi proposta pelo vereador Flávio Valle (PSD), em parceria com Marcos Dias (Podemos) e Pedro Duarte (Novo). O requerimento contou com o apoio de 25 parlamentares, o que garantiu sua aprovação automática.
A22: NOTA | B22: 45708 | C22: =(IF(ISBLANK(B22),"",TEXT(DATE(MID(B22,7,4), MID(B22,4,2), MID(B22,1,2)), "mm/yyyy"))) -> 02/2025 | D22: Combate ao Antissemitismo | E22: Câmara do Rio cria Frente Parlamentar de Combate ao Antissemitismo | F22: VEJA RIO | G22: LU LACERDA | H22: https://vejario.abril.com.br/coluna/lu-lacerda/camara-do-rio-cria-frente-parlamentar-de-combate-ao-antissemitismo/ | I22: “Infelizmente o ódio contra judeus ainda persiste, algumas vezes de forma explícita, e em outras disfarçado sob diferentes pretextos. O Rio é uma cidade turística e reconhecida por sua diversidade e ... Leia mais em: https://vejario.abril.com.br/coluna/lu-lacerda/camara-do-rio-cria-frente-parlamentar-de-combate-ao-antissemitismo/ | J22: Ação dos vereadores Flávio Valle, Marcos Dias e Pedro Duarte, com apoio de outros 25 vereadores, o que garantiu a sua criação imediata. Leia mais em: https://vejario.abril.com.br/coluna/lu-lacerda/camara-do-rio-cria-frente-parlamentar-de-combate-ao-antissemitismo/
A23: NOTA | B23: 45711 | C23: =(IF(ISBLANK(B23),"",TEXT(DATE(MID(B23,7,4), MID(B23,4,2), MID(B23,1,2)), "mm/yyyy"))) -> 02/2025 | D23: Mandato | E23: Vereadores e influencers: Flávio Valle lidera lista de crescimento de seguidores | F23: TEMPO REAL | G23: VITOR D'AVILA | H23: https://temporealrj.com/vereadores-e-influencers-flavio-valle-lidera-lista-de-crescimento-de-seguidores/ | J23: O novato Flávio Valle (PSD) aparece no topo do ranking da estatística de crescimento da base de seguidores no Instagram, no último mês, com um aumento de 4,9% (1.572 novos seguidores). O vereador vem seguido por Gigi Castilho (Republicanos), com 4,5% (740), e Wagner Tavares (PSB), com 4,2% (178).
A24: RELEASE | B24: 45712 | C24: =(IF(ISBLANK(B24),"",TEXT(DATE(MID(B24,7,4), MID(B24,4,2), MID(B24,1,2)), "mm/yyyy"))) -> 02/2025 | D24: Mandato | E24: Vereadores ampliam alcance digital: Flávio Valle é destaque no Instagram | F24: DIÁRIO DO RIO | G24: QUINTINO GOMES FREIRE | H24: https://diariodorio.com/vereadores-ampliam-alcance-digital-flavio-valle-e-destaque-no-instagram/ | J24: No cenário político atual, a atuação parlamentar vai além da Câmara: conquistar espaço nas redes sociais tornou-se essencial para manter o eleitor informado. No último mês, o vereador Flávio Valle (PSD) liderou o crescimento de seguidores no Instagram, com um aumento de 4,9%, equivalente a 1.572 novos seguidores.
A25: NOTA | B25: 45712 | C25: =(IF(ISBLANK(B25),"",TEXT(DATE(MID(B25,7,4), MID(B25,4,2), MID(B25,1,2)), "mm/yyyy"))) -> 02/2025 | D25: Turismo | E25: Câmara do Rio oficializa presidentes e vices de 14 comissões permanentes | F25: TEMPO REAL | H25: https://temporealrj.com/camara-do-rio-oficializa-presidentes-e-vices-de-14-comissoes-permanentes/ | J25: Comissão Permanente de Turismo: Flávio Valle (PSD) é o presidente; Jorge Canella (União Brasil) é o vice-presidente; Rocal (PSD) é o vogal interino.
A26: RELEASE | B26: 45712 | C26: =(IF(ISBLANK(B26),"",TEXT(DATE(MID(B26,7,4), MID(B26,4,2), MID(B26,1,2)), "mm/yyyy"))) -> 02/2025 | D26: Combate ao Antissemitismo | E26: Câmara do Rio terá Frente Parlamentar de Combate ao Antissemitismo | F26: CONIB | H26: https://conib.org.br/noticias/todas-as-noticias/39495-camara-do-rio-tera-frente-parlamentar-de-combate-ao-antissemitismo.html
A27: RELEASE | B27: 45713 | C27: =(IF(ISBLANK(B27),"",TEXT(DATE(MID(B27,7,4), MID(B27,4,2), MID(B27,1,2)), "mm/yyyy"))) -> 02/2025 | D27: Meio Ambiente | E27: Programa Vaga Viva propõe jardins e bicicletários em espaços de estacionamento | F27: DIÁRIO DO RIO | G27: QUINTINO GOMES FREIRE | H27: https://diariodorio.com/programa-vaga-viva-propoe-jardins-e-bicicletarios-em-espacos-de-estacionamento/ | J27: A Câmara Municipal do Rio de Janeiro analisa o Programa Vaga Viva, proposta do vereador Flavio Valle que estabelece diretrizes para a conversão de vagas de estacionamento em áreas verdes e espaços de convivência.
A28: NOTA | B28: 45715 | C28: =(IF(ISBLANK(B28),"",TEXT(DATE(MID(B28,7,4), MID(B28,4,2), MID(B28,1,2)), "mm/yyyy"))) -> 02/2025 | D28: Ordenamento | E28: Copacabana: o que vem a ser a nova pintura na Mureta do Leme? | F28: VEJA RIO | G28: LU LACERDA | H28: https://vejario.abril.com.br/coluna/lu-lacerda/copacabana-amanhecem-com-nova-pintura-na-mureta-do-leme/ | J28: Tudo começou via secretaria de Conservação, que, com a melhor das intenções, pediu ajuda ao vereador Flávio Valle, ex-subsecretário da Zona Sul, para indicar algum artista visual. Ele citou Malu Vibe... Leia mais em: https://vejario.abril.com.br/coluna/lu-lacerda/copacabana-amanhecem-com-nova-pintura-na-mureta-do-leme/
A29: RELEASE | B29: 45714 | C29: =(IF(ISBLANK(B29),"",TEXT(DATE(MID(B29,7,4), MID(B29,4,2), MID(B29,1,2)), "mm/yyyy"))) -> 02/2025 | D29: Segurança | E29: Projeto prevê que Guardas Municipais do Rio passem por processo interno para integrar Força Municipal de Segurança | F29: CBN | G29: LEONARDO REZENDE | H29: https://cbn.globo.com/rio-de-janeiro/noticia/2025/02/26/projeto-preve-que-guardas-municipais-do-rio-passem-por-processo-interno-para-integrar-forca-municipal-de-seguranca.ghtml | I29: "Tem dois pontos. Primeiro, a gente poder premiar os guardas que entendem que a função deles, como agentes públicos, deve ser a segurança pública. Eles vão poder fazer parte desse processo seletivo. Mas, além disso, a Guarda Municipal está passando por um processo de refundação da sua instituição. A prefeitura entende que a Guarda Municipal, hoje, precisa focar em olhar mais para o cidadão, focar mais na parte da zeladoria urbana, na fiscalização das posturas", disse. | J29: Vereador da base aliada do prefeito, Flavio Valle, afirmou que o município realiza uma refundação da Guarda Municipal - voltada para o ordenamento público.
A30: RELEASE | B30: 45727 | C30: =(IF(ISBLANK(B30),"",TEXT(DATE(MID(B30,7,4), MID(B30,4,2), MID(B30,1,2)), "mm/yyyy"))) -> 03/2025 | D30: Mandato | E30: Estrelismo, carnaval e bolinho de bacalhau – Bastidores do Rio | F30: DIÁRIO DO RIO | G30: QUINTINO GOMES FREIRE | H30: https://diariodorio.com/estrelismo-carnaval-e-bolinho-de-bacalhau-bastidores-do-rio/ | J30: O vereador Júnior Flávio Valle participou do Hillel International Israel Summit, em Chicago, onde lideranças judaicas discutiram o crescimento do antissemitismo em universidades americanas e estratégias de combate à desinformação.
A31: NOTA | B31: 45728 | C31: =(IF(ISBLANK(B31),"",TEXT(DATE(MID(B31,7,4), MID(B31,4,2), MID(B31,1,2)), "mm/yyyy"))) -> 03/2025 | D31: Turismo | E31: Presidente da Comissão de Turismo propõe limites para o financiamento do Carnaval | F31: TEMPO REAL | H31: https://temporealrj.com/presidente-da-comissao-de-turismo-propoe-limites-para-o-financiamento-do-carnaval/ | I31: “Precisamos discutir certos limites no financiamento do Carnaval. Por muito tempo, a prefeitura precisou aportar recursos e ela historicamente sempre fez esse papel com muita maestria, mas hoje o Carnaval é muito mais sofisticado. A cada ano que passa, a Liga Independente (Liesa) vai ficando, de fato, mais independente. E o governo do estado, há alguns anos, começou também a colocar dinheiro”, disse. | J31: Em discurso na Câmara de Vereadores, nesta terça feira (11), Flávio Valle (PSD), presidente da Comissão de Turismo, sugeriu que sejam discutidos limites para o financiamento do carnaval. Na fala, contudo, ele ressaltou a importância da festa para a economia carioca e destacou os números da arrecadação de impostos (ISS): mais de R$ 530 milhões.
A32: ARTIGO | B32: 45733 | C32: =(IF(ISBLANK(B32),"",TEXT(DATE(MID(B32,7,4), MID(B32,4,2), MID(B32,1,2)), "mm/yyyy"))) -> 03/2025 | D32: Economia | E32: Flávio Valle: Por que a Câmara Municipal do Rio deve aprovar o empréstimo solicitado pela Prefeitura | F32: O DIA | G32: Flavio Valle | H32: https://odia.ig.com.br/opiniao/2025/03/7021183-flavio-valle-por-que-a-camara-municipal-do-rio-deve-aprovar-o-emprestimo-solicitado-pela-prefeitura.html | I32: Que venham os novos investimentos!
A33: RELEASE | B33: 45734 | C33: =(IF(ISBLANK(B33),"",TEXT(DATE(MID(B33,7,4), MID(B33,4,2), MID(B33,1,2)), "mm/yyyy"))) -> 03/2025 | D33: Combate ao Antissemitismo | E33: FIERJ promove o lançamento de 'Eternamente 7 de Outubro' e debate sobre terrorismo e antissemitismo | F33: CONIB | H33: https://conib.org.br/noticias/todas-as-noticias/39554-fierj-promove-o-lancamento-de-eternamente-7-de-outubro-e-debate-sobre-terrorismo-e-antissemitismo.html | I33: "Quando a gente conta a história, disponibiliza informação, estamos educando e com isto mitigando interpretações distorcidas e prevenindo incidentes de discriminação, como o antissemitismo. A disseminação de informações corretas e o incentivo à educação são pilares essenciais para construir uma sociedade mais consciente e inclusiva. Além disso, promover o diálogo e o entendimento entre diferentes grupos culturais e religiosos fortalece a coesão social e contribui para um futuro mais justo e harmonioso”, avaliou o vereador Flavio Valle, presidente da Frente Parlamentar de Combate ao Antissemitismo da CMRJ, após o evento. | J33: Após a exibição do documentário, aconteceu uma mesa de debate com a participação do comentarista da Jovem Pan Roberto Motta, do vereador Flávio Valle, do advogado Daniel Bialski e do diretor do filme, Ronaldo Gomlevsky, que agradeceu a oportunidade em nome do presidente da FIERJ, Bruno Feigelson. Os debatedores aprofundaram o conteúdo do documentário, suas mensagens e o contexto dos eventos retratados.
A34: RELEASE | B34: 45734 | C34: =(IF(ISBLANK(B34),"",TEXT(DATE(MID(B34,7,4), MID(B34,4,2), MID(B34,1,2)), "mm/yyyy"))) -> 03/2025 | D34: Turismo | E34: Flávio Valle assume Comissão de Turismo da Câmara com foco na retomada econômica do Rio | F34: DIÁRIO DO RIO | G34: QUINTINO GOMES FREIRE | H34: https://diariodorio.com/flavio-valle-assume-comissao-de-turismo-da-camara-com-foco-na-retomada-economica-do-rio/ | I34: “Estamos vivendo um momento positivo, com o Rio voltando a atrair turistas nacionais e estrangeiros em larga escala. Precisamos aproveitar essa fase, trabalhando em conjunto com o trade turístico para transformar esses números em desenvolvimento econômico e geração de empregos”, afirmou Flávio Valle. | J34: O vereador Flávio Valle, eleito recentemente para seu primeiro mandato na Câmara Municipal, foi apresentado nesta semana como o novo presidente da Comissão de Turismo da casa legislativa. O evento aconteceu no Hotel Prodigy Santos Dumont e reuniu empresários dos setores hoteleiro, gastronômico, de transportes e eventos da cidade.
A35: RELEASE | B35: 45734 | C35: =(IF(ISBLANK(B35),"",TEXT(DATE(MID(B35,7,4), MID(B35,4,2), MID(B35,1,2)), "mm/yyyy"))) -> 03/2025 | D35: Turismo | E35: Audiência pública na Câmara vai debater proposta de regulamentação do Airbnb no Rio | F35: TEMPO REAL | H35: https://temporealrj.com/audiencia-publica-na-camara-vai-debater-proposta-de-regulamentacao-do-airbnb-no-rio/ | I35: “A audiência pública é uma oportunidade para reunir diferentes setores da sociedade, incluindo representantes das plataformas, hoteleiros, moradores e poder público, a fim de buscar soluções equilibradas que beneficiem tanto a economia local quanto a população”, afirmou | J35: Segundo o vereador Flávio Valle (PSD), presidente do colegiado, o crescimento dessas plataformas tem impactado significativamente o setor de turismo e hospedagem. O que gera debates sobre questões como tributação, segurança, concorrência com hotéis tradicionais e impacto no mercado imobiliário.
A36: NOTA | B36: 45734 | C36: =(IF(ISBLANK(B36),"",TEXT(DATE(MID(B36,7,4), MID(B36,4,2), MID(B36,1,2)), "mm/yyyy"))) -> 03/2025 | D36: Turismo | E36: Visit Rio apresenta Flávio Valle, novo presidente da Comissão de Turismo da Câmara ao trade | F36: TURISNEWS | H36: https://turisnews.com.br/visit-rio-apresenta-flavio-valle-novo-presidente-da-comissao-de-turismo-da-camara-ao-trade/ | I36: “No ano passado, o Rio registrou a maior arrecadação de ISS (Imposto Sobre Serviços) do setor de turismo dos últimos cinco anos. Os números refletem o aumento no número de visitantes e a capacidade da cidade de capitalizar eventos, gerando receita para os cofres públicos e movimentando a economia local. Essa combinação de turismo cultural, de entretenimento e de negócios parece ser uma fórmula vencedora para a cidade, que consegue aproveitar sua infraestrutura e vocação natural para eventos de grande escala durante o ano inteiro. Vamos potencializar esse trabalho por meio da Comissão de Turismo”, afirma o vereador Flávio Valle. | J36: Na manhã desta terça-feira (18), o novo presidente da Comissão de Turismo da Câmara Municipal do Rio, Vereador Flávio Valle, foi apresentado oficialmente ao trade turístico carioca durante evento promovido pelo Visit Rio Convention Bureau.
A37: NOTA | B37: 45734 | C37: =(IF(ISBLANK(B37),"",TEXT(DATE(MID(B37,7,4), MID(B37,4,2), MID(B37,1,2)), "mm/yyyy"))) -> 03/2025 | D37: Turismo | E37: Visit Rio apresenta Flávio Valle, novo presidente da Comissão de Turismo da Câmara do Rio | F37: BRASILTURIS | G37: RAFAEL DESTRO | H37: https://brasilturis.com.br/2025/03/18/visit-rio-apresenta-flavio-valle-novo-presidente-da-comissao-de-turismo-da-camara-do-rio/?amp=1 | I37: No ano passado, o Rio registrou a maior arrecadação de ISS do setor turístico dos últimos cinco anos. Os números refletem o crescimento no número de visitantes e a capacidade da cidade de capitalizar eventos, gerando receita para os cofres públicos e movimentando a economia local. Essa combinação de turismo cultural, de entretenimento e de negócios tem se mostrado uma fórmula vencedora para a cidade”, explicou Flávio Valle. | J37: O Visit Rio Convention Bureau promoveu, na manhã desta terça-feira (18), um evento no hotel Prodigy Santos Dumont para apresentar oficialmente ao trade turístico carioca o vereador Flávio Valle, novo presidente da Comissão de Turismo da Câmara Municipal do Rio. A cerimônia reuniu empresários e profissionais dos setores de hotelaria, gastronomia, transportes e eventos, reforçando a importância da cooperação entre o setor público e privado para impulsionar o turismo na capital fluminense.
A38: RELEASE | B38: 45734 | C38: =(IF(ISBLANK(B38),"",TEXT(DATE(MID(B38,7,4), MID(B38,4,2), MID(B38,1,2)), "mm/yyyy"))) -> 03/2025 | D38: Turismo | E38: Audiência pública discute impacto e regras para Airbnb no Rio | F38: DIÁRIO DO RIO | G38: QUINTINO GOMES FREIRE | H38: https://diariodorio.com/audiencia-publica-discute-impacto-e-regras-para-airbnb-no-rio/ | I38: Queremos reunir representantes das plataformas digitais, hoteleiros, moradores e autoridades para buscar soluções equilibradas, capazes de beneficiar a economia da cidade e a população como um todo”, destacou Flávio Valle. | J38: Uma audiência pública marcada para a próxima terça-feira (25), às 9h30, no plenário da Câmara Municipal do Rio, vai debater a proposta que pretende regulamentar serviços de hospedagem por plataformas digitais, como Airbnb e Booking. A iniciativa é da Comissão de Turismo, presidida pelo vereador Flávio Valle (PSD).
A39: RELEASE | B39: 45735 | C39: =(IF(ISBLANK(B39),"",TEXT(DATE(MID(B39,7,4), MID(B39,4,2), MID(B39,1,2)), "mm/yyyy"))) -> 03/2025 | D39: Turismo | E39: Debate sobre o Airbnb na Câmara do Rio pode se internacionalizar antes da decisão de vereadores | F39: AGÊNCIA DO PODER | G39: AMANDA RAITER | H39: https://agendadopoder.com.br/debate-sobre-o-airbnb-na-camara-do-rio-pode-se-internacionalizar-antes-da-decisao-de-vereadores/ | J39: Enquanto o projeto para regulamentação do Airbnb parece encontrar pouca resistência entre os vereadores, tendo apenas o liberal Pedro Duarte (NOVO) declaradamente “contra”, fontes ligada ao vereador Flávio Valle (PSD), empossado nesta semana como presidente da Comissão de Turismo, já admite que as discussões sobre o assunto devem ouvir experiências internacionais antes da votação do projeto.
A40: NOTA | B40: 45735 | C40: =(IF(ISBLANK(B40),"",TEXT(DATE(MID(B40,7,4), MID(B40,4,2), MID(B40,1,2)), "mm/yyyy"))) -> 03/2025 | D40: Turismo | E40: Visit Rio apresenta Flávio Valle, novo presidente da Comissão de Turismo da Câmara Municipal | F40: PORTAL SHOW VIP | H40: https://www.showvip.com.br/2025/03/visit-rio-apresenta-flavio-valle-novo.html | I40: No ano passado, o Rio registrou a maior arrecadação de ISS (Imposto Sobre Serviços) do setor de turismo dos últimos cinco anos. Os números refletem o aumento no número de visitantes e a capacidade da cidade de capitalizar eventos, gerando receita para os cofres públicos e movimentando a economia local. Essa combinação de turismo cultural, de entretenimento e de negócios parece ser uma fórmula vencedora para a cidade, que consegue aproveitar sua infraestrutura e vocação natural para eventos de grande escala durante o ano inteiro. Vamos potencializar esse trabalho por meio da Comissão de Turismo", afirma o vereador Flávio Valle. | J40: Na manhã desta terça-feira (18), o novo presidente da Comissão de Turismo da Câmara Municipal do Rio, Vereador Flávio Valle, foi apresentado oficialmente ao trade turístico carioca durante evento promovido pelo Visit Rio Convention Bureau. A cerimônia foi realizada no hotel Prodigy Santos Dumont e teve a presença de empresários e colaboradores da rede hoteleira, e dos setores de gastronomia, transportes e eventos.
A41: NOTA | B41: 45736 | C41: =(IF(ISBLANK(B41),"",TEXT(DATE(MID(B41,7,4), MID(B41,4,2), MID(B41,1,2)), "mm/yyyy"))) -> 03/2025 | D41: Mandato | E41: Aterro do Flamengo recebe mais uma pelada política: Valle x Ferreirinha | F41: TEMPO REAL | G41: VITOR D'AVILA | H41: https://temporealrj.com/aterro-do-flamengo-recebe-mais-uma-pelada-politica-valle-x-ferreirinha/ | J41: De um lado, estará o time do vereador Flávio Valle (PSD) e seu gabinete. Do outro, a equipe montada pelo secretário municipal de Educação e deputado federal licenciado, Renan Ferreirinha, do mesmo partido. Eles compõem a base e o governo, respectivamente, de Eduardo Paes (PSD).
A42: NOTA | B42: 45737 | C42: =(IF(ISBLANK(B42),"",TEXT(DATE(MID(B42,7,4), MID(B42,4,2), MID(B42,1,2)), "mm/yyyy"))) -> 03/2025 | D42: Turismo | E42: Aviso de Pauta: Câmara realiza audiência pública sobre regulamentação dos serviços digitais de hospedagem | F42: CÂMARA RIO | H42: https://www.camara.rio/comunicacao/noticias/2537-aviso-de-pauta-camara-realiza-audiencia-publica-sobre-regulamentacao-dos-servicos-digitais-de-hospedagem | I42: "A audiência pública é uma oportunidade para reunir diferentes setores da sociedade, a fim de buscar soluções equilibradas que beneficiem tanto a economia local quanto a população", ressaltou o vereador Flávio Valle (PSD), presidente da comissão.
A43: NOTA | B43: 45737 | C43: =(IF(ISBLANK(B43),"",TEXT(DATE(MID(B43,7,4), MID(B43,4,2), MID(B43,1,2)), "mm/yyyy"))) -> 03/2025 | D43: Mandato | E43: Ferreirinha x Valle: mais uma pelada política termina em empate | F43: TEMPO REAL | H43: https://temporealrj.com/ferreirinha-x-valle-mais-uma-pelada-politica-termina-em-empate/ | J43: Está difícil tirar a igualdade do placar nas peladas políticas pelo Rio. No amistoso entre o time Educação FC, do capitão e secretário Renan Ferreirinha, contra o time do gabinete do vereador Flávio Valle, ambos do PSD, deu empate: 2 a 2.
A44: NOTA | B44: 45737 | C44: =(IF(ISBLANK(B44),"",TEXT(DATE(MID(B44,7,4), MID(B44,4,2), MID(B44,1,2)), "mm/yyyy"))) -> 03/2025 | D44: Turismo | E44: A próxima treta na Câmara de Vereadores: Airbnb | F44: CBN | G44: LEANDRO RESENDE | H44: https://cbn.globo.com/rio-de-janeiro/analise/2025/03/21/a-proxima-treta-na-camara-de-vereadores-airbnb.ghtml | J44: Na audiência de terça-feira (25) na Câmara, o vereador Flávio Valle apresentará como a questão é discutida no mundo. A grande preocupação com o avanço do Airbnb em cidades turísticas como Paris, Barcelona e Nova Iorque é o fato de muitos proprietários de imóveis preferirem alugar seus espaços para turistas, por curta temporada (visando valores maiores) do que alugar para residentes locais, em aluguéis de longo prazo.
A45: COLUNA | B45: 45740 | C45: =(IF(ISBLANK(B45),"",TEXT(DATE(MID(B45,7,4), MID(B45,4,2), MID(B45,1,2)), "mm/yyyy"))) -> 03/2025 | D45: Mandato | E45: "Renovadores da política" prestam conta | F45: O DIA | H45: https://www.iclipping.com.br/noticia/86/15031613 | J45: Nos próximos dias 26 e 27, a diretora da escola de formação política RenovaBR, Bruna Barros, e o gerente de Relacionamento, Davi Abreu, farão reuniões com os vereadores Pedro Duarte (NOVO), Flávio Valle e Joyce Trindade (ambos do PSD) e o prefeito de Mesquita, Alex Maroto (PL), entre outras lideranças, para discutir os desafios e as perspectivas dos mandatos. O Rio é um dos estados que mais elegeu representantes formados pela instituição.
A46: NOTA | B46: 45740 | C46: =(IF(ISBLANK(B46),"",TEXT(DATE(MID(B46,7,4), MID(B46,4,2), MID(B46,1,2)), "mm/yyyy"))) -> 03/2025 | D46: Mandato | E46: Vereadores Thalita Galhardo e Flávio Valle batem boca em audiência sobre Airbnb | F46: TEMPO REAL | G46: LUCAS LUCIANO | H46: https://temporealrj.com/vereadores-thalita-galhardo-e-flavio-valle-batem-boca-em-audiencia-sobre-airbnb/ | I46: Em seguida, o vereador Flávio Valle, do PSD, partido do autor do projeto, Salvino Oliveira, não demorou a rebater as críticas de Galhardo. “Eu não estou vendo ainda nenhuma politização partidária”, disse Valle, antes de ser interrompido por Talita. Ele continuou defendendo que a politização das discussões é algo positivo, afirmando que a política é justamente esse processo. Para ele, a politização do tema é benéfica para a sociedade, pois permite ouvir todos os lados e estimular um debate mais amplo e democrático. | J46: Os vereadores Talita Galhardo (PSDB) e Flávio Valle (PSD) protagonizaram um bate-boca durante audiência na Câmara dos Vereadores do Rio, nesta segunda-feira (24), sobre o polêmico projeto de regulamentação das plataformas de aluguel por temporada, como o Airbnb.
A47: NOTA | B47: 45740 | C47: =(IF(ISBLANK(B47),"",TEXT(DATE(MID(B47,7,4), MID(B47,4,2), MID(B47,1,2)), "mm/yyyy"))) -> 03/2025 | D47: Turismo | E47: Reunião ou audiência? Confusão marca 1º debate sobre regulamentação do Airbnb | F47: TEMPO REAL | G47: LUCAS LUCIANO | H47: https://temporealrj.com/reuniao-ou-audiencia-confusao-marca-1o-debate-sobre-regulamentacao-do-airbnb/ | J47: A audiência pública da Comissão de Turismo será às 9h30, no plenário da Câmara, nesta terça. Segundo o vereador Flávio Valle (PSD), presidente do colegiado, o crescimento dessas plataformas tem impactado significativamente o setor de turismo e hospedagem.
A48: NOTA | B48: 45740 | C48: =(IF(ISBLANK(B48),"",TEXT(DATE(MID(B48,7,4), MID(B48,4,2), MID(B48,1,2)), "mm/yyyy"))) -> 03/2025 | D48: Turismo | E48: Regulamentação do Airbnb gera embate na Câmara Municipal | F48: VEJA RIO | G48: Bruno Chateaubriand | H48: https://vejario.abril.com.br/coluna/bruno-chateaubriand/regulamentacao-do-airbnb-gera-embate-na-camara-municipal
A49: MATÉRIA | B49: 45741 | C49: =(IF(ISBLANK(B49),"",TEXT(DATE(MID(B49,7,4), MID(B49,4,2), MID(B49,1,2)), "mm/yyyy"))) -> 03/2025 | D49: Turismo | E49: Airbnb na mira: projetos de lei tentam regular plataforma enquanto condomínios proíbem aluguéis | F49: O GLOBO | G49: Selma Schmidt e Thayná Rodrigues | H49: https://oglobo.globo.com/rio/noticia/2025/03/25/projetos-de-lei-miram-regulacao-do-airbnb-e-condominios-ja-proibem-alugueis-por-plataformas.ghtml | I49: O que o prefeito quer é garantir que a cidade esteja cheia de turistas e que o setor hoteleiro não seja ameaçado pelo aluguel por temporada — afirma ele. | J49: Da bancada governista e ex-subprefeito do Rio, como Salvino, o vereador Flávio Valle (PSD), presidente da Comissão de Turismo da Câmara, está preparando outro projeto de regulamentação do aluguel por curta temporada. Segundo ele, nas conversas que teve com Eduardo Paes, o prefeito se mostrou disposto a regulamentar o assunto, “desde que não seja uma aberração”.
A50: REPORTAGEM | B50: 45741 | C50: =(IF(ISBLANK(B50),"",TEXT(DATE(MID(B50,7,4), MID(B50,4,2), MID(B50,1,2)), "mm/yyyy"))) -> 03/2025 | D50: Turismo | E50: Câmara discute regulamentação de aluguéis por temporada de residências | F50: BOM DIA RIO | H50: https://www.iclipping.com.br/noticia/86/15059189
A51: NOTA | B51: 45741 | C51: =(IF(ISBLANK(B51),"",TEXT(DATE(MID(B51,7,4), MID(B51,4,2), MID(B51,1,2)), "mm/yyyy"))) -> 03/2025 | D51: Turismo | E51: Longas filas se formam na Cinelândia para audiência sobre regulamentação do Airbnb | F51: TEMPO REAL | G51: LUCAS LUCIANO | H51: https://temporealrj.com/longas-filas-se-formam-na-cinelandia-para-audiencia-sobre-regulamentacao-do-airbnb/ | J51: A comissão é formada pelos vereadores Flávio Valle (PSD), presidente, Jorge Canella (União), vice-presidente, e Rocal (PSD), vogal. Essa comissão tem como objetivo emitir pareceres sobre projetos de lei relacionados ao turismo que tramitam na Câmara, podendo sugerir emendas antes da votação.
A52: NOTA | B52: 45741 | C52: =(IF(ISBLANK(B52),"",TEXT(DATE(MID(B52,7,4), MID(B52,4,2), MID(B52,1,2)), "mm/yyyy"))) -> 03/2025 | D52: Turismo | E52: Airbnb, a treta: autor do projeto tenta derrubar audiência convocada pela Comissão de Turismo | F52: TEMPO REAL | G52: Berenice Seara | H52: https://temporealrj.com/airbnb-a-treta-autor-do-projeto-tenta-derrubar-audiencia-convocada-pela-comissao-de-turismo/
A53: NOTA | B53: 45741 | C53: =(IF(ISBLANK(B53),"",TEXT(DATE(MID(B53,7,4), MID(B53,4,2), MID(B53,1,2)), "mm/yyyy"))) -> 03/2025 | D53: Turismo | E53: Flávio Valle chama de ‘censura’ tentativa de barrar audiência sobre Airbnb | F53: TEMPO REAL | G53: LUCAS LUCIANO | H53: https://temporealrj.com/flavio-valle-chama-de-censura-tentativa-de-barrar-audiencia-sobre-airbnb/ | I53: Preciso manifestar meu total repúdio a uma tentativa frustrada de impugnar esta audiência pública, que seguiu rigorosamente o regimento interno desta Casa. É lamentável que, em vez de respeitarmos o debate democrático, haja quem tente impor a censura e calar vozes legítimas”, afirmou o parlamentar. | J53: O vereador Flávio Valle (PSD), presidente da Comissão de Turismo, iniciou a audiência desta terça-feira (25) criticando seu colega de partido, o vereador Salvino Oliveira (PSD), que tentou impedir a realização do encontro para debater a regulamentação do aluguel temporário de imóveis por meio de plataformas digitais, como o Airbnb. Em sua fala, Valle atacou Salvino, autor do polêmico projeto, e chamou de “censura” a tentativa de barrar o debate.
A54: NOTA | B54: 45741 | C54: =(IF(ISBLANK(B54),"",TEXT(DATE(MID(B54,7,4), MID(B54,4,2), MID(B54,1,2)), "mm/yyyy"))) -> 03/2025 | D54: Turismo | E54: Câmara Municipal do Rio discute regulamentação do aluguel de casas e apartamentos por temporada | F54: G1
A55: RELEASE | B55: 45748 | C55: =(IF(ISBLANK(B55),"",TEXT(DATE(MID(B55,7,4), MID(B55,4,2), MID(B55,1,2)), "mm/yyyy"))) -> 04/2025 | D55: Combate ao Antissemitismo | E55: Vereador Flávio Valle recebe família vítima do Hamas e reforça luta contra o antissemitismo | F55: DIÁRIO DO RIO | G55: QUINTINO GOMES FREIRE | H55: https://diariodorio.com/vereador-flavio-valle-recebe-familia-vitima-do-hamas-e-reforca-luta-contra-o-antissemitismo/ | I55: “O Rio de Janeiro foi a primeira cidade brasileira a adotar a definição de antissemitismo da IHRA (International Holocaust Remembrance Alliance), um marco crucial para identificar e combater discursos e atos antissemitas. Além disso, criei na Câmara Municipal a Frente Parlamentar de Combate ao Antissemitismo, garantindo que o tema seja tratado com a seriedade necessária. O antissemitismo não será tolerado em nossa cidade. Não permitiremos que o ódio, a intolerância e a discriminação tenham espaço em nossa sociedade”, afirmou o vereador Flávio Valle. | J55: Na tarde de segunda-feira (31), o vereador Flávio Valle, presidente da Frente Parlamentar de Combate ao Antissemitismo da Câmara Municipal do Rio de Janeiro, recebeu em seu gabinete a família Engel, vítima do ataque terrorista do Hamas em 7 de outubro.
A56: NOTA | B56: 45748 | C56: =(IF(ISBLANK(B56),"",TEXT(DATE(MID(B56,7,4), MID(B56,4,2), MID(B56,1,2)), "mm/yyyy"))) -> 04/2025 | D56: Meio Ambiente | E56: Vereadores querem municipalizar Floresta da Tijuca | F56: VEJA RIO | G56: LU LACERDA | H56: https://vejario.abril.com.br/coluna/lu-lacerda/vereadores-querem-municipalizar-floresta-da-tijuca/ | J56: Os vereadores Cesar Maia e Flávio Valle entraram com projeto pedindo a municipalização da Floresta da Tijuca, depois da morte de um turista, sem atendimento, durante uma visita ao Cristo. Jorge Alex D...
A57: RELEASE | B57: 45755 | C57: =(IF(ISBLANK(B57),"",TEXT(DATE(MID(B57,7,4), MID(B57,4,2), MID(B57,1,2)), "mm/yyyy"))) -> 04/2025 | D57: Ordenamento | E57: Casarão de 1920 que seria demolido no Flamengo pode ser tombado | F57: DIARIO DO RIO | G57: VICTOR SERRA | H57: https://diariodorio.com/casarao-de-1920-que-seria-demolido-no-flamengo-pode-ser-tombado/ | I57: “Queremos fomentar ações de educação patrimonial e turismo cultural, transformando o imóvel em um ponto de referência para a comunidade”, explica o parlamentar. | J57: O vereador Flávio Valle acaba de protocolar um projeto de lei na Câmara Municipal que propõe o tombamento do sobrado histórico da Rua Dois de Dezembro, no Flamengo. O casario da década de 20 corria o risco de ser demolido para a construção de um prédio moderno.
A58: RELEASE | B58: 45756 | C58: =(IF(ISBLANK(B58),"",TEXT(DATE(MID(B58,7,4), MID(B58,4,2), MID(B58,1,2)), "mm/yyyy"))) -> 04/2025 | D58: Mandato | E58: Câmara Rio aprova título de cidadão honorário ao vereador Marcelo Diniz | F58: AGENDA DO PODER | G58: AMANDA RAITER | H58: https://agendadopoder.com.br/camara-rio-aprova-titulo-de-cidadao-honorario-ao-vereador-marcelo-diniz/ | J58: Já o afilhado político de Cavaliere, Flávio Valle (PSD), que estreou na casa neste ano, assina junto com o xará Flávio Pato e Caiado a homenagem a Ganso, natural do Pará, o jogador integra o Fluminense, time de Valle.
A59: NOTA | B59: 45757 | C59: =(IF(ISBLANK(B59),"",TEXT(DATE(MID(B59,7,4), MID(B59,4,2), MID(B59,1,2)), "mm/yyyy"))) -> 04/2025 | D59: Meio Ambiente | E59: Naturalização: espécie ameaçada de extinção será plantada na Lagoa Rodrigo de Freitas | F59: O GLOBO | G59: ANCELMO GOIS | H59: https://oglobo.globo.com/blogs/ancelmo-gois/post/2025/04/naturalizacao-especie-ameacada-de-extincao-sera-plantada-na-lagoa-rodrigo-de-freitas.ghtml | J59: Projeto naturalização
A60: RELEASE | B60: 45757 | C60: =(IF(ISBLANK(B60),"",TEXT(DATE(MID(B60,7,4), MID(B60,4,2), MID(B60,1,2)), "mm/yyyy"))) -> 04/2025 | D60: Turismo | E60: Airbnb será o próximo convidado da Comissão Especial da Câmara, liderada por Salvino | F60: AGENDA DO PODER | G60: AMANDA RAITER | H60: https://agendadopoder.com.br/airbnb-sera-o-proximo-convidado-da-comissao-especial-da-camara-liderada-por-salvino/ | J60: Já a Comissão de Turismo, presidida por Flávio Valle (PSD), que declinou da coautoria do projeto de Salvino, promove mais duas audiências públicas para debater o assunto, sendo a próxima, em conjunto com a Comissão de Assuntos Urbanos, presidida por Duarte.
A61: RELEASE | B61: 45758 | C61: =(IF(ISBLANK(B61),"",TEXT(DATE(MID(B61,7,4), MID(B61,4,2), MID(B61,1,2)), "mm/yyyy"))) -> 04/2025 | D61: Ordenamento | E61: Projeto direciona até 20% do ISS para revitalização de espaços públicos | F61: AGENDA DO PODER | G61: AMANDA RAITER | H61: https://agendadopoder.com.br/projeto-direciona-ate-20-do-iss-para-revitalizacao-de-espacos-publicos/#google_vignette | I61: “A requalificação de espaços públicos é um antídoto contra a violência. Com esse projeto, unimos eficiência fiscal e impacto social, transformando o Rio em uma cidade mais segura e acolhedora”, afirma. | J61: O vereador Flávio Valle (PSD) apresentou o projeto de Lei na Câmara do Rio, que institui incentivo fiscal referente ao Imposto Sobre Serviços de Qualquer Natureza (ISS) para projetos de conservação urbana. Batizado de “ISS Conservação”, a iniciativa permitirá que os contribuintes do imposto direcionem até 20% do valor recolhido do tributo municipal para a revitalização de espaços públicos, como ruas, praças, parques, restingas e ciclovias cariocas.
A62: RELEASE | B62: 45761 | C62: =(IF(ISBLANK(B62),"",TEXT(DATE(MID(B62,7,4), MID(B62,4,2), MID(B62,1,2)), "mm/yyyy"))) -> 04/2025 | D62: Causa Animal | E62: Projeto quer mais rigor na venda de animais em vias públicas | F62: AGENDA DO PODER | G62: AMANDA RAITER | H62: https://agendadopoder.com.br/projeto-quer-mais-rigor-na-venda-de-animais-em-vias-publicas/ | I62: “Nosso projeto inclui mais espécies de animais na redação, que antes se restringia aos animais domésticos (cães e gatos), além disso, nossa proposta também garante a apreensão dos animais, o que antes não estava previsto em lei. Essa medida busca assegurar que os animais sejam tratados com ética, incentivando a aquisição responsável e regulamentada por canais seguros, como abrigos credenciados e instituições de proteção animal”, afirma Valle. | J62: A Câmara Municipal do Rio de Janeiro vai discutir um novo Projeto de Lei Nº 387/2025, de autoria do vereador Flavio Valle (PSD), que propõe alterações significativas à Lei nº 6.435/2018, ampliando as medidas de proteção e bem-estar dos animais no município.
A63: RELEASE | B63: 45767 | C63: =(IF(ISBLANK(B63),"",TEXT(DATE(MID(B63,7,4), MID(B63,4,2), MID(B63,1,2)), "mm/yyyy"))) -> 04/2025 | D63: Ordenamento | E63: Orla pode ganhar estatuto de ordem pública | F63: AGENDA DO PODER | G63: AMANDA RAITER | H63: https://agendadopoder.com.br/orla-pode-ganhar-estatuto-de-ordem-publica/ | I63: “Nosso projeto busca consolidar um modelo de gestão urbana integrada, que privilegie o equilíbrio entre desenvolvimento econômico, preservação ambiental e inclusão social. Além disso, estamos alinhados com os Objetivos de Desenvolvimento Sustentável (ODS) da ONU – em especial o ODS 11 (Cidades e Comunidades Sustentáveis), o ODS 12 (Consumo e Produção Responsáveis) e o ODS 14 (Vida na Água)”, explica. | J63: O vereador Flávio Valle (PSD) anunciou, em reunião com o Orla Rio, que já protocolou o projeto de Lei que prevê a criação do Estatuto de sua autoria para organizar as praias cariocas. Valle, que também é presidente da Comissão de Turismo e foi subprefeito da Zona Sul, divulgou o anúncio em suas redes sociais.
A64: RELEASE | B64: 45772 | C64: =(IF(ISBLANK(B64),"",TEXT(DATE(MID(B64,7,4), MID(B64,4,2), MID(B64,1,2)), "mm/yyyy"))) -> 04/2025 | D64: Economia | E64: Câmara do Rio pode ganhar Conselho Fiscal Independente | F64: AGENDA DO PODER | G64: AMANDA RAITER | H64: https://agendadopoder.com.br/camara-muncipal-pode-ganhar-conselho-fiscal-independente/#google_vignette | I64: “A cidade do Rio vem avançando na gestão fiscal, mas precisamos consolidar esse progresso com um órgão técnico, imparcial e permanente. O Conselho Fiscal Independente vai além da fiscalização: é um instrumento de educação cidadã, que coloca dados técnicos à disposição da sociedade para embasar debates qualificados sobre o uso do dinheiro público.”, defende. | J64: Foi publicado no Diário Oficial da Câmara Municipal do Rio de Janeiro o Projeto de Lei nº 401/2025, de autoria do vereador Flávio Valle (PSD), que cria o Conselho Fiscal Independente, um órgão permanente para monitorar as finanças públicas municipais com independência técnica e transparência. A proposta visa a fortalecer o controle interno, qualificar o debate fiscal e garantir maior responsabilidade na gestão dos recursos públicos.
A65: RELEASE | B65: 45772 | C65: =(IF(ISBLANK(B65),"",TEXT(DATE(MID(B65,7,4), MID(B65,4,2), MID(B65,1,2)), "mm/yyyy"))) -> 04/2025 | D65: Esporte e Lazer | E65: Corridas esportivas ganharão apoio de vereador no Rio | F65: AGENDA DO PODER | G65: AMANDA RAITER | H65: https://agendadopoder.com.br/corridas-esportivas-ganharao-apoio-de-vereador-no-rio/ | J65: O vereador Flávio Valle (PSD) anunciou, em sua rede social, que irá se reunir com o Executivo para destacar e ampliar os circuitos de corridas esportivas que acontecem na cidade. No conteúdo, o parlamentar garante que quer rever detalhes com produtores dos eventos esportivos e com o prefeito Eduardo Paes, além do secretário de Esportes e Lazer, Guilherme Schleder, na intenção de abrir novas oportunidades para tais atividades ao ar livre.
A66: RELEASE | B66: 45776 | C66: =(IF(ISBLANK(B66),"",TEXT(DATE(MID(B66,7,4), MID(B66,4,2), MID(B66,1,2)), "mm/yyyy"))) -> 04/2025 | D66: Meio Ambiente | E66: Floresta da Tijuca: presidente da Comissão de Turismo da Câmara se reúne com Padre Omar | F66: AGENDA DO PODER | G66: AMANDA RAITER | H66: https://agendadopoder.com.br/floresta-da-tijuca-presidente-da-comissao-de-turismo-se-reune-com-padre-omar/ | J66: O presidente da Comissão de Turismo da Câmara do Rio, Flávio Valle (PSD), teve um primeiro encontro com o reitor do Santuário Cristo Redentor, Padre Omar, para começar a discutir o projeto de Lei que permite a municipalização do Parque Nacional da Tijuca, demanda do deputado federal Pedro Paulo (PSD), que também lançou seu próprio projeto.
A67: RELEASE | B67: 45779 | C67: =(IF(ISBLANK(B67),"",TEXT(DATE(MID(B67,7,4), MID(B67,4,2), MID(B67,1,2)), "mm/yyyy"))) -> 05/2025 | D67: Ordenamento | E67: Rio pode ganhar lei para combater adulteração de bicicletas elétricas | F67: AGENDA DO PODER | G67: AMANDA RAITER | H67: https://agendadopoder.com.br/rio-pode-ganhar-lei-para-combater-adulteracao-de-bicicletas-eletricas/ | I67: “Estão vendendo motos disfarçadas de bicicletas. Aí vira uma motocicleta sem emplacamento, sem habilitação e sem segurança. É um perigo – e uma infração. Por isso, estamos protocolando um projeto de lei para proibir a adulteração das bikes elétricas e exigir que lojas informem claramente o que é bicicleta elétrica, ciclomotor (apelidada de cinquentinha, exige habilitação) e autopropelido (também chamada de scooter elétrica ou vespa, em especial na Itália)”, explica Valle. | J67: Um flagrante da Defesa do Consumidor do Rio, onde foi constatada a oferta de bicicletas elétricas com adulteração na velocidade em uma loja especializada, já está na vira do vereador Flávio Valle (PSD) e pode ganhar lei municipal. O anúncio foi feito, ao lado do secretário da pasta, João Pires.
A68: NOTA | B68: 45782 | C68: =(IF(ISBLANK(B68),"",TEXT(DATE(MID(B68,7,4), MID(B68,4,2), MID(B68,1,2)), "mm/yyyy"))) -> 05/2025 | D68: Mandato | E68: Rosa Fernandes adota Flávio Valle – Bastidores do Rio | F68: DIÁRIO DO RIO | G68: QUINTINO GOMES FREIRE | H68: https://diariodorio.com/rosa-fernandes-adota-flavio-valle-bastidores-do-rio/ | J68: O vereador Júnior Flávio Valle tem agora uma mãe política na Câmara: a experiente Rosa Fernandes.
A69: RELEASE | B69: 45783 | C69: =(IF(ISBLANK(B69),"",TEXT(DATE(MID(B69,7,4), MID(B69,4,2), MID(B69,1,2)), "mm/yyyy"))) -> 05/2025 | D69: Ordenamento | E69: Proposta quer combater barulho excessivo no Rio de Janeiro com novas regras e fiscalização mais rígida | F69: DIÁRIO DO RIO | G69: QUINTINO GOMES FREIRE | H69: https://diariodorio.com/proposta-quer-combater-barulho-excessivo-no-rio-de-janeiro-com-novas-regras-e-fiscalizacao-mais-rigida/ | I69: “A circulação de veículos com escapamentos adulterados, festas irregulares e obras fora do horário permitido são exemplos de abusos que afetam diretamente a saúde, o bem-estar e o sossego da população. Precisamos regulamentar com rigor e garantir o direito ao silêncio”, afirma o autor do projeto, vereador Flavio Valle. | J69: A Câmara Municipal do Rio de Janeiro analisa o Projeto de Lei nº 431/2025, de autoria do vereador Flavio Valle, que propõe a padronização das medidas de combate à poluição sonora na cidade. O texto define limites de emissão de ruídos, métodos de medição, hipóteses de permissão e proibição, além de prever sanções para infratores e a criação de um mapa de ruído urbano.
A70: RELEASE | B70: 45783 | C70: =(IF(ISBLANK(B70),"",TEXT(DATE(MID(B70,7,4), MID(B70,4,2), MID(B70,1,2)), "mm/yyyy"))) -> 05/2025 | D70: Turismo | E70: Airbnb: reunião sobre Segurança Pública promete novo embate entre os vereadores da comissão | F70: AGENDA DO PODER | G70: AMANDA RAITER | H70: https://agendadopoder.com.br/airbnb-reuniao-sobre-seguranca-publica-promete-novo-embate-entre-os-vereadores-da-comissao/ | J70: Ao certo, Valle, que é presidente da Comissão de Turismo, estaria decidido concluir discussões com os envolvidos, através de audiências públicas para protocolar um de sua autoria.
A71: RELEASE | B71: 45783 | C71: =(IF(ISBLANK(B71),"",TEXT(DATE(MID(B71,7,4), MID(B71,4,2), MID(B71,1,2)), "mm/yyyy"))) -> 05/2025 | D71: Ordenamento | E71: Rio pode ganhar penas mais duras contra o barulho e criar selo turístico para impulsionar setor | F71: AGENDA DO PODER | G71: AMANDA RAITER | H71: https://agendadopoder.com.br/rio-pode-ganhar-penas-mais-duras-contra-o-barulho-e-criar-selo-turistico-para-impulsionar-setor/#google_vignette | I71: “Estamos modernizando a legislação para dar mais efetividade ao combate a esse problema que afeta a qualidade de vida dos cariocas e maior previsibilidade fiscalizatória”, relata Valle, que completou que o projeto pode permitir à cidade ter “uma legislação moderna e alinhada com as melhores práticas nacionais”. | J71: O vereador Flávio Valle (PSD) protocolou, nesta terça-feira (6), dois projetos de lei criados para melhorar a qualidade de vida dos cariocas. O primeiro, o nº 431/2025, tem intuito de unificar e atualizar as normas de combate à poluição sonora no município, revogando a Lei Nº 6179/2017, que atualmente regula o tema.
A72: RELEASE | B72: 45783 | C72: =(IF(ISBLANK(B72),"",TEXT(DATE(MID(B72,7,4), MID(B72,4,2), MID(B72,1,2)), "mm/yyyy"))) -> 05/2025 | D72: Turismo | E72: Lady Gaga: vereadores usam redes sociais como palco de debate sobre o retorno financeiro | F72: AGENDA DO PODER | G72: AMANDA RAITER | H72: https://agendadopoder.com.br/lady-gaga-vereadores-usam-redes-sociais-como-palco-de-debate-sobre-o-retorno-financeiro/ | J72: Na base de Eduardo Paes, prefeito que garantiu a vinda da musa pop, o economista por formação e parlamentar de primeiro mandato Flávio Valle (PSD) lançou, nesta terça-feira (6), um vídeo em que ele desmente outro economista que joga para baixo os números de retorno financeiro da artista na cidade, mostrando que o montante superou expectativas.
A73: NOTA | B73: 45783 | C73: =(IF(ISBLANK(B73),"",TEXT(DATE(MID(B73,7,4), MID(B73,4,2), MID(B73,1,2)), "mm/yyyy"))) -> 05/2025 | D73: Ordenamento | E73: Procon flagra lojas do Rio oferecendo desbloqueio ilegal de velocidade em bicicletas elétricas | F73: G1 | G73: Guilherme Peixoto, André Coelho Costa, RJ2 | H73: https://g1.globo.com/rj/rio-de-janeiro/noticia/2025/05/06/procon-flagra-lojas-do-rio-oferecendo-desbloqueio-ilegal-de-velocidade-em-bicicletas-eletricas.ghtml?utm_source=share-universal&utm_medium=share-bar-app&utm_campaign=materias | I73: O que tá acontecendo é que as lojas estão vendendo um veículo que é autopropelido, mas na hora elas oferecem o aumento ali da velocidade através de mudança de software permitindo que esses veículos ultrapassem a velocidade de 32 km que é permitida pelo Contran para os autopropelidos", explicou o vereador Flávio Valle. | J73: O vereador Flávio Valle (PSD) protocolou um projeto de lei na Câmara do Rio para estabelecer regras a quem vende ou aluga bicicletas elétricas no município. O objetivo da proposta é proibir que as lojas que vendem esses veículos façam a adulteração dessa velocidade. O projeto também obriga as lojas a informar ao consumidor o que que ele está comprando e onde ele pode transitar.
A74: NOTÍCIA | B74: 45784 | C74: =(IF(ISBLANK(B74),"",TEXT(DATE(MID(B74,7,4), MID(B74,4,2), MID(B74,1,2)), "mm/yyyy"))) -> 05/2025 | D74: Ordenamento | E74: Barulho excessivo no Rio de Janeiro | F74: HORA H | H74: https://www.iclipping.com.br/noticia/86/15783666 | J74: A Câmara Municipal do Rio de Janeiro analisa o Projeto de Lei no 431/2025, de autoria do vereador Flavio Valle, que propõe a padronização das medidas de combate à poluição sonora na cidade. O texto define limites de emissão de ruídos, métodos de medição, hipóteses de permissão e proibição, além de prever sanções para infratores e a criação de um mapa de ruído urbano.
A75: RELEASE | B75: 45784 | C75: =(IF(ISBLANK(B75),"",TEXT(DATE(MID(B75,7,4), MID(B75,4,2), MID(B75,1,2)), "mm/yyyy"))) -> 05/2025 | D75: Ordenamento | E75: Bicicletas elétricas com velocidade adulterada viram alvo de operação no Rio | F75: DIÁRIO DO RIO | G75: QUINTINO GOMES FREIRE | H75: https://diariodorio.com/bicicletas-eletricas-com-velocidade-adulterada-viram-alvo-de-operacao-no-rio/ | I75: “Apesar de parecer vantagem para o consumidor, essa prática configura uma armadilha que pode causar acidentes graves e viola a legislação de trânsito”, alertou Flávio Valle. | J75: Uma operação de fiscalização realizada na Zona Sul do Rio de Janeiro revelou práticas irregulares envolvendo a venda e adulteração de bicicletas elétricas. A ação, liderada pelo vereador Flávio Valle com apoio da Secretaria Municipal de Defesa do Consumidor, ocorreu em resposta ao aumento de acidentes provocados por veículos que ultrapassam os limites legais de velocidade.
A76: RELEASE | B76: 45784 | C76: =(IF(ISBLANK(B76),"",TEXT(DATE(MID(B76,7,4), MID(B76,4,2), MID(B76,1,2)), "mm/yyyy"))) -> 05/2025 | D76: Ordenamento | E76: Lojas da Zona Sul do Rio adulteram limitador de velocidade de bicicletas elétricas | F76: BAND NEWS | G76: VINICIUS CALIXTO | H76: https://www.band.com.br/bandnews-fm/rio-de-janeiro/noticias/lojas-da-zona-sul-do-rio-adulteram-limitador-de-velocidade-de-bicicletas-eletricas-202505071615 | J76: O vereador Flávio Valle, que recebeu as denúncias, protocolou um Projeto de Lei na Câmara dos Vereadores que estabelece regras para quem vende ou aluga bicicletas no município do Rio, com o objetivo de impedir que as lojas adulterem as leis e causem prejuízos ao consumidor.
A77: NOTA | B77: 45784 | C77: =(IF(ISBLANK(B77),"",TEXT(DATE(MID(B77,7,4), MID(B77,4,2), MID(B77,1,2)), "mm/yyyy"))) -> 05/2025 | D77: Ordenamento | E77: Ação identifica adulteração de velocidade de bicicletas elétricas em lojas da Zona Sul | F77: O DIA | H77: https://odia.ig.com.br/rio-de-janeiro/2025/05/7052048-acao-identifica-adulteracao-de-velocidade-de-bicicletas-eletricas-em-lojas-da-zona-sul.html | J77: A fiscalização foi realizada no último dia 30, pela Secretaria Municipal de Defesa do Consumidor, depois que denúncias feitas ao vereador Flávio Valle (PSD) relataram que algumas lojas vendem bicicletas elétricas e oferecem a adulteração, para ultrapassar o limite permitido de 32 km/h, com a retirada de limitadores de velocidade.
A78: RELEASE | B78: 45785 | C78: =(IF(ISBLANK(B78),"",TEXT(DATE(MID(B78,7,4), MID(B78,4,2), MID(B78,1,2)), "mm/yyyy"))) -> 05/2025 | D78: Combate ao Antissemitismo | E78: Dia das Mães: Marcada pelo Holocausto, Liliana Syrkis recebe medalha pós-morte | F78: AGENDA DO PODER | G78: AMANDA RAITER | H78: https://agendadopoder.com.br/dia-das-maes-marcada-pelo-holocausto-liliana-syrkis-recebe-medalha-pos-morte/ | I78: “Liliana foi muito mais do que uma grande dama da alta costura carioca. Ela foi uma mulher judia que sobreviveu à Segunda Guerra e também sofreu com a ditadura brasileira. Sua história é um exemplo de resiliência e sobrevivência. Merece nossos aplausos e o mais profundo respeito”, afirma. | J78: Representante da comunidade judaica na Câmara do Rio, o vereador de primeiro mandato Flávio Valle (PSD) concederá, no dia 15, a Medalha Chiquinha Gonzaga à memória de Liliana Syrkis, uma das figuras mais marcantes da comunidade judaica e polonesa no Rio de Janeiro e mãe do então vereador carioca e ex-deputado federal Alfredo Syrkis, no Salão Nobre.
A79: RELEASE | B79: 45786 | C79: =(IF(ISBLANK(B79),"",TEXT(DATE(MID(B79,7,4), MID(B79,4,2), MID(B79,1,2)), "mm/yyyy"))) -> 05/2025 | D79: Mandato | E79: ‘Efeito Trump’ leva Pedro Paulo à Europa | F79: AGENDA DO PODER | G79: AMANDA RAITER | H79: https://agendadopoder.com.br/efeito-trump-leva-pedro-paulo-a-europa/ | J79: O deputado federal Pedro Paulo (PSD) foi convidado pelo Fórum Europa e pelo Instituto Brasileiro de Ensino, Desenvolvimento e Pesquisa (IDP), para participar do 2º Foro Transformaciones – Un Mundo en Ebullición (em português, Fórum Transformações – Um mundo em ebulição), em Madrid, na Espanha, junto com o vereador e membro da Comissão de Orçamento da Câmara do Rio Flávio Valle (PSD), que é economista por formação. A iniciativa acontece até esta sexta-feira (9).
A80: RELEASE | B80: 45787 | C80: =(IF(ISBLANK(B80),"",TEXT(DATE(MID(B80,7,4), MID(B80,4,2), MID(B80,1,2)), "mm/yyyy"))) -> 05/2025 | D80: Mandato | E80: Presidente da Comissão de Turismo da Câmara do Rio fica ferido após tentativa de assalto em Madri | F80: O GLOBO | G80: FERNANDA TORRES | H80: https://oglobo.globo.com/blogs/ancelmo-gois/post/2025/05/presidente-da-comissao-de-turismo-da-camara-do-rio-fica-ferido-apos-tentativa-de-assalto-em-madri.ghtml | I80: "Eu comecei dar golpes e socos no cara", diz o vereador, que ficou machucado. "Um morador estava passando e eu acabei entrando no prédio junto com ele e liguei para a polícia". | J80: O vereador Flavio Valle (PSD), presidente da Comissão de Turismo da Câmara Municipal do Rio, ficou ferido durante uma tentativa de assalto em Madri, na Espanha. O vereador havia participado do "Fórum de Integração Brasil Europa" com o deputado Pedro Paulo (PSD). Após o seminário, eles saíram para jantar. Flavio Valle estava sozinho quando foi abordado por um homem, por volta da 0h (horário local), na Praça Tirso de Molina. Ele caminhava em direção a seu Airbnb. O assaltante, desarmado, pediu o celular. Como o vereador se reusou a entregá-lo, os dois entraram em luta corporal.
A81: RELEASE | B81: 45787 | C81: =(IF(ISBLANK(B81),"",TEXT(DATE(MID(B81,7,4), MID(B81,4,2), MID(B81,1,2)), "mm/yyyy"))) -> 05/2025 | D81: Mandato | E81: Vereador Flavio Valle é agredido durante tentativa de assalto em Madri | F81: PORTAL TELA | H81: https://www.portaltela.com/noticias/casos-de-policia/2025/05/10/vereador-flavio-valle-e-agredido-durante-tentativa-de-assalto-em-madri | I81: "Eu comecei a dar golpes e socos no cara", relatou Valle. Durante a confusão, um morador que passava pelo local ajudou o vereador a entrar em um prédio, onde ele conseguiu ligar para a polícia. | J81: O vereador Flavio Valle (PSD), presidente da Comissão de Turismo da Câmara Municipal do Rio, foi ferido em uma tentativa de assalto em Madri, na Espanha. O incidente ocorreu por volta da 0h (horário local) enquanto ele caminhava em direção ao seu Airbnb após participar do "Fórum de Integração Brasil Europa" com o deputado Pedro Paulo (PSD).
A82: RELEASE | B82: 45787 | C82: =(IF(ISBLANK(B82),"",TEXT(DATE(MID(B82,7,4), MID(B82,4,2), MID(B82,1,2)), "mm/yyyy"))) -> 05/2025 | D82: Mandato | E82: Vereador carioca assaltado em Madrid fala com exclusividade ao Agenda do Poder: “Cheguei a lutar no chão, mas estou bem” (vídeo) | F82: AGENDA DO PODER | G82: AMANDA RAITER | H82: https://agendadopoder.com.br/vereador-carioca-assaltado-em-madrid-fala-com-exclusividade-ao-agenda-do-poder-cheguei-a-lutar-no-chao-mas-estou-bem-video/ | I82: “Cheguei a lutar no chão, mas estou bem. A imobilização é por precaução, pois amanhã (11) tenho voo para o Brasil”, diz o parlamentar, que ficará enfaixado por uma semana por causa de um dedo. | J82: O mais jovem vereador da Câmara do Rio, Flávio Valle (PSD), deu agora à noite, madrugada na Espanha, detalhes exclusivos ao Agenda do Poder sobre o assalto sofrido por ele, na madrugada deste sábado, 10, em Madrid capital espanhola. Ele deu detalhes de como reagiu à tentativa violenta de tomada de seu celular e cordão.
A83: NOTA | B83: 45787 | C83: =(IF(ISBLANK(B83),"",TEXT(DATE(MID(B83,7,4), MID(B83,4,2), MID(B83,1,2)), "mm/yyyy"))) -> 05/2025 | D83: Mandato | E83: Vereador Flávio Valle fica ferido em tentativa de assalto na Espanha | F83: TEMPO REAL | H83: https://temporealrj.com/vereador-flavio-valle-fica-ferido-em-tentativa-de-assalto-na-espanha/ | I83: “Eu comecei a dar golpes e socos no cara”, relatou Flávio Valle | J83: O vereador Flávio Valle (PSD), presidente da Comissão de Turismo da Câmara do Rio, ficou ferido durante uma tentativa de assalto em Madri, na Espanha. As informações são da jornalista Fernanda Pontes, da coluna de Ancelmo Gois, no jornal O Globo.
A84: NOTA | B84: 45787 | C84: =(IF(ISBLANK(B84),"",TEXT(DATE(MID(B84,7,4), MID(B84,4,2), MID(B84,1,2)), "mm/yyyy"))) -> 05/2025 | D84: Mandato | E84: Vereador do Rio Flavio Valle é ferido em tentativa de assalto em Madri | F84: AGENDA DO PODER | H84: https://youtu.be/-DaPXuZGZS8?si=lFImliCquYO493NE | I84: cheguei a ficar caído no chão junto com o cara enfim e fiz muito para me proteger porque eu vi ali também que ele não tava armado sei que a gente não deve reagir a assalto né mas acho que é é basicamente isso que eu tenho a dizer pera aí meio curioso que eu vim participar desse seminário aqui que eu fui convidado e eu tava estudando né os temas aqui de Madrid e um deles era segurança pública né a gente sabe que todo país tem desafio de segurança pública né mas aqui a Europa é sempre país muito bem organizado as polícias ativas etc
A85: ARTIGO | B85: 45789 | C85: =(IF(ISBLANK(B85),"",TEXT(DATE(MID(B85,7,4), MID(B85,4,2), MID(B85,1,2)), "mm/yyyy"))) -> 05/2025 | D85: Ordenamento | E85: Flávio Valle - A orla carioca: um patrimônio que precisa de regras claras | F85: O DIA | G85: FLAVIO VALLE | H85: https://odia.ig.com.br/opiniao/2025/05/7054279-flavio-valle-a-orla-carioca-um-patrimonio-que-precisa-de-regras-claras.html | I85: Vamos juntos transformar nossa orla em um legado duradouro para o futuro!
A86: NOTA | B86: 45789 | C86: =(IF(ISBLANK(B86),"",TEXT(DATE(MID(B86,7,4), MID(B86,4,2), MID(B86,1,2)), "mm/yyyy"))) -> 05/2025 | D86: Ordenamento | E86: Treta à vista no BotaSoho: projeto quer transformar a Arnaldo Quintela em área de especial interesse turístico | F86: TEMPO REAL | G86: BERENICE SEARA | H86: https://temporealrj.com/treta-a-vista-no-botasoho-projeto-quer-transformar-a-arnaldo-quintela-em-area-de-especial-interesse-turistico/ | I86: “Sua atmosfera boêmia, acolhedora e autenticamente carioca atrai turistas brasileiros e estrangeiros em busca de uma vivência cultural rica e próxima do cotidiano local. Bares com identidade própria, restaurantes que exaltam a culinária brasileira e internacional, além de uma programação musical diversificada, fazem da rua uma parada obrigatória para quem deseja explorar a cidade sob uma ótica contemporânea e vibrante”, diz Valle, na justificativa do projeto. | J86: O vereador Flávio Valle (PSD), um dos queridinhos do prefeito Eduardo Paes (PSD), protocolou um projeto de lei para considerar a Rua Arnaldo Quintela — o reino dos bares em Botafogo — “de interesse turístico, cultural e social”.
A87: NOTA | B87: 45789 | C87: =(IF(ISBLANK(B87),"",TEXT(DATE(MID(B87,7,4), MID(B87,4,2), MID(B87,1,2)), "mm/yyyy"))) -> 05/2025 | D87: Ordenamento | E87: Vereador apresenta lei para proibir alteração no limite de velocidade de bicicletas elétricas | F87: TEMPO REAL | H87: https://temporealrj.com/vereador-apresenta-lei-para-proibir-alteracao-no-limite-de-velocidade-de-bicicletas-eletricas/ | I87: “A alteração de dispositivos de segurança e alteração do limite de velocidade representa a violação da legislação vigente, além de colocar em risco a vida do próprio condutor e de terceiros”, diz o vereador, na justificativa do projeto. | J87: Foi publicado no Diário Oficial desta segunda-feira (12) o projeto de lei do vereador Flávio Valle (PSD) que proíbe “qualquer alteração no limite de velocidade definido pelos fabricantes para bicicletas elétricas”. Se for aprovado, o texto avisa que a vedação vale tanto para lojas e estabelecimentos que vendem ou alugam as magrelas, quanto para os usuários.
A88: RELEASE | B88: 45789 | C88: =(IF(ISBLANK(B88),"",TEXT(DATE(MID(B88,7,4), MID(B88,4,2), MID(B88,1,2)), "mm/yyyy"))) -> 05/2025 | D88: Mandato | E88: Cegonha à solta na Prefeitura – Bastidores do Rio | F88: DIARIO DO RIO | G88: QUINTINO GOMES FREIRE | H88: https://diariodorio.com/cegonha-a-solta-na-prefeitura-bastidores-do-rio/ | J88: Defensor do Airbnb no Rio, o vereador Flávio Valle usou o modelo de estadia em sua viagem para Madrid.
A89: RELEASE | B89: 45790 | C89: =(IF(ISBLANK(B89),"",TEXT(DATE(MID(B89,7,4), MID(B89,4,2), MID(B89,1,2)), "mm/yyyy"))) -> 05/2025 | D89: Meio Ambiente | E89: Lagoa Rodrigo de Freitas pode ganhar status de Unidade de Conservação | F89: DIÁRIO DO RIO | G89: QUINTINO GOMES FREIRE | H89: https://diariodorio.com/lagoa-rodrigo-de-freitas-pode-ganhar-status-de-unidade-de-conservacao/ | I89: “A proposta reforça o compromisso do Rio de Janeiro com a preservação ambiental e a sustentabilidade urbana” — destacou Flávio Valle | J89: O Diário Oficial da Câmara Municipal do Rio de Janeiro divulgou os Projetos de Lei 512 e 513/2025, de autoria do vereador Flávio Valle, que visam transformar áreas naturalizadas da Lagoa Rodrigo de Freitas, nos trechos do Parque dos Patins e do Parque do Cantagalo, em Área de Especial Interesse Ambiental (AEIA). A medida tem como objetivo consolidar esses espaços como Unidade de Conservação, garantindo sua preservação ambiental.
A90: NOTA | B90: 45791 | C90: =(IF(ISBLANK(B90),"",TEXT(DATE(MID(B90,7,4), MID(B90,4,2), MID(B90,1,2)), "mm/yyyy"))) -> 05/2025 | D90: Combate ao Antissemitismo | E90: Exposição conta história judaica do Rio pelo olhar do advogado Samuel Malamud | F90: O GLOBO | G90: FERNANDA PONTES | H90: https://oglobo.globo.com/blogs/ancelmo-gois/post/2025/05/exposicao-conta-historia-judaica-do-rio-pelo-olhar-do-advogado-samuel-malamud.ghtml | I90: Com a curadoria da equipe do Arquivo Geral da Cidade do Rio de Janeiro, em parceria com a Câmara Municipal, a mostra é uma iniciativa do vereador Flávio Valle, presidente da Comissão Parlamentar de Combate ao Antissemitismo, com curadoria do Arquivo Geral da Cidade do Rio de Janeiro, por meio da Secretaria municipal de Cultura.
A91: RELEASE | B91: 45791 | C91: =(IF(ISBLANK(B91),"",TEXT(DATE(MID(B91,7,4), MID(B91,4,2), MID(B91,1,2)), "mm/yyyy"))) -> 05/2025 | D91: Conservação | E91: Ex-subprefeito quer lei para expandir ‘tutela’ de praças pela iniciativa privada | F91: AGENDA DO PODER | G91: AMANDA RAITER | H91: https://agendadopoder.com.br/ex-subprefeito-quer-lei-para-expandir-tutela-de-pracas-pela-iniciativa-privada/ | I91: Com o Adoção Carioca, vamos substituir um modelo defasado por uma política moderna, capaz de engajar cidadãos e empresas na melhoria dos espaços públicos. A cidade ganha com mais conservação, sustentabilidade e zelo pelo patrimônio urbano”, explica. | J91: Gestor de um mandato da zona sul, onde foi subprefeito, o vereador Flávio Valle (PSD) tirou inspiração do passado operacional para mais um projeto que pode virar lei no Rio: instituir adoção de espaços públicos na cidade do Rio de Janeiro, para que a iniciativa privada passe a auxiliar a Prefeitura na conservação.
A92: COLUNA | B92: 45792 | C92: =(IF(ISBLANK(B92),"",TEXT(DATE(MID(B92,7,4), MID(B92,4,2), MID(B92,1,2)), "mm/yyyy"))) -> 05/2025 | D92: Ordenamento | E92: Pensando a orla do futuro: foi marcada audiência pública | F92: VEJA RIO | G92: LU LACERDA | H92: https://vejario.abril.com.br/coluna/lu-lacerda/pensando-a-orla-do-futuro-foi-marcada-audiencia-publica/ | I92: O projeto busca consolidar um modelo de gestão integrada, alinhado aos Objetivos de Desenvolvimento Sustentável (ODS) da ONU, garantindo equilíbrio entre desenvolvimento econômico, preservação ambiental e inclusão social. E todo mundo pode participar: moradores, comerciantes, empresários de turismo… Pra gente aprimorar o projeto”, diz Valle. | J92: Está marcada, para a próxima terça (20/05), uma audiência pública na Câmara Municipal, promovida pelo vereador Flavio Valle (PSD), para falar sobre o “Estatuto da Orla”, com participação do prefeito Eduardo Paes. O projeto busca regulamentar, de forma unificada, o uso da orla carioca, abrangendo praias, calçadões, parques, ciclovias etc.
A93: RELEASE | B93: 45791 | C93: =(IF(ISBLANK(B93),"",TEXT(DATE(MID(B93,7,4), MID(B93,4,2), MID(B93,1,2)), "mm/yyyy"))) -> 05/2025 | D93: Ordenamento | E93: Audiência pública na Câmara discutirá regulamentação da orla do Rio | F93: DIÁRIO DO RIO | G93: VICTOR SERRA | H93: https://diariodorio.com/audiencia-publica-na-camara-discutira-regulamentacao-da-orla-do-rio/ | J93: A Câmara Municipal do Rio vai realizar, na próxima segunda-feira (20/05), às 10h, uma audiência pública para discutir o Projeto de Lei nº 488/2025, que institui o Estatuto da Orla da cidade. A proposta é do vereador Flávio Valle (PSD), presidente da Comissão de Turismo, e busca regulamentar de forma unificada o uso da orla carioca, incluindo praias, calçadões, ciclovias, parques e demais espaços urbanos litorâneos.
A94: NOTA | B94: 45792 | C94: =(IF(ISBLANK(B94),"",TEXT(DATE(MID(B94,7,4), MID(B94,4,2), MID(B94,1,2)), "mm/yyyy"))) -> 05/2025 | D94: Mandato | E94: Fogo no palácio: Diego Vaz provoca Rogério Amorim e surge mascarado na Câmara | F94: TEMPO REAL | G94: VITOR D'AVILA | H94: https://temporealrj.com/fogo-no-palacio-diego-vaz-provoca-rogerio-amorim-e-surge-mascarado-na-camara/
A95: RELEASE | B95: 45792 | C95: =(IF(ISBLANK(B95),"",TEXT(DATE(MID(B95,7,4), MID(B95,4,2), MID(B95,1,2)), "mm/yyyy"))) -> 05/2025 | D95: Mandato | E95: Mascarados, em ironia a ex-assessor de Amorim, atrasam sessão na Câmara | F95: AGENDA DO PODER | G95: AMANDA RAITER | H95: https://agendadopoder.com.br/mascarados-em-ironia-a-ex-assessor-de-amorim-atrasam-sessao-na-camara/ | I95: Já Flávio lembrou que o secretário afastou Monique, mas a ré conseguiu o direito na Justiça de ocupar cargo na Secretaria de Educação e ainda lembrou que o ‘mascarado’, ex-assessor de Amorim, também integrou o governo Wilson Witzel. | J95: Testemunhas ainda teriam visto pessoas da equipe do vereador e ex-prefeito da Zona Sul Flávio Valle distribuindo a indumentária. Valle já chefiou Santos na época de Executivo e, recentemente, fez uma parceria na fiscalização de lojas que vendem bicicletas elétricas com adulteração, que gerou uma lei, já aprovada pelo Executivo, de autoria de Flávio Valle. Já o gabinete do parlamentar psdista nega a distribuição do item, alegando que as máscaras chegaram à Cinelândia, causando a brincadeira entre os presentes.
A96: RELEASE | B96: 45792 | C96: =(IF(ISBLANK(B96),"",TEXT(DATE(MID(B96,7,4), MID(B96,4,2), MID(B96,1,2)), "mm/yyyy"))) -> 05/2025 | D96: Combate ao Antissemitismo | E96: Filho do ex-deputado Syrkis recebe homenagem da avó Liliana na Câmara | F96: AGENDA DO PODER | G96: AMANDA RAITER | H96: https://agendadopoder.com.br/filho-do-ex-deputado-syrkis-recebe-homenagem-da-avo-liliana-na-camara/ | J96: Militante e mãe do ex-deputado federal e ex-vereador Alfredo Syrkis, Liliana Syrkis foi a escolhida pelo vereador Flávio Valle (PSD) para, não só receber a póstuma Medalha Chiquinha Gonzaga, como também simbolizar a luta contra o antissemitismo e os 77 anos da criação de Israel.
A97: COLUNA | B97: 45792 | C97: =(IF(ISBLANK(B97),"",TEXT(DATE(MID(B97,7,4), MID(B97,4,2), MID(B97,1,2)), "mm/yyyy"))) -> 05/2025 | D97: Combate ao Antissemitismo | E97: Câmara: medalha para Liliana Syrkis e moção para organizações judaicas | F97: VEJA RIO | G97: LU LACERDA | H97: https://vejario.abril.com.br/coluna/lu-lacerda/camara-medalha-para-liliana-syrkis-e-mocao-para-organizacoes-judaicas/ | J97: Nesta quinta (15/05), em cerimônia na Câmara, o vereador Flávio Valle homenageou Liliana Syrkis, morta aos 101 anos em fevereiro, com a Medalha Chiquinha Gonzaga, por sua contribuição à Cultura no Rio...
A98: NOTA | B98: 45793 | C98: =(IF(ISBLANK(B98),"",TEXT(DATE(MID(B98,7,4), MID(B98,4,2), MID(B98,1,2)), "mm/yyyy"))) -> 05/2025 | D98: Ordenamento | E98: Prefeitura vai fazer parceria com empresas para fiscalizar motos por aplicativo | F98: TEMPO REAL | H98: https://temporealrj.com/prefeitura-vai-fazer-parceria-com-empresas-para-fiscalizar-motos-por-aplicativo/ | J98: O prefeito Eduardo Paes (PSD) deu a informação, nesta sexta-feira (16), em encontro com barraqueiros de praia e o vereador Flávio Valle (PSD). A medida, afirma, vai permitir a fiscalização em tempo real das motos de entrega por aplicativo. Segundo Paes, o monitoramento será feito via GPS.
A99: NOTA | B99: 45794 | C99: =(IF(ISBLANK(B99),"",TEXT(DATE(MID(B99,7,4), MID(B99,4,2), MID(B99,1,2)), "mm/yyyy"))) -> 05/2025 | D99: Combate ao Antissemitismo | E99: Rio terá exposição que resgata memória cultural judaica e reforça combate ao antissemitismo | F99: O GLOBO | G99: FELIPE GRINBERG | H99: https://oglobo.globo.com/rio/noticia/2025/05/17/rio-tera-exposicao-que-resgata-memoria-cultural-judaica-e-reforca-combate-ao-antissemitismo.ghtml | I99: É uma oportunidade única para resgatar e valorizar a memória cultural judaica no Rio. Preservar essa história é essencial não para reconhecer a contribuição da comunidade judaica para a cidade, combater o antissemitismo e fortalecer valores de respeito e diversidade. Queremos incentivar o conhecimento histórico e promover um debate fundamental sobre identidade e convivência cultural — disse Valle. | J99: A exposição é uma iniciativa do vereador Flávio Valle (PSD), presidente da Comissão Parlamentar de Combate ao Antissemitismo, com apoio do Arquivo Geral da Cidade do Rio de Janeiro por meio da Secretaria Municipal de Cultura.
A100: NOTA | B100: 45796 | C100: =(IF(ISBLANK(B100),"",TEXT(DATE(MID(B100,7,4), MID(B100,4,2), MID(B100,1,2)), "mm/yyyy"))) -> 05/2025 | D100: Ordenamento | E100: Aviso de Pauta: Comissão de Turismo realiza audiência pública sobre o Estatuto da Orla da Cidade | F100: CÂMARA MUNICIPAL DO RIO DE JANEIRO | H100: https://www.camara.rio/comunicacao/noticias/2633-aviso-de-pauta-comissao-de-turismo-realiza-audiencia-publica-sobre-o-estatuto-da-orla-da-cidade | J100: A Comissão de Turismo da Câmara do Rio realiza, nesta terça-feira (20/05), às 10h, uma audiência pública para debater o Projeto de Lei nº 488/2025, que institui o Estatuto da Orla da Cidade. A proposta é de autoria do vereador Flávio Valle (PSD), presidente da comissão.
...

Sheet Comunicação Digital
A1: TIPO DE CONTEÚDO | B1: DATA | C1: MÊS | D1: ASSUNTO | E1: LEGENDA | F1: FORMATO | G1: LINK | H1: INTERAÇÕES | I1: LIKES | J1: COMENTÁRIOS | K1: COMPARTILHAMENTO | L1: REPUBLICADOS | M1: SALVOS | AT1: Interações | AU1: Mês
A2: APRESENTAÇÃO | B2: 45658 | C2: =TEXT(B2, "mm/yyyy") -> 01/2025 | D2: Mandato | E2: De prefeitinho a vereador! 😉 Ano novo, novo desafio! Hoje, tomei posse como vereador do Rio e já começamos com tudo. O Prefeito Eduardo Paes anunciou 46 decretos para tornar nossa cidade mais segura, tecnológica e conectada. 💻🚓 Agora, meu compromisso é fiscalizar e garantir que essas ações continuem a ser implementadas, transformando a vida dos cariocas. Vamos juntos por um Rio ainda melhor! 🫶🏻❤️ | F2: Reels | G2: https://www.instagram.com/p/DETPZYsypg_/ | H2: =I2+J2+K2+L2+M2 -> 2503 | I2: 2137 | J2: 246 | K2: 98 | L2: 0 | M2: 22 | AS2: 45728 | AT2: =I2+J2+K2 -> 2481 | AU2: =TEXT(AS2,"mmmm/yyyy") -> março/2025
A3: APRESENTAÇÃO | B3: 45658 | C3: =TEXT(B3, "mm/yyyy") -> 01/2025 | D3: Mandato | E3: Empossado Vereador! Uma honra poder representar os cariocas no parlamento! Contem comigo! 💪 | F3: Carrossel de Fotos | G3: https://www.instagram.com/p/DES_f4HSRLI/ | H3: =I3+J3+K3+M3 -> 1598 | I3: 1439 | J3: 134 | K3: 19 | L3: 0 | M3: 6 | U3: MÊS | V3: Causa Animal | W3: Combate ao Antissemitismo | X3: Conservação | Y3: Economia | Z3: Esporte e Lazer | AA3: Gabinete | AB3: Meio Ambiente | AC3: Ordenamento | AD3: Saúde | AE3: Segurança | AF3: Turismo | AI3: MÊS | AJ3: NOTA | AK3: COLUNA | AL3: ENTREVISTA | AM3: MATÉRIA | AN3: ARTIGO | AO3: NOTÍCIA | AP3: REDAÇÃO | AQ3: REPORTAGEM | AR3: RELEASE | AS3: 45728 | AT3: =I3+J3+K3 -> 1592 | AU3: =TEXT(AS3,"mmmm/yyyy") -> março/2025
A4: LIFESTYLE | B4: 45658 | C4: =TEXT(B4, "mm/yyyy") -> 01/2025 | D4: Esporte e Lazer | E4: Esse trio vai trabalhar muito pela cidade e pela Zona Sul nos próximos anos. Dudu é tetra! Feliz Ano Novo! | F4: Carrossel de Fotos | G4: https://www.instagram.com/p/DEROZYaO0vz/ | H4: =I4+J4+K4+M4 -> 3043 | I4: 2899 | J4: 105 | K4: 26 | L4: 0 | M4: 13 | U4: janeiro/2025 | W4: 9 | AI4: janeiro/2025 | AJ4: 1 | AN4: 1 | AR4: 7 | AS4: 45728 | AT4: =I4+J4+K4 -> 3030 | AU4: =TEXT(AS4,"mmmm/yyyy") -> março/2025
A5: DENÚNCIA | B5: 45664 | C5: =TEXT(B5, "mm/yyyy") -> 01/2025 | D5: Meio Ambiente | E5: Nesse final de semana, recebi várias reclamações sobre o lixo nas praias da Zona Sul. É triste ver esse espaço tão especial da nossa cidade assim. 🏖️🗑️ Mas embora muitas críticas tenham sido voltadas para a atuação da @prefeitura_rio e da @comlurbcomunica , será que essa é mesmo a realidade? Elas estão sempre atuando com planejamento e, mais uma vez, já deixaram tudo limpo pra gente aproveitar outra vez. 🧹✨ Além disso, o prefeito @eduardopaes tem investido pesadamente na COMLURB por meio da compra de novos equipamentos de limpeza, tecnologia e valorização dos garis. E aí, será que o problema não está na falta de cuidado e consciência de quem frequenta esses lugares? 🌊 A cidade é nossa, e cuidar dela também é nossa responsabilidade! 💚 | F5: Reels | G5: https://www.instagram.com/p/DEhfTijOeG_/ | H5: =I5+J5+K5+L5+M5 -> 2529 | I5: 1918 | J5: 396 | K5: 200 | L5: 0 | M5: 15 | U5: fevereiro/2025 | W5: 5 | AA5: 4 | AB5: 2 | AC5: 2 | AE5: 2 | AF5: 3 | AI5: fevereiro/2025 | AJ5: 6 | AN5: 1 | AR5: 11 | AS5: 45847 | AT5: =I5+J5+K5 -> 2514 | AU5: =TEXT(AS5,"mmmm/yyyy") -> julho/2025 | AV5: =SUM(AT151:AT171) -> 20257 | AW5: 45658
A6: PROXIMIDADE | B6: 45668 | C6: =TEXT(B6, "mm/yyyy") -> 01/2025 | D6: Turismo | E6: Dia também de encontrar com os barraqueiros do Terreirão do Samba para dialogar a respeito do Carnaval | F6: Carrossel de Fotos | G6: https://www.instagram.com/p/DEshg7rOtjc/ | H6: =I6+J6+K6+M6 -> 158 | I6: 157 | J6: 0 | K6: 0 | L6: 0 | M6: 1 | U6: março/2025 | W6: 1 | Y6: 1 | AA6: 5 | AF6: 18 | AI6: março/2025 | AJ6: 15 | AK6: 1 | AM6: 1 | AN6: 1 | AQ6: 1 | AR6: 6 | AS6: 45847 | AT6: =I6+J6+K6 -> 157 | AU6: =TEXT(AS6,"mmmm/yyyy") -> julho/2025 | AV6: =SUM(AT122:AT150) -> 17521 | AW6: 45689
A7: PROXIMIDADE | B7: 45668 | C7: =TEXT(B7, "mm/yyyy") -> 01/2025 | D7: Conservação | E7: Manhã de sábado na Chácara do Céu com subprefeito @bernardorubiao , GEL @lealtds e meu amigo @marcelinhodociep dialogando e entendo as demandas. | F7: Carrossel de Fotos | G7: https://www.instagram.com/p/DEsQkR_OW8g/ | H7: =I7+J7+K7+M7 -> 357 | I7: 333 | J7: 14 | K7: 7 | L7: 0 | M7: 3 | U7: abril/2025 | V7: 1 | W7: 1 | Y7: 1 | Z7: 1 | AA7: 1 | AB7: 3 | AC7: 3 | AF7: 1 | AI7: abril/2025 | AJ7: 2 | AR7: 10 | AS7: 45847 | AT7: =I7+J7+K7 -> 354 | AU7: =TEXT(AS7,"mmmm/yyyy") -> julho/2025 | AV7: 14490 | AW7: 45717
A8: NOTÍCIA | B8: 45668 | C8: =TEXT(B8, "mm/yyyy") -> 01/2025 | D8: Economia | E8: O projeto da Bolsa de carbono do Rio foi viabilizado através de um projeto de Lei elaborado pela gestão do prefeito @eduardopaes estabelecendo incentivo fiscal para esse tipo de operação (redução do ISS para 2%) e criando um fundo de abatimento de ISS de R$60MM. O resultado tá aí! Além disso, destaque para o @i12_org que se consolida cada vez mais como um hub de inovação, tecnologia e desenvolvimento para a cidade! Rio, capital dos investimentos verdes! ♻️ | F8: Carrossel Estático | G8: https://www.instagram.com/p/DEr/DDcsMab/ | H8: =I8+J8+K8+M8 -> 161 | I8: 127 | J8: 9 | K8: 20 | L8: 0 | M8: 5 | U8: maio/2025 | W8: 9 | X8: 1 | AA8: 11 | AB8: 1 | AC8: 43 | AF8: 4 | AI8: maio/2025 | AJ8: 40 | AK8: 2 | AL8: 1 | AO8: 1 | AP8: 1 | AR8: 24 | AS8: 45843 | AT8: =I8+J8+K8 -> 156 | AU8: =TEXT(AS8,"mmmm/yyyy") -> julho/2025 | AV8: =SUM(AT75:AT98) -> 21623 | AW8: 45748
A9: APRESENTAÇÃO | B9: 45671 | C9: =TEXT(B9, "mm/yyyy") -> 01/2025 | D9: Mandato | E9: Ainda não foi minha vez no @bbb , mas no GVFV / Gabinete Vereador Flávio Valle / a gente já tá ao vivo, 24/7, fazendo todo o planejamento pra cuidarmos do Rio com muita dedicação. 📹 Bora dar uma espiadinha na equipe que faz tudo isso acontecer? 👀 A Câmara Municipal mais vigiada do Brasil! | F9: Carrossel Estático | G9: https://www.instagram.com/p/DEzmY3UOH1V/ | H9: =I9+J9+K9+M9 -> 1925 | I9: 1464 | J9: 157 | K9: 283 | L9: 0 | M9: 21 | AS9: 45841 | AT9: =I9+J9+K9 -> 1904 | AU9: =TEXT(AS9,"mmmm/yyyy") -> julho/2025 | AV9: =SUM(AT37:AT74) -> 26240 | AW9: 45778
A10: PROXIMIDADE | B10: 45672 | C10: =TEXT(B10, "mm/yyyy") -> 01/2025 | D10: Mandato | E10: A Câmara Municipal ainda tá de recesso, mas o nosso Gabinete já tá funcionando a pleno vapor! 💨 Nas próximas semanas, eu e minha equipe vamos conhecer alguns projetos da gestão do prefeito @eduardopaes e estudar esses casos de sucesso! Hoje, foi a vez do Super Centro Carioca de Saúde. 🏥 A unidade oferece exames, consultas e procedimentos de última geração pelo SUS. Mais de 1.500.000 atendimentos já foram realizados, com um aumento de 30% da oferta de vagas no SISREG. Um trabalho essencial para nossa cidade. Agradeço especialmente ao nosso Secretário de Saúde, @danielsoranz , pela oportunidade. Seguimos com a certeza de que, junto com o prefeito @eduardopaes , ainda vamos avançar muito na Saúde da nossa cidade! 💙 | F10: Reels | G10: https://www.instagram.com/p/DE3IbGluxjf/ | H10: =I10+J10+K10+L10+M10 -> 550 | I10: 461 | J10: 61 | K10: 22 | L10: 0 | M10: 6 | AS10: 45839 | AT10: =I10+J10+K10 -> 544 | AU10: =TEXT(AS10,"mmmm/yyyy") -> julho/2025 | AV10: =SUM(AT12:AT36) -> 67042 | AW10: 45809
A11: PROXIMIDADE | B11: 45673 | C11: =TEXT(B11, "mm/yyyy") -> 01/2025 | D11: Combate ao Antissemitismo | E11: Neste momento tão importante para o nosso povo em Israel e ao redor do mundo, em que foi anunciado o cessar fogo, vivemos um momento de fé e união na @camarario . Junto com meu amigo e vereador @marcosdiasoficial_ , realizamos a cerimônia de colocação da Mezuzá na porta do nosso gabinete como um gesto de proteção e esperança. No evento, que contou com a presença de queridos amigos da comunidade, reforcei meu compromisso como único vereador judeu das capitais brasileiras, com o diálogo, a convivência e a construção de um Rio melhor para todos nós. 🇮🇱💙 | F11: Reels | G11: https://www.instagram.com/p/DE5U7zguEn4/ | H11: =I11+J11+K11+L11+M11 -> 809 | I11: 641 | J11: 125 | K11: 39 | L11: 0 | M11: 4 | AS11: 45839 | AT11: =I11+J11+K11 -> 805 | AU11: =TEXT(AS11,"mmmm/yyyy") -> julho/2025 | AV11: =SUM(AT5:AT11) -> 6434 | AW11: 45839
A12: PROXIMIDADE | B12: 45674 | C12: =TEXT(B12, "mm/yyyy") -> 01/2025 | D12: Economia | E12: Hoje, em continuidade às visitas para conhecer iniciativas de sucesso da gestão @eduardopaes , visitamos dois exemplos incríveis de inovação e tecnologia: o Porto Maravalley e o COR, Centro de Operações Rio. O @maravalley.rio é um hub pioneiro no Brasil, conectando educação, startups e grandes empresas em um ecossistema que desenvolve soluções reais para a cidade. Já o @operacoes.rio, referência mundial em gestão urbana, opera 24/7 com mais de 5.500 câmeras, antecipando riscos e agilizando ações para tornar a cidade mais segura. Agradeço ao @daniel.b.barros, @julioazevedo.rio e @marcusbelchior pela recepção. Seguimos aprendendo para construir um Rio ainda melhor! 🚀💙 | F12: Reels | G12: https://www.instagram.com/p/DE7auOLsihQ/ | H12: =I12+J12+K12+L12+M12 -> 296 | I12: 252 | J12: 27 | K12: 16 | L12: 0 | M12: 1 | AS12: 45838 | AT12: =I12+J12+K12 -> 295 | AU12: =TEXT(AS12,"mmmm/yyyy") -> junho/2025
A13: LIFESTYLE | B13: 45675 | C13: =TEXT(B13, "mm/yyyy") -> 01/2025 | D13: Economia | E13: Sabadão é dia de estudar orçamento público no curso do professor e analista do Tesouro Nacional @paulofeijo! Obrigado pela indicação @renanferreirinha! | F13: Carrossel de Fotos | G13: https://www.instagram.com/p/DE/ftVoO2ym/ | H13: =I13+J13+K13+M13 -> 721 | I13: 646 | J13: 59 | K13: 10 | L13: 0 | M13: 6 | AS13: 45838 | AT13: =I13+J13+K13 -> 715 | AU13: =TEXT(AS13,"mmmm/yyyy") -> junho/2025
A14: PROXIMIDADE | B14: 45677 | C14: =TEXT(B14, "mm/yyyy") -> 01/2025 | D14: Conservação | E14: Participando hoje da Missa e Procissão do padroeiro da cidade do Rio de Janeiro, São Sebastião, junto com nosso prefeito em exercício @eduardo.cavaliere e @lucaswpadilha , @renanferreirinha, @delmartharocha , @marcelocalero e @rafaelaloisiofreitas . Como Vereador, reforço meu compromisso na valorização dos diferentes credos e combate a intolerância religiosa em nossa cidade. | F14: Carrossel de Fotos | G14: https://www.instagram.com/p/DFD6cuBShzP/ | H14: =I14+J14+K14+M14 -> 400 | I14: 376 | J14: 16 | K14: 7 | L14: 0 | M14: 1 | AS14: 45838 | AT14: =I14+J14+K14 -> 399 | AU14: =TEXT(AS14,"mmmm/yyyy") -> junho/2025
A15: PROBLEMA X SOLUÇÃO | B15: 45678 | C15: =TEXT(B15, "mm/yyyy") -> 01/2025 | D15: Ordenamento | E15: Recebi diversas reclamações de usuários reclamando da falta de climatização dentro de uma academia em Botafogo. Imediatamente o secretário @joaopiresx veio ao local fazer a fiscalização e notificação ao estabelecimento. Acompanharemos o caso até a situação ser resolvida! O zap do nosso gabinete está à disposição para denúncias! 21 97891/9938 | F15: Reels | G15: https://www.instagram.com/p/DFGuOJOOPYc/ | H15: =I15+J15+K15+L15+M15 -> 8072 | I15: 4005 | J15: 662 | K15: 3288 | L15: 0 | M15: 117 | AS15: 45835 | AT15: =I15+J15+K15 -> 7955 | AU15: =TEXT(AS15,"mmmm/yyyy") -> junho/2025
A16: INFORMAÇÃO | B16: 45678 | C16: =TEXT(B16, "mm/yyyy") -> 01/2025 | D16: Mandato | E16: Iniciando o Curso de Processo Legislativo da @camarario para conhecer mais sobre as leis e regulamentos. Valeu pela oportunidade presidente @carlo_caiado e @williancoelho.rj @rafaelaloisiofreitas !!! | F16: Carrossel de Fotos | G16: https://www.instagram.com/p/DFF3D91sk67/ | H16: =I16+J16+K16+M16 -> 415 | I16: 382 | J16: 27 | K16: 4 | L16: 0 | M16: 2 | AS16: 45834 | AT16: =I16+J16+K16 -> 413 | AU16: =TEXT(AS16,"mmmm/yyyy") -> junho/2025
A17: PROXIMIDADE | B17: 45682 | C17: =TEXT(B17, "mm/yyyy") -> 01/2025 | D17: Ordenamento | E17: Visita às comunidades do Tabajaras a do PPG com o subprefeito @bernardorubiao , o Gestor Local de Copacabana @brunosantos.rio e os presidentes Sávio e Marquinho para acompanhar a entrega das novas caixas de lixo da @comlurbcomunica na gestão do prefeito @eduardopaes . Ao longo das próximas semanas, diversas outras comunidades da cidade também receberão o equipamento. | F17: Carrossel de Fotos | G17: https://www.instagram.com/p/DFQZ1cKuC2J/ | H17: =I17+J17+K17+M17 -> 348 | I17: 309 | J17: 18 | K17: 18 | L17: 0 | M17: 3 | AS17: 45834 | AT17: =I17+J17+K17 -> 345 | AU17: =TEXT(AS17,"mmmm/yyyy") -> junho/2025
A18: APELO EMOCIONAL | B18: 45683 | C18: =TEXT(B18, "mm/yyyy") -> 01/2025 | D18: Combate ao Antissemitismo | E18: Relembrar para jamais repetir. O horror do Holocausto é uma marca profunda na história, que nos ensina a lutar contra o ódio e a discriminação. Hoje, reafirmamos nosso compromisso de combater o antissemitismo e a intolerância religiosa. Agradeço mais uma vez a @federacaorj, a @coniboficial e a gestão @eduardopaes por esse momento tão importante para a nossa luta diária. ✡️ | F18: Reels | G18: https://www.instagram.com/p/DFTlpTHOL36/ | H18: =I18+J18+K18+L18+M18 -> 770 | I18: 634 | J18: 83 | K18: 44 | L18: 0 | M18: 9 | AS18: 45833 | AT18: =I18+J18+K18 -> 761 | AU18: =TEXT(AS18,"mmmm/yyyy") -> junho/2025
A19: LIFESTYLE | B19: 45684 | C19: =TEXT(B19, "mm/yyyy") -> 01/2025 | D19: Saúde | E19: Dia de ganhar parabéns mas também um puxãozinho de orelha da nutri!👊🏻💪🏼 E junto com a consulta, tô lançando o desafio do GymRats e quero te convidar pra se exercitar comigo! É só clicar no link da bio e fazer parte da nossa equipe! Bora cuidar da saúde?! Te espero lá! 😉 | F19: Reels | G19: https://www.instagram.com/p/DFVkfm9O/Vy/ | H19: =I19+J19+K19+L19+M19 -> 324 | I19: 243 | J19: 26 | K19: 51 | L19: 0 | M19: 4 | AS19: 45832 | AT19: =I19+J19+K19 -> 320 | AU19: =TEXT(AS19,"mmmm/yyyy") -> junho/2025
A20: INFORMAÇÃO | B20: 45685 | C20: =TEXT(B20, "mm/yyyy") -> 01/2025 | D20: Combate ao Antissemitismo | E20: Você sabe qual é o custo do antissemitismo para o turismo no Brasil? 🤔✈️ Em um estudo inédito realizado pelo nosso gabinete, identificamos que a discriminação contra judeus afeta diretamente a imagem do país como destino turístico, afastando visitantes e gerando prejuízos para setores como hotelaria, gastronomia e lazer. Além do impacto econômico, essa realidade compromete a reputação do Brasil no cenário internacional. Combater o antissemitismo não é apenas uma questão de justiça social, mas também uma medida essencial para fortalecer nossa economia e garantir um ambiente acolhedor para todos. Quer ler o estudo completo? Acesse o link na bio! 🔗 | F20: Carrossel Estático | G20: https://www.instagram.com/p/DFYzByIuYxZ/ | H20: =I20+J20+K20+M20 -> 411 | I20: 321 | J20: 43 | K20: 34 | L20: 0 | M20: 13 | AS20: 45832 | AT20: =I20+J20+K20 -> 398 | AU20: =TEXT(AS20,"mmmm/yyyy") -> junho/2025
A21: NOTÍCIA | B21: 45687 | C21: =TEXT(B21, "mm/yyyy") -> 01/2025 | D21: Turismo | E21: ✈️✈️✈️ Com a palavra, o CEO da @voegoloficial: “A política de restringir a oferta no Santos Dumont deu certo,e a tese de que isso fortaleceria o Galeão se confirmou. Hoje as empresas internacionais estão ampliando voos para o Rio por conta da oferta de conexões que temos lá. Uma alimenta a outra.” Sem dúvida, essa foi uma das políticas públicas da gestão do prefeito @eduardopaes que mais gerou impactos de curto prazo no setor de turismo do país. Em um ano de coordenação de aeroportos, já vemos os incríveis resultados! | F21: Estático | G21: https://www.instagram.com/p/DFdGkbEuoNi/ | H21: =I21+J21+K21+M21 -> 99 | I21: 81 | J21: 10 | K21: 6 | L21: 0 | M21: 2 | AS21: 45831 | AT21: =I21+J21+K21 -> 97 | AU21: =TEXT(AS21,"mmmm/yyyy") -> junho/2025
A22: INFORMAÇÃO | B22: 45688 | C22: =TEXT(B22, "mm/yyyy") -> 01/2025 | D22: Saúde | E22: Hoje, participei da apresentação do projeto de reforma do Hospital Cardoso Fontes, realizada pela @prefeitura_rio, que assumiu a gestão da unidade federal em dezembro do ano passado. 🏥 Com a reforma, leitos fechados serão reabertos e a capacidade de atendimento ambulatorial vai ser dobrada. Um grande avanço quando falamos de acessibilidade aos serviços de saúde. Em 2008, nós tínhamos 3% de cobertura da atenção primária das clínicas da família. Hoje, esse número já está acima de 70%. Parabéns ao Prefeito @eduardopaes e ao Secretário Municipal de Saúde, @danielsoranz, pela iniciativa! Contem com o nosso mandato para seguir avançando com a saude na nossa cidade. 🚀 | F22: Reels | G22: https://www.instagram.com/p/DFf_LjwOWi2/ | H22: =I22+J22+K22+L22+M22 -> 312 | I22: 257 | J22: 37 | K22: 16 | L22: 0 | M22: 2 | AS22: 45822 | AT22: =I22+J22+K22 -> 310 | AU22: =TEXT(AS22,"mmmm/yyyy") -> junho/2025
A23: PROXIMIDADE | B23: 45689 | C23: =TEXT(B23, "mm/yyyy") -> 02/2025 | D23: Ordenamento | E23: Estivemos hoje na Escola Municipal Pedro Ernesto, na Lagoa, junto com o Prefeito @eduardopaes e o Secretário de Educação @renanferreirinha, para acompanhar o dia de acolhimento das famílias e a entrega dos kits escolares. O evento marcou o início do ano letivo, fortalecendo a integração entre alunos, responsáveis, professores e funcionários. Seguimos acompanhando de perto as ações para garantir uma educação de qualidade na nossa cidade. 📚🔬🚀 | F23: Carrossel de Fotos | G23: https://www.instagram.com/p/DFiKwXhupM4/ | H23: =I23+J23+K23+M23 -> 398 | I23: 361 | J23: 24 | K23: 12 | L23: 0 | M23: 1 | AS23: 45821 | AT23: =I23+J23+K23 -> 397 | AU23: =TEXT(AS23,"mmmm/yyyy") -> junho/2025
A24: PROXIMIDADE | B24: 45690 | C24: =TEXT(B24, "mm/yyyy") -> 02/2025 | D24: Mandato | E24: Almoço de hoje com o quase doutor em Economia @gildovigor que tá vigorando no TCC sobre Segurança Pública no Brasil. Em breve, novidades em conjunto para nossa cidade! | F24: Carrossel de Fotos | G24: https://www.instagram.com/p/DFlZ8H6ywCd/ | H24: =I24+J24+K24+M24 -> 1322 | I24: 1233 | J24: 52 | K24: 27 | L24: 0 | M24: 10 | AS24: 45821 | AT24: =I24+J24+K24 -> 1312 | AU24: =TEXT(AS24,"mmmm/yyyy") -> junho/2025
A25: NOTÍCIA | B25: 45690 | C25: =TEXT(B25, "mm/yyyy") -> 02/2025 | D25: Combate ao Antissemitismo | E25: A FIERJ se solidariza e, ao mesmo tempo, cumprimenta o vereador Flávio Valle pela denúncia ao ato de antissemitismo na Câmara dos Vereadores do Rio de Janeiro. É grave, ofensivo e inaceitável o que ocorreu. Não podemos aceitar intimidações. Estamos junto com Flávio e entendemos que deve haver vigilância e apuração sobre quaisquer atos de violência contra judeus e minorias. | F25: Estático | G25: https://www.instagram.com/p/DFkrDqhukFM/ | H25: =I25+J25+K25+M25 -> 142 | I25: 126 | J25: 11 | K25: 5 | L25: 0 | AS25: 45818 | AT25: =I25+J25+K25 -> 142 | AU25: =TEXT(AS25,"mmmm/yyyy") -> junho/2025
A26: APRESENTAÇÃO | B26: 45691 | C26: =TEXT(B26, "mm/yyyy") -> 02/2025 | D26: Mandato | E26: Iniciando uma nova jornada como aluno do Mestrado em Administração Pública da @fgv.oficial ! Política Pública baseada em dados e evidências!! 📈 | F26: Carrossel de Fotos | G26: https://www.instagram.com/p/DFoO_4cIZlz/ | H26: =I26+J26+K26+M26 -> 677 | I26: 581 | J26: 73 | K26: 18 | L26: 0 | M26: 5 | AS26: 45815 | AT26: =I26+J26+K26 -> 672 | AU26: =TEXT(AS26,"mmmm/yyyy") -> junho/2025
A27: PROBLEMA X SOLUÇÃO | B27: 45692 | C27: =TEXT(B27, "mm/yyyy") -> 02/2025 | D27: Ordenamento | E27: ABANDONO E INSEGURANÇA EM LARANJEIRAS! 🚨 A antiga Churrascaria Gaúcha, na Rua das Laranjeiras, está completamente abandonada: portas arrombadas, lixo, entulho e até indícios de desmanche de fios roubados. Além disso, tem servido de abrigo para pessoas em situação de vulnerabilidade e usuários de drogas na região. Os moradores, claro, estão inseguros e cobrando providências! Acionamos a @prefeitura_rio, que prontamente atendeu ao nosso chamado e enviou a @comlurbcomunica para iniciar a limpeza do local. Mais cedo, estive no local com o Gerente Executivo Local, @yagoazeredo.rio, para acompanhar a situação de perto. Seguimos pressionando por soluções e pela responsabilização dos proprietários do imóvel. Esse abandono não pode continuar! #Laranjeiras #Segurança #Ordenamento #FlávioValleVereador | F27: Reels | G27: https://www.instagram.com/p/DFqSs43O2Rr/ | H27: =I27+J27+K27+L27+M27 -> 666 | I27: 482 | J27: 118 | K27: 63 | L27: 0 | M27: 3 | AS27: 45814 | AT27: =I27+J27+K27 -> 663 | AU27: =TEXT(AS27,"mmmm/yyyy") -> junho/2025
A28: PROXIMIDADE | B28: 45692 | C28: =TEXT(B28, "mm/yyyy") -> 02/2025 | D28: Esporte e Lazer | E28: Meu querido amigo, deputado e secretário de Esportes @rio.guilhermeschleder veio conhecer nosso gabinete na @camarario e aproveitamos para falar das atividades esportivas na orla da cidade, que desde 2022 são regulamentadas pela prefeitura, garantindo boa convivência entre os banhistas e esportistas. Conte com meu apoio no parlamento para defender a bandeira dos esportes na cidade! | F28: Carrossel de Fotos | G28: https://www.instagram.com/p/DFp_g0JMmTF/ | H28: =I28+J28+K28+M28 -> 320 | I28: 282 | J28: 34 | K28: 3 | L28: 0 | M28: 1 | AS28: 45814 | AT28: =I28+J28+K28 -> 319 | AU28: =TEXT(AS28,"mmmm/yyyy") -> junho/2025
A29: NOTÍCIA | B29: 45693 | C29: =TEXT(B29, "mm/yyyy") -> 02/2025 | D29: Combate ao Antissemitismo | E29: 🇧🇷🤝🇮🇱 INOVAÇÃO, EDUCAÇÃO, CULTURA E COMBATE AO ANTISSEMITISMO: UMA PARCERIA HISTÓRICA ENTRE RIO E ISRAEL Hoje demos mais um passo importante para fortalecer a cooperação entre o Rio de Janeiro e o Estado de Israel! Em reunião com o Coordenador de Relações Internacionais da @prefeitura_rio, @pedrofranciscomv, e sua equipe, iniciamos a elaboração do Termo de Cooperação Técnica, que abrirá caminho para o intercâmbio de tecnologias inovadoras, avanços na educação, parcerias culturais e iniciativas de combate ao antissemitismo. Israel é referência mundial em inovação e empreendedorismo, e essa parceria trará oportunidades reais para impulsionar o desenvolvimento da cidade. Além disso, reafirmamos nosso compromisso com políticas públicas que promovam o respeito, a segurança e a inclusão, contribuindo para o desenvolvimento do Rio. 💡🌍✡️ | F29: Carrossel de Fotos | G29: https://www.instagram.com/p/DFs/bXuSRGx/ | H29: =I29+J29+K29+M29 -> 340 | I29: 313 | J29: 17 | K29: 8 | L29: 0 | M29: 2 | AS29: 45813 | AT29: =I29+J29+K29 -> 338 | AU29: =TEXT(AS29,"mmmm/yyyy") -> junho/2025
A30: INFORMAÇÃO | B30: 45695 | C30: =TEXT(B30, "mm/yyyy") -> 02/2025 | D30: Meio Ambiente | E30: O que não te contaram sobre o Jardim de Alah? 🤔🌳 Tão falando por aí que várias árvores serão removidas, mas o que esqueceram de dizer é que mais da metade são espécies invasoras e, no lugar, 300 novas árvores serão plantadas – um aumento de 40% do número atual! 🌱💚 E isso é só o começo! O Jardim de Alah vai passar por uma transformação completa: fim do estacionamento para dar espaço a um solo drenante, parcão com estrutura de verdade pros nossos pets aproveitarem e novas áreas de lazer, como quadras esportivas e ginásio! Chega de abandono e de desinformação! Vamos garantir um Jardim de Alah mais verde, seguro e acessível para todos. Me segue para acompanhar de perto essa mudança! 👀 #JardimdeAlah #Revitalização #FlávioValleVereador | F30: Reels | G30: https://www.instagram.com/p/DFx9gacOY5j/ | H30: =I30+J30+K30+L30+M30 -> 2404 | I30: 1559 | J30: 413 | K30: 394 | L30: 0 | M30: 38 | AS30: 45813 | AT30: =I30+J30+K30 -> 2366 | AU30: =TEXT(AS30,"mmmm/yyyy") -> junho/2025
A31: LIFESTYLE | B31: 45695 | C31: =TEXT(B31, "mm/yyyy") -> 02/2025 | D31: Esporte e Lazer | E31: ⚽🔥 Duelo do século! Gabinete Flávio Valle x Gabinete Pedro Duarte. O placar? 1x1! Mas a rivalidade fica só em campo. Na Câmara, seguimos no mesmo time: trabalhando pelo Rio de Janeiro! 💪🏽🏛️ | F31: Reels | G31: https://www.instagram.com/p/DFwTLJKuNOk/ | H31: =I31+J31+K31+L31+M31 -> 1531 | I31: 1146 | J31: 151 | K31: 220 | L31: 0 | M31: 14 | AS31: 45813 | AT31: =I31+J31+K31 -> 1517 | AU31: =TEXT(AS31,"mmmm/yyyy") -> junho/2025
A32: DENÚNCIA | B32: 45696 | C32: =TEXT(B32, "mm/yyyy") -> 02/2025 | D32: Segurança | E32: Quando fui subprefeito, aprendi que o crack é mais que um problema social ou de saúde, é um problema de segurança pública. Enquanto a prefeitura realiza o papel dela com a Secretaria de Assistência Social e com o programa Seguir Em Frente da Secretaria de Saúde, esse trabalho fica impossível sem a ajuda das forças policiais do estado na identificação e REPRESSÃO DA VENDA DO CRACK. Como pontua o secretário @danielsoranz, “Não adianta prender o pequeno traficante e não identificar a rota do tráfico e das pessoas que estão se beneficiando e ganhando dinheiro com isso. E isso tudo feito ao lado do BPM e da delegacia. É algo para estranhar.” | F32: Carrossel Misto | G32: https://www.instagram.com/p/DFzarqVucdk/ | H32: =I32+J32+K32+M32 -> 944 | I32: 748 | J32: 126 | K32: 59 | L32: 0 | M32: 11 | AS32: 45812 | AT32: =I32+J32+K32 -> 933 | AU32: =TEXT(AS32,"mmmm/yyyy") -> junho/2025
A33: PROBLEMA X SOLUÇÃO | B33: 45697 | C33: =TEXT(B33, "mm/yyyy") -> 02/2025 | D33: Ordenamento | E33: Bike é na ciclovia! 🚲🛣️ Mesmo com a orla fechada para lazer, as bicicletas devem seguir circulando apenas na ciclovia. Muita gente não sabe dessa regra, então estivemos em Ipanema com as equipes da @gel.lagoa.rio e @cetrio.rio , para sensibilizar a população e garantir a segurança de todos! Como vereador, vou seguir trabalhando para melhorar junto com o prefeito @eduardopaes a mobilidade urbana e oferecer novas alternativas de locomoção na nossa cidade. Juntos, vamos construir um trânsito mais seguro e uma cidade mais conectada para todos! | F33: Reels | G33: https://www.instagram.com/p/DF3NjhCyXdA/ | H33: =I33+J33+K33+L33+M33 -> 1927 | I33: 1483 | J33: 227 | K33: 201 | L33: 0 | M33: 16 | AS33: 45811 | AT33: =I33+J33+K33 -> 1911 | AU33: =TEXT(AS33,"mmmm/yyyy") -> junho/2025
A34: CLICKBAIT | B34: 45699 | C34: =TEXT(B34, "mm/yyyy") -> 02/2025 | D34: Combate ao Antissemitismo | E34: Um dos maiores rappers do mundo é nazista. 🚨‼️ Ontem, no Super Bowl, Kanye West gastou 10 milhões de dólares para divulgar uma camisa com uma suástica e o código “HH / 01”, referência à saudação nazista. Isso não é um erro. Isso não é coincidência. O pior? O antissemitismo se tornou um negócio lucrativo. Kanye tem milhões de seguidores, continua sendo exaltado e suas falas de ódio seguem impunes. Eu não vou me calar. Denunciar é combater. Se você também não aceita isso, COMPARTILHE! | F34: Reels | G34: https://www.instagram.com/p/DF6YmI_O6Oe/ | H34: =I34+J34+K34+L34+M34 -> 44202 | I34: 25468 | J34: 1867 | K34: 15935 | L34: 0 | M34: 932 | AS34: 45811 | AT34: =I34+J34+K34 -> 43270 | AU34: =TEXT(AS34,"mmmm/yyyy") -> junho/2025
A35: PROBLEMA X SOLUÇÃO | B35: 45700 | C35: =TEXT(B35, "mm/yyyy") -> 02/2025 | D35: Ordenamento | E35: ⚡ Parece um ninho, né? Mas é furto de energia! 🚨 Recebemos diversas queixas sobre a desordem debaixo do viaduto da Autoestrada Lagoa Barra, em São Conrado. Solicitamos a @Prefeitura_Rio, e o Projeto Rio em Ordem entrou em ação: ordenamento da calçada e fim dos "gatos" de energia! Pra você não levar choque, o Rio precisa de um choque de civilidade! ⚡ #RioEmOrdem #ChoqueDeCivilidade #FlavioValleVereador | F35: Reels | G35: https://www.instagram.com/p/DF/fwGNhJrH/ | H35: =I35+J35+K35+L35+M35 -> 643 | I35: 532 | J35: 83 | K35: 24 | L35: 0 | M35: 4 | AS35: 45810 | AT35: =I35+J35+K35 -> 639 | AU35: =TEXT(AS35,"mmmm/yyyy") -> junho/2025
A36: LIFESTYLE | B36: 45701 | C36: =TEXT(B36, "mm/yyyy") -> 02/2025 | D36: Mandato | E36: Almoço com o presidente do Banco Central Gabriel Galípolo, prefeito @eduardopaes , vice/prefeito @eduardo.cavaliere , deputado @rio.pedropaulo e o secretário de desenvolvimento econômico @osmarcglima discutindo ideias e projetos para a sempre capital do Brasil: claro que to falando do Rio! . . 📸 @bethsantos11 | F36: Carrossel de Fotos | G36: https://www.instagram.com/p/DGBcai3u2SO/ | H36: =I36+J36+K36+M36 -> 561 | I36: 495 | J36: 28 | K36: 32 | L36: 0 | M36: 6 | AS36: 45810 | AT36: =I36+J36+K36 -> 555 | AU36: =TEXT(AS36,"mmmm/yyyy") -> junho/2025
A37: INFORMAÇÃO | B37: 45702 | C37: =TEXT(B37, "mm/yyyy") -> 02/2025 | D37: Economia | E37: O caminho inteligente para o crescimento sustentável integra desenvolvimento econômico, preservação ambiental e bem/estar social. Por isso, o Prefeito @eduardopaes vem estimulando o avanço da nossa cidade através da redução de impostos nas áreas de tecnologia, ativos verdes e finanças! 🚀 💚 Quer entender melhor essa história? Clique no link da bio e leia o artigo na íntegra! 🔗 | F37: Carrossel Estático | G37: https://www.instagram.com/p/DGDnqsIu1AZ/ | H37: =I37+J37+K37+M37 -> 122 | I37: 88 | J37: 17 | K37: 17 | L37: 0 | M37: 0 | AS37: 45808 | AT37: =I37+J37+K37 -> 122 | AU37: =TEXT(AS37,"mmmm/yyyy") -> maio/2025
A38: LIFESTYLE | B38: 45703 | C38: =TEXT(B38, "mm/yyyy") -> 02/2025 | D38: Esporte e Lazer | E38: 🚨 Lei Maria da Moda | F38: Carrossel de Fotos | G38: https://www.instagram.com/p/DGG/txtSSaH/ | H38: =I38+J38+K38+M38 -> 674 | I38: 613 | J38: 56 | K38: 5 | L38: 0 | AS38: 45807 | AT38: =I38+J38+K38 -> 674 | AU38: =TEXT(AS38,"mmmm/yyyy") -> maio/2025
A39: INFORMAÇÃO | B39: 45705 | C39: =TEXT(B39, "mm/yyyy") -> 02/2025 | D39: Mandato | E39: Temporada de sessão plenária oficialmente aberta! 🏛️🚀 Meu compromisso é buscar soluções, propor avanços e trabalhar por um Rio mais desenvolvido. Obrigado aos 18.613 cariocas que acreditaram no nosso projeto de um Rio melhor. 💙 Hoje, com a presença do prefeito @eduardopaes e do vice/prefeito @eduardo.cavaliere , que apresentaram o Projeto de Lei para a criação da Força Municipal de Segurança, iniciamos mais um período de debates e decisões que impactam diretamente a vida dos cariocas. Um grande passo para um Rio mais seguro e civilizado. Que seja um ano de muito trabalho e conquistas para o Rio de Janeiro, futura capital honorária do Brasil! Vamos juntos lutar por nossa cidade maravilhosa! #FlávioValleVereador #CâmaraMunicipal #riodejaneiro | F39: Carrossel de Fotos | G39: https://www.instagram.com/p/DGL7DRDOVHt/ | H39: =I39+J39+K39+L39+M39 -> 1172 | I39: 1025 | J39: 106 | K39: 39 | L39: 0 | M39: 2 | AS39: 45807 | AT39: =I39+J39+K39 -> 1170 | AU39: =TEXT(AS39,"mmmm/yyyy") -> maio/2025
A40: NOTÍCIA | B40: 45707 | C40: =TEXT(B40, "mm/yyyy") -> 02/2025 | D40: Mandato | E40: É OFICIAL! Fui escolhido para duas missões estratégicas na @camarario: ✅ Presidir a Comissão de Turismo e ✅ integrar a Comissão de Finanças, Orçamento e Fiscalização Financeira. Quando fui Subprefeito da zona mais turística da cidade, aprendi o quanto o turismo impulsiona nossa economia e enriquece nossa cultura. À frente da comissão, quero fortalecer políticas públicas que valorizem esse potencial e gerem novas oportunidades para os cariocas! Já como economista e mestrando em Administração Pública, entendo que uma gestão fiscal bem/feita é o que garante investimentos e melhorias para a cidade, cuidando de quem mais precisa da nossa assistência: a população. Agora, é arregaçar as mangas e trabalhar para seguir transformando o Rio, entendendo a importância do trabalho integrado entre o legislativo e executivo, com a gestão @eduardopaes! Vamos juntos enfrentar esse novo desafio! 💙 | F40: Carrossel Estático | G40: https://www.instagram.com/p/DGQaRWSucq3/ | H40: =I40+J40+K40+L40+M40 -> 739 | I40: 597 | J40: 109 | K40: 30 | L40: 0 | M40: 3 | AS40: 45806 | AT40: =I40+J40+K40 -> 736 | AU40: =TEXT(AS40,"mmmm/yyyy") -> maio/2025
A41: APRESENTAÇÃO | B41: 45707 | C41: =TEXT(B41, "mm/yyyy") -> 02/2025 | D41: Mandato | E41: 📢 O primeiro discurso na @camara.rio como vereador a gente nunca esquece! Reafirmei meu compromisso com uma cidade de contas equilibradas, fundamental para avançarmos em políticas públicas que melhorem a vida de quem mais precisa. Graças ao trabalho do prefeito @eduardopaes, o Rio superou o déficit deixado pelo governo anterior e voltou a investir no que é essencial. A Câmara é um espaço de ideias, e todas devem ser respeitadas para construirmos soluções reais. Como único representante da comunidade judaica, propus a criação da Frente Parlamentar contra o Antissemitismo, reforçando o compromisso com o respeito e a diversidade. Seguimos juntos por um Rio melhor! 💙 #FlávioValleVereador | F41: Reels | G41: https://www.instagram.com/p/DGO_rI8OuQc/ | H41: =I41+J41+K41+L41+M41 -> 612 | I41: 510 | J41: 83 | K41: 16 | L41: 0 | M41: 3 | AS41: 45806 | AT41: =I41+J41+K41 -> 609 | AU41: =TEXT(AS41,"mmmm/yyyy") -> maio/2025
A42: INFORMAÇÃO | B42: 45708 | C42: =TEXT(B42, "mm/yyyy") -> 02/2025 | D42: Combate ao Antissemitismo | E42: Hoje, na Câmara Municipal, subi à tribuna com o coração pesado. A confirmação do assassinato brutal da família Bibas, sequestrada no ataque de 07 de outubro, escancara a crueldade desses ataques. O massacre daquele dia foi o pior atentado contra judeus desde o Holocausto. Por isso, a criação da Frente Parlamentar de Combate ao Antissemitismo é um compromisso com a memória das vítimas e com um futuro sem ódio. Além disso, submeti um Projeto de Lei para instituir o Dia Municipal de Combate ao Antissemitismo em 07 de outubro, uma data que jamais poderá ser esquecida. A memória das vítimas precisa ser honrada com ações concretas contra o ódio e a intolerância. Am Israel Chai! 💙🇮🇱 | F42: Reels | G42: https://www.instagram.com/p/DGT/YiLOYvg/ | H42: =I42+J42+K42+L42+M42 -> 1099 | I42: 919 | J42: 89 | K42: 85 | L42: 0 | M42: 6 | AS42: 45805 | AT42: =I42+J42+K42 -> 1093 | AU42: =TEXT(AS42,"mmmm/yyyy") -> maio/2025
A43: PROBLEMA X SOLUÇÃO | B43: 45709 | C43: =TEXT(B43, "mm/yyyy") -> 02/2025 | D43: Ordenamento | E43: 🚨 Pinga/pinga de ar/condicionado na rua? Isso é proibido! A lei Nº 2749/1999 obriga o uso de calhas para evitar que a água caia na calçada. Nosso gabinete recebeu a demanda e já acionou a Gerência Executiva Local para notificar esse prédio e resolver o problema. Se cada um fizer a sua parte, a cidade funciona melhor. Conhece algum prédio com o mesmo problema? Manda pra gente no WhatsApp! 🚀#FlávioValleVereador | F43: Reels | G43: https://www.instagram.com/p/DGV6A6yuH05/ | H43: =I43+J43+K43+L43+M43 -> 1686 | I43: 1210 | J43: 229 | K43: 201 | L43: 0 | M43: 46 | AS43: 45804 | AT43: =I43+J43+K43 -> 1640 | AU43: =TEXT(AS43,"mmmm/yyyy") -> maio/2025
A44: DENÚNCIA | B44: 45709 | C44: =TEXT(B44, "mm/yyyy") -> 02/2025 | D44: Meio Ambiente | E44: Não consigo me conformar com a falta de civilidade dos sujismundos que não fazem o mínimo esforço para deixar a cidade limpa. Mesmo com o exército laranja da @comlurbcomunica limpando as praias todos os dias e com os investimentos do prefeito @eduardopaes em novos maquinários de limpeza, os porcalhões parecem nem se importar em sujar o lugar que ELES mesmos frequentam. Vamos solicitar que a Prefeitura intensifique a fiscalização do Lixo Zero e rever os valores da multa para quem joga lixo no espaço público. Se mesmo com a lixeira ao lado, vemos cenas como essa, infelizmente só a dor (no bolso) vai gerar a compreensão. / fim do desabafo. | F44: Estático | G44: https://www.instagram.com/p/DGVciEfOIrf/ | H44: =I44+J44+K44+L44+M44 -> 683 | I44: 512 | J44: 139 | K44: 27 | L44: 0 | M44: 5 | AS44: 45804 | AT44: =I44+J44+K44 -> 678 | AU44: =TEXT(AS44,"mmmm/yyyy") -> maio/2025
A45: TREND | B45: 45710 | C45: =TEXT(B45, "mm/yyyy") -> 02/2025 | D45: Esporte e Lazer | E45: Esse Dudu tá diferente! 👀 Uma pequena homenagem pro maior prefeito que a cidade maravilhosa já viu! Alô, @eduardopaes! 💙 O carnaval já tá tomando conta do Rio, mas a gente não pode esquecer que essa cidade é a nossa casa. Bora curtir com responsabilidade, cuidar das ruas e fazer dessa festa a mais bonita de todas! Conto com vocês! 🎉🎶 | F45: Reels | G45: https://www.instagram.com/p/DGY0sTGSZvT/ | H45: =I45+J45+K45+L45+M45 -> 1317 | I45: 1063 | J45: 102 | K45: 139 | L45: 0 | M45: 13 | AS45: 45802 | AT45: =I45+J45+K45 -> 1304 | AU45: =TEXT(AS45,"mmmm/yyyy") -> maio/2025
A46: PROXIMIDADE | B46: 45710 | C46: =TEXT(B46, "mm/yyyy") -> 02/2025 | D46: Esporte e Lazer | E46: Vai Duduuuuu! 💉💉🌇🌇 Homenagem ao melhor prefeito que essa cidade já teve! @eduardopaes | F46: Carrossel de Fotos | G46: https://www.instagram.com/p/DGYccgHu5HD/ | H46: =I46+J46+K46+L46+M46 -> 2080 | I46: 1792 | J46: 72 | K46: 201 | L46: 0 | M46: 15 | AS46: 45800 | AT46: =I46+J46+K46 -> 2065 | AU46: =TEXT(AS46,"mmmm/yyyy") -> maio/2025
A47: TREND | B47: 45710 | C47: =TEXT(B47, "mm/yyyy") -> 02/2025 | D47: Mandato | E47: Primeiro você começa, depois você melhora! 🚀✨ Ninguém nasce pronto, mas com trabalho, estudo e experiência, a gente consegue chegar lá. Cada passo da nossa trajetória foi essencial para estarmos aqui hoje, na Câmara Municipal do Rio de Janeiro! 🏛️ #FlávioValleVereador | F47: Carrossel Misto | G47: https://www.instagram.com/p/DGYH3CJOBSm/ | H47: =I47+J47+K47+L47+M47 -> 1004 | I47: 920 | J47: 50 | K47: 27 | L47: 0 | M47: 7 | AS47: 45800 | AT47: =I47+J47+K47 -> 997 | AU47: =TEXT(AS47,"mmmm/yyyy") -> maio/2025
A48: PROXIMIDADE | B48: 45710 | C48: =TEXT(B48, "mm/yyyy") -> 02/2025 | D48: Esporte e Lazer | E48: Abrindo a programação de Carnaval do @terreiraodosamba.oficial reencontrando todos os barraqueiros que carregam a história do carnaval do Rio de Janeiro! Também teve um tamborim junto com o presidente da Riotur @fellows.rio e @miltoncunhaoficial | F48: Carrossel de Fotos | G48: https://www.instagram.com/p/DGW2/8AuqaU/ | H48: =I48+J48+K48+L48+M48 -> 364 | I48: 349 | J48: 10 | K48: 4 | L48: 0 | M48: 1 | AS48: 45800 | AT48: =I48+J48+K48 -> 363 | AU48: =TEXT(AS48,"mmmm/yyyy") -> maio/2025
A49: LIFESTYLE | B49: 45712 | C49: =TEXT(B49, "mm/yyyy") -> 02/2025 | D49: Mandato | E49: P.O.V.: Começando mais uma semana de trabalho no GVFV! | F49: Estático | G49: https://www.instagram.com/p/DGdh8FuOb9f/ | H49: =I49+J49+K49+L49+M49 -> 219 | I49: 205 | J49: 6 | K49: 6 | L49: 0 | M49: 2 | AS49: 45799 | AT49: =I49+J49+K49 -> 217 | AU49: =TEXT(AS49,"mmmm/yyyy") -> maio/2025
A50: DENÚNCIA | B50: 45714 | C50: =TEXT(B50, "mm/yyyy") -> 02/2025 | D50: Segurança | E50: O Rio precisa de uma política de segurança mais eficiente! 🚨 Hoje, só em Copacabana, existem nove projetos diferentes de segurança, mas sem coordenação entre si. Enquanto isso, 90% dos crimes de baixa periculosidade estão concentrados em apenas 5% da cidade. Para preencher essas lacunas e atuar de forma estratégica, o Prefeito @eduardopaes propôs a criação da Força de Segurança Municipal. Na sessão de ontem, demonstrei mais uma vez meu apoio à essa iniciativa, que vai garantir mais segurança e proteção para todos os cariocas. 🚔🚀 | F50: Reels | G50: https://www.instagram.com/p/DGiPAERuL00/ | H50: =I50+J50+K50+L50+M50 -> 393 | I50: 303 | J50: 67 | K50: 16 | L50: 1 | M50: 6 | AS50: 45799 | AT50: =I50+J50+K50 -> 386 | AU50: =TEXT(AS50,"mmmm/yyyy") -> maio/2025
A51: PROXIMIDADE | B51: 45715 | C51: =TEXT(B51, "mm/yyyy") -> 02/2025 | D51: Turismo | E51: Hoje visitei a Cidade do Samba com o prefeito @eduardopaes, o vice/prefeito @eduardocavaliere e o presidente da Câmara @carlo_caiado, para acompanhar os últimos preparativos das escolas para o maior espetáculo da Terra: o Carnaval! 🎉🎊 Além da festa, esse é um dos eventos mais importantes para o turismo e a economia do Rio. Como presidente da Comissão de Turismo da @camarario, meu compromisso é fortalecer ainda mais esse setor, impulsionando empregos, renda e oportunidades para a cidade. Vamos juntos! 💙 #FlavioValleVereador | F51: Carrossel de Fotos | G51: https://www.instagram.com/p/DGjolyhOFvf/ | H51: =I51+J51+K51+M52+M51 -> 515 | I51: 478 | J51: 15 | K51: 9 | L51: 0 | M51: 3 | P51: 45658 | Q51: =IF(ISBLANK(COUNTIF(C:C,C2)),"",COUNTIF(C:C,C2)) -> 21 | AS51: 45798 | AT51: =I51+J51+K51 -> 502 | AU51: =TEXT(AS51,"mmmm/yyyy") -> maio/2025
A52: PROXIMIDADE | B52: 45717 | C52: =TEXT(B52, "mm/yyyy") -> 03/2025 | D52: Conservação | E52: Nada melhor do que trabalhar com o que se ama e, Rio, eu te amo demais! 460 anos sendo a melhor cidade do mundo! Parabéns, Rio! Conta comigo pra cuidar de você. 💙🎉 | F52: Reels | G52: https://www.instagram.com/p/DGqTaZ2O745/ | H52: =I52+J52+K52+L52+M52 -> 385 | I52: 292 | J52: 28 | K52: 55 | L52: 0 | M52: 10 | P52: 45689 | Q52: =IF(ISBLANK(COUNTIF(C:C,C27)),"",COUNTIF(C:C,C27)) -> 29 | AS52: 45798 | AT52: =I52+J52+K52 -> 375 | AU52: =TEXT(AS52,"mmmm/yyyy") -> maio/2025
